Workbook
Name Slicer_State: #N/A
Name Slicer_State1: #N/A
Name Slicer_State2: #N/A
Name Slicer_State3: #N/A

Sheet Names
A1: Project
A2: Name1 | B2: Bleona Krasniqi Section 7
A3: Name2
A4: Name3
A5: Name4
A6: Group Number

Sheet Raw_Data_CodesPredictions
A1: Model 1 | C1: =IFERROR(VLOOKUP(C$10,'Models training data'!$AG$22:$AH$37,2,FALSE),0) -> 110221.95 | D1: =IFERROR(VLOOKUP(D$10,'Models training data'!$AG$22:$AH$37,2,FALSE),0) -> 0 | E1: =IFERROR(VLOOKUP(E$10,'Models training data'!$AG$22:$AH$37,2,FALSE),0) -> 0 | F1: =IFERROR(VLOOKUP(F$10,'Models training data'!$AG$22:$AH$37,2,FALSE),0) -> 0 | G1: =IFERROR(VLOOKUP(G$10,'Models training data'!$AG$22:$AH$37,2,FALSE),0) -> 0 | H1: =IFERROR(VLOOKUP(H$10,'Models training data'!$AG$22:$AH$37,2,FALSE),0) -> 0 | I1: =IFERROR(VLOOKUP(I$10,'Models training data'!$AG$22:$AH$37,2,FALSE),0) -> 0 | J1: =IFERROR(VLOOKUP(J$10,'Models training data'!$AG$22:$AH$37,2,FALSE),0) -> 0 | ... AQ1: =IFERROR(VLOOKUP(AQ$10,'Models training data'!$AG$22:$AH$37,2,FALSE),0) -> 0
A2: Model 2 | C2: =IFERROR(VLOOKUP(C$10,'Models training data'!$AW$23:$AX$41,2,FALSE),0) -> 101870.91 | D2: =IFERROR(VLOOKUP(D$10,'Models training data'!$AW$23:$AX$41,2,FALSE),0) -> 0 | E2: =IFERROR(VLOOKUP(E$10,'Models training data'!$AW$23:$AX$41,2,FALSE),0) -> 0 | F2: =IFERROR(VLOOKUP(F$10,'Models training data'!$AW$23:$AX$41,2,FALSE),0) -> 0 | G2: =IFERROR(VLOOKUP(G$10,'Models training data'!$AW$23:$AX$41,2,FALSE),0) -> 0 | H2: =IFERROR(VLOOKUP(H$10,'Models training data'!$AW$23:$AX$41,2,FALSE),0) -> 0 | I2: =IFERROR(VLOOKUP(I$10,'Models training data'!$AW$23:$AX$41,2,FALSE),0) -> 0 | J2: =IFERROR(VLOOKUP(J$10,'Models training data'!$AW$23:$AX$41,2,FALSE),0) -> 0 | ... AQ2: =IFERROR(VLOOKUP(AQ$10,'Models training data'!$AW$23:$AX$41,2,FALSE),0) -> 0
A3: Model 3 | C3: =IFERROR(VLOOKUP(C$10,'Models training data'!$BN$23:$BO$41,2,FALSE),0) -> 11.507982 | D3: =IFERROR(VLOOKUP(D$10,'Models training data'!$BN$23:$BO$41,2,FALSE),0) -> 0 | E3: =IFERROR(VLOOKUP(E$10,'Models training data'!$BN$23:$BO$41,2,FALSE),0) -> 0 | F3: =IFERROR(VLOOKUP(F$10,'Models training data'!$BN$23:$BO$41,2,FALSE),0) -> 0 | G3: =IFERROR(VLOOKUP(G$10,'Models training data'!$BN$23:$BO$41,2,FALSE),0) -> 0 | H3: =IFERROR(VLOOKUP(H$10,'Models training data'!$BN$23:$BO$41,2,FALSE),0) -> 0 | I3: =IFERROR(VLOOKUP(I$10,'Models training data'!$BN$23:$BO$41,2,FALSE),0) -> 0 | J3: =IFERROR(VLOOKUP(J$10,'Models training data'!$BN$23:$BO$41,2,FALSE),0) -> 0 | ... AQ3: =IFERROR(VLOOKUP(AQ$10,'Models training data'!$BN$23:$BO$41,2,FALSE),0) -> 0
A4: Model 4 | C4: =IFERROR(VLOOKUP(C$10,'Models training data'!$CD$23:$CE$39,2,FALSE),0) -> 99191.043 | D4: =IFERROR(VLOOKUP(D$10,'Models training data'!$CD$23:$CE$39,2,FALSE),0) -> 0 | E4: =IFERROR(VLOOKUP(E$10,'Models training data'!$CD$23:$CE$39,2,FALSE),0) -> 0 | F4: =IFERROR(VLOOKUP(F$10,'Models training data'!$CD$23:$CE$39,2,FALSE),0) -> 0 | G4: =IFERROR(VLOOKUP(G$10,'Models training data'!$CD$23:$CE$39,2,FALSE),0) -> 0 | H4: =IFERROR(VLOOKUP(H$10,'Models training data'!$CD$23:$CE$39,2,FALSE),0) -> 0 | I4: =IFERROR(VLOOKUP(I$10,'Models training data'!$CD$23:$CE$39,2,FALSE),0) -> 0 | J4: =IFERROR(VLOOKUP(J$10,'Models training data'!$CD$23:$CE$39,2,FALSE),0) -> 0 | ... AQ4: =IFERROR(VLOOKUP(AQ$10,'Models training data'!$CD$23:$CE$39,2,FALSE),0) -> 0
A5: Model 5 | C5: =IFERROR(VLOOKUP(C$10,'Models training data'!$CT$23:$CU$39,2,FALSE),0) -> 11.492466 | D5: =IFERROR(VLOOKUP(D$10,'Models training data'!$CT$23:$CU$39,2,FALSE),0) -> 0 | E5: =IFERROR(VLOOKUP(E$10,'Models training data'!$CT$23:$CU$39,2,FALSE),0) -> 0 | F5: =IFERROR(VLOOKUP(F$10,'Models training data'!$CT$23:$CU$39,2,FALSE),0) -> 0 | G5: =IFERROR(VLOOKUP(G$10,'Models training data'!$CT$23:$CU$39,2,FALSE),0) -> 0 | H5: =IFERROR(VLOOKUP(H$10,'Models training data'!$CT$23:$CU$39,2,FALSE),0) -> 0 | I5: =IFERROR(VLOOKUP(I$10,'Models training data'!$CT$23:$CU$39,2,FALSE),0) -> 0 | J5: =IFERROR(VLOOKUP(J$10,'Models training data'!$CT$23:$CU$39,2,FALSE),0) -> 0 | ... AQ5: =IFERROR(VLOOKUP(AQ$10,'Models training data'!$CT$23:$CU$39,2,FALSE),0) -> 0
A6: Model 6 | C6: =IFERROR(VLOOKUP(C$10,'Models training data'!$DJ$23:$DK$38,2,FALSE),0) -> 101555.06 | D6: =IFERROR(VLOOKUP(D$10,'Models training data'!$DJ$23:$DK$38,2,FALSE),0) -> 0 | E6: =IFERROR(VLOOKUP(E$10,'Models training data'!$DJ$23:$DK$38,2,FALSE),0) -> 0 | F6: =IFERROR(VLOOKUP(F$10,'Models training data'!$DJ$23:$DK$38,2,FALSE),0) -> 0 | G6: =IFERROR(VLOOKUP(G$10,'Models training data'!$DJ$23:$DK$38,2,FALSE),0) -> 0 | H6: =IFERROR(VLOOKUP(H$10,'Models training data'!$DJ$23:$DK$38,2,FALSE),0) -> 0 | I6: =IFERROR(VLOOKUP(I$10,'Models training data'!$DJ$23:$DK$38,2,FALSE),0) -> 0 | J6: =IFERROR(VLOOKUP(J$10,'Models training data'!$DJ$23:$DK$38,2,FALSE),0) -> 0 | ... AQ6: =IFERROR(VLOOKUP(AQ$10,'Models training data'!$DJ$23:$DK$38,2,FALSE),0) -> 0
A7: Model 7 | C7: =IFERROR(VLOOKUP(C$10,'Models training data'!$DZ$23:$EA$38,2,FALSE),0) -> 11.515151 | D7: =IFERROR(VLOOKUP(D$10,'Models training data'!$DZ$23:$EA$38,2,FALSE),0) -> 0 | E7: =IFERROR(VLOOKUP(E$10,'Models training data'!$DZ$23:$EA$38,2,FALSE),0) -> 0 | F7: =IFERROR(VLOOKUP(F$10,'Models training data'!$DZ$23:$EA$38,2,FALSE),0) -> 0 | G7: =IFERROR(VLOOKUP(G$10,'Models training data'!$DZ$23:$EA$38,2,FALSE),0) -> 0 | H7: =IFERROR(VLOOKUP(H$10,'Models training data'!$DZ$23:$EA$38,2,FALSE),0) -> 0 | I7: =IFERROR(VLOOKUP(I$10,'Models training data'!$DZ$23:$EA$38,2,FALSE),0) -> 0 | J7: =IFERROR(VLOOKUP(J$10,'Models training data'!$DZ$23:$EA$38,2,FALSE),0) -> 0 | ... AQ7: =IFERROR(VLOOKUP(AQ$10,'Models training data'!$DZ$23:$EA$38,2,FALSE),0) -> 0
A8: Model 8 | C8: =IFERROR(VLOOKUP(C$10,'Models training data'!$EP$23:$EQ$36,2,FALSE),0) -> 11.319305 | D8: =IFERROR(VLOOKUP(D$10,'Models training data'!$EP$23:$EQ$36,2,FALSE),0) -> 0 | E8: =IFERROR(VLOOKUP(E$10,'Models training data'!$EP$23:$EQ$36,2,FALSE),0) -> 0 | F8: =IFERROR(VLOOKUP(F$10,'Models training data'!$EP$23:$EQ$36,2,FALSE),0) -> 0 | G8: =IFERROR(VLOOKUP(G$10,'Models training data'!$EP$23:$EQ$36,2,FALSE),0) -> 0 | H8: =IFERROR(VLOOKUP(H$10,'Models training data'!$EP$23:$EQ$36,2,FALSE),0) -> 0 | I8: =IFERROR(VLOOKUP(I$10,'Models training data'!$EP$23:$EQ$36,2,FALSE),0) -> 0 | J8: =IFERROR(VLOOKUP(J$10,'Models training data'!$EP$23:$EQ$36,2,FALSE),0) -> 0 | ... AQ8: =IFERROR(VLOOKUP(AQ$10,'Models training data'!$EP$23:$EQ$36,2,FALSE),0) -> -0.084641088
A9: Model 9 | C9: =IFERROR(VLOOKUP(C$10,'Models training data'!FF23:FG38,2,FALSE),0) -> 9.8805996 | D9: =IFERROR(VLOOKUP(D$10,'Models training data'!$FF$23:$FG$40,2,FALSE),0) -> 0 | E9: =IFERROR(VLOOKUP(E$10,'Models training data'!$FF$23:$FG$40,2,FALSE),0) -> 0 | F9: =IFERROR(VLOOKUP(F$10,'Models training data'!$FF$23:$FG$40,2,FALSE),0) -> 0 | G9: =IFERROR(VLOOKUP(G$10,'Models training data'!$FF$23:$FG$40,2,FALSE),0) -> 0 | H9: =IFERROR(VLOOKUP(H$10,'Models training data'!$FF$23:$FG$40,2,FALSE),0) -> 0 | I9: =IFERROR(VLOOKUP(I$10,'Models training data'!$FF$23:$FG$40,2,FALSE),0) -> 0 | J9: =IFERROR(VLOOKUP(J$10,'Models training data'!$FF$23:$FG$40,2,FALSE),0) -> 0 | K9: =IFERROR(VLOOKUP(K$10,'Models training data'!$FF$23:$FG$40,2,FALSE),0) -> 0.00015554873 | ... AA9: =IFERROR(VLOOKUP(AA$10,'Models training data'!$FF$23:$FG$40,2,FALSE),0) -> 0 | AB9: =IFERROR(VLOOKUP(AB$10,'Models training data'!$FF$22:$FG$37,2,FALSE),0) -> -0.023518021 | AC9: =IFERROR(VLOOKUP(AC$10,'Models training data'!$FF$23:$FG$40,2,FALSE),0) -> -0.010830567 | AD9: =IFERROR(VLOOKUP(AD$10,'Models training data'!$FF$23:$FG$40,2,FALSE),0) -> 0.11906675 | AE9: =IFERROR(VLOOKUP(AE$10,'Models training data'!$FF$23:$FG$40,2,FALSE),0) -> 0.12323027 | AF9: =IFERROR(VLOOKUP(AF$10,'Models training data'!$FF$23:$FG$40,2,FALSE),0) -> 0.1630314 | AG9: =IFERROR(VLOOKUP(AG$10,'Models training data'!$FF$23:$FG$40,2,FALSE),0) -> 0 | AH9: =IFERROR(VLOOKUP(AH$10,'Models training data'!$FF$23:$FG$40,2,FALSE),0) -> 0 | AI9: =IFERROR(VLOOKUP(AI$10,'Models training data'!$FF$23:$FG$40,2,FALSE),0) -> 0 | AJ9: =IFERROR(VLOOKUP(AJ$10,'Models training data'!$FF$23:$FG$40,2,FALSE),0) -> 0 | ... AQ9: =IFERROR(VLOOKUP(AQ$10,'Models training data'!$FF$23:$FG$40,2,FALSE),0) -> -0.016895223
A10: Var | C10: Intercept | K10: Sum of count | L10: Sum of count^2 | M10: Sum of ln_count | N10: train | O10: month | P10: Sum of month1 | Q10: Sum of month 2 | R10: Sum of month 3 | S10: Sum of month 4 | T10: Sum of month 5 | U10: Sum of month 6 | V10: Sum of month 7 | W10: Sum of month 8 | X10: Sum of month 9 | Y10: Sum of month 10 | Z10: Sum of month 11 | AA10: Sum of month 12 | AB10: Sum of dum_dl | AC10: Sum of dum_md | AD10: Sum of dum_nj | AE10: Sum of dum_ny | AF10: Sum of dum_pa | AG10: Sum of TV_spend2 | AH10: Sum of Radio_spend2 | AI10: Sum of Youtube_Spend2 | AJ10: Sum of Facebook_Spend_ | AL10: Sum of ln_tv_spend+20%avg | AM10: Sum of ln_radio_spend+20%avg | AN10: Sum of ln_youtube_spend+20%avg | AO10: Sum of ln_facebook_spend+20%avg | AP10: Sum of momth_1_2_3_4_5 | AQ10: Sum of month_6_9_10_11_12
P13: 1 | Q13: 2 | R13: 3 | S13: 4 | T13: 5 | U13: 6 | V13: 7 | W13: 8 | X13: 9 | Y13: 10 | Z13: 11 | AA13: 12 | AB13: DL | AC13: MD | AD13: NJ | AE13: NY | AF13: PA
B14: State | C14: Date | D14: TV_Spend | E14: Radio_Spend | F14: YouTube_spend | G14: =CONCATENATE("Facebook_spend_",Names!$B$6) -> Facebook_spend_ | H14: sales | I14: Total Spend | J14: Year | K14: count | L14: count^2 | M14: ln_count | N14: train | O14: month | P14: month1 | Q14: month 2 | R14: month 3 | S14: month 4 | T14: month 5 | U14: month 6 | V14: month7 | W14: month 8 | X14: month 9 | Y14: month 10 | Z14: month 11 | AA14: month 12 | AB14: dum_dl | AC14: dum_md | AD14: dum_nj | AE14: dum_ny | AF14: dum_pa | AG14: sum of TV_spend | AH14: Sum of Radio_spend | AI14: Sum of Youtube_Spend | AJ14: Sum of Facebook_Spend | AK14: ln_sales | AL14: ln_tv_spend+20%avg | AM14: ln_radio_spend+20%avg | AN14: ln_youtube_spend+20%avg | AO14: ln_facebook_spend+20%avg | AP14: momth_1_2_3_4_5 | AQ14: month_6_9_10_11_12 | AR14: Pred_1 | AS14: Pred_2 | AT14: Pred_3 | AU14: Pred_4 | AV14: Pred_5 | AW14: Pred_6 | AX14: Pred_7 | AY14: Pred_8 | AZ14: Pred_9
B15: NJ | C15: 44562 | D15: 2025 | E15: 400 | F15: 200 | G15: 123.492 | H15: 94403.31 | I15: =SUM(D15:G15) -> 2748.492 | J15: =YEAR(C15) -> 2022 | K15: =IF(B15=B14,K14+1,1) -> 1 | L15: =K15^2 -> 1 | M15: =LN(L15) -> 0 | N15: =IF(K15<127,1,0) -> 1 | O15: =MONTH(C15) -> 1 | P15: =IF($O15=P$13,1,0) -> 1 | Q15: =IF($O15=Q$13,1,0) -> 0 | R15: =IF($O15=R$13,1,0) -> 0 | S15: =IF($O15=S$13,1,0) -> 0 | T15: =IF($O15=T$13,1,0) -> 0 | U15: =IF($O15=U$13,1,0) -> 0 | V15: =IF($O15=V$13,1,0) -> 0 | W15: =IF($O15=W$13,1,0) -> 0 | ... AA15: =IF($O15=AA$13,1,0) -> 0 | AB15: =IF($B15=AB$13,1,0) -> 0 | AC15: =IF($B15=AC$13,1,0) -> 0 | AD15: =IF($B15=AD$13,1,0) -> 1 | AE15: =IF($B15=AE$13,1,0) -> 0 | AF15: =IF($B15=AF$13,1,0) -> 0 | AG15: 2025 | AH15: 400 | AI15: 200 | AJ15: 123.492 | AK15: =LN(H15) -> 11.455331 | AL15: =LN(D15+'Models training data'!$Y$4) -> 7.7476861 | AM15: =LN(E15+'Models training data'!$Y$5) -> 6.1420634 | AN15: =LN(F15+'Models training data'!$Y$6) -> 5.5028019 | AO15: =LN(G15+'Models training data'!$Y$7) -> 5.1538431 | AP15: =V15+W15+X15+Y15+Z15 -> 0 | AQ15: =AA15+AC15+AD15+AE15+AF15 -> 1 | AR15: =$C$1+SUMPRODUCT($K$1:$AQ$1,K15:AQ15) -> 86392.099 | AS15: =$C$2+SUMPRODUCT($K$2:$AQ$2,K15:AQ15) -> 94935.696 | AT15: =$C$3+SUMPRODUCT($K$3:$AQ$3,K15:AQ15) -> 11.450218 | AU15: =$C$4+SUMPRODUCT($K$4:$AQ$4,K15:AQ15) -> 96041.204 | AV15: =$C$5+SUMPRODUCT($K$5:$AQ$5,K15:AQ15) -> 11.466226 | AW15: =$C$6+SUMPRODUCT($K$6:$AQ$6,K15:AQ15) -> 98126.677 | AX15: =$C$7+SUMPRODUCT($K$7:$AQ$7,K15:AQ15) -> 11.487945 | AY15: =$C$8+SUMPRODUCT($K$8:$AQ$8,K15:AQ15) -> 11.474839 | AZ15: =$C$9+SUMPRODUCT($K$9:$AQ$9,K15:AQ15) -> 11.450588
B16: =B15 -> NJ | C16: 44569 | D16: 2055.375 | E16: 410 | F16: 209 | G16: 152.75714 | H16: 96073.235 | I16: =SUM(D16:G16) -> 2827.1321 | J16: =YEAR(C16) -> 2022 | K16: =IF(B16=B15,K15+1,1) -> 2 | L16: =K16^2 -> 4 | M16: =LN(L16) -> 1.3862944 | N16: =IF(K16<127,1,0) -> 1 | O16: =MONTH(C16) -> 1 | P16: =IF($O16=P$13,1,0) -> 1 | Q16: =IF($O16=Q$13,1,0) -> 0 | R16: =IF($O16=R$13,1,0) -> 0 | S16: =IF($O16=S$13,1,0) -> 0 | T16: =IF($O16=T$13,1,0) -> 0 | U16: =IF($O16=U$13,1,0) -> 0 | V16: =IF($O16=V$13,1,0) -> 0 | W16: =IF($O16=W$13,1,0) -> 0 | ... AA16: =IF($O16=AA$13,1,0) -> 0 | AB16: =IF($B16=AB$13,1,0) -> 0 | AC16: =IF($B16=AC$13,1,0) -> 0 | AD16: =IF($B16=AD$13,1,0) -> 1 | AE16: =IF($B16=AE$13,1,0) -> 0 | AF16: =IF($B16=AF$13,1,0) -> 0 | AG16: 2055.375 | AH16: 410 | AI16: 209 | AJ16: 152.75714 | AK16: =LN(H16) -> 11.472866 | AL16: =LN(D16+'Models training data'!$Y$4) -> 7.760715 | AM16: =LN(E16+'Models training data'!$Y$5) -> 6.1633402 | AN16: =LN(F16+'Models training data'!$Y$6) -> 5.5388233 | AO16: =LN(G16+'Models training data'!$Y$7) -> 5.3100511 | AP16: =V16+W16+X16+Y16+Z16 -> 0 | AQ16: =AA16+AC16+AD16+AE16+AF16 -> 1 | AR16: =$C$1+SUMPRODUCT($K$1:$AQ$1,K16:AQ16) -> 86367.709 | AS16: =$C$2+SUMPRODUCT($K$2:$AQ$2,K16:AQ16) -> 94911.598 | AT16: =$C$3+SUMPRODUCT($K$3:$AQ$3,K16:AQ16) -> 11.44996 | AU16: =$C$4+SUMPRODUCT($K$4:$AQ$4,K16:AQ16) -> 95944.094 | AV16: =$C$5+SUMPRODUCT($K$5:$AQ$5,K16:AQ16) -> 11.464917 | AW16: =$C$6+SUMPRODUCT($K$6:$AQ$6,K16:AQ16) -> 97123.758 | AX16: =$C$7+SUMPRODUCT($K$7:$AQ$7,K16:AQ16) -> 11.4764 | AY16: =$C$8+SUMPRODUCT($K$8:$AQ$8,K16:AQ16) -> 11.482071 | AZ16: =$C$9+SUMPRODUCT($K$9:$AQ$9,K16:AQ16) -> 11.474354
B17: =B16 -> NJ | C17: 44576 | D17: 2108.5312 | E17: 425.5 | F17: 219.35 | G17: 139.12511 | H17: 96098.15 | I17: =SUM(D17:G17) -> 2892.5064 | J17: =YEAR(C17) -> 2022 | K17: =IF(B17=B16,K16+1,1) -> 3 | L17: =K17^2 -> 9 | M17: =LN(L17) -> 2.1972246 | N17: =IF(K17<127,1,0) -> 1 | O17: =MONTH(C17) -> 1 | P17: =IF($O17=P$13,1,0) -> 1 | Q17: =IF($O17=Q$13,1,0) -> 0 | R17: =IF($O17=R$13,1,0) -> 0 | S17: =IF($O17=S$13,1,0) -> 0 | T17: =IF($O17=T$13,1,0) -> 0 | U17: =IF($O17=U$13,1,0) -> 0 | V17: =IF($O17=V$13,1,0) -> 0 | W17: =IF($O17=W$13,1,0) -> 0 | ... AA17: =IF($O17=AA$13,1,0) -> 0 | AB17: =IF($B17=AB$13,1,0) -> 0 | AC17: =IF($B17=AC$13,1,0) -> 0 | AD17: =IF($B17=AD$13,1,0) -> 1 | AE17: =IF($B17=AE$13,1,0) -> 0 | AF17: =IF($B17=AF$13,1,0) -> 0 | AG17: 2108.5312 | AH17: 425.5 | AI17: 219.35 | AJ17: 139.12511 | AK17: =LN(H17) -> 11.473125 | AL17: =LN(D17+'Models training data'!$Y$4) -> 7.7831148 | AM17: =LN(E17+'Models training data'!$Y$5) -> 6.1954499 | AN17: =LN(F17+'Models training data'!$Y$6) -> 5.5787047 | AO17: =LN(G17+'Models training data'!$Y$7) -> 5.2403097 | AP17: =V17+W17+X17+Y17+Z17 -> 0 | AQ17: =AA17+AC17+AD17+AE17+AF17 -> 1 | AR17: =$C$1+SUMPRODUCT($K$1:$AQ$1,K17:AQ17) -> 86343.318 | AS17: =$C$2+SUMPRODUCT($K$2:$AQ$2,K17:AQ17) -> 94887.501 | AT17: =$C$3+SUMPRODUCT($K$3:$AQ$3,K17:AQ17) -> 11.449702 | AU17: =$C$4+SUMPRODUCT($K$4:$AQ$4,K17:AQ17) -> 95848.163 | AV17: =$C$5+SUMPRODUCT($K$5:$AQ$5,K17:AQ17) -> 11.463624 | AW17: =$C$6+SUMPRODUCT($K$6:$AQ$6,K17:AQ17) -> 96537.088 | AX17: =$C$7+SUMPRODUCT($K$7:$AQ$7,K17:AQ17) -> 11.469646 | AY17: =$C$8+SUMPRODUCT($K$8:$AQ$8,K17:AQ17) -> 11.483731 | AZ17: =$C$9+SUMPRODUCT($K$9:$AQ$9,K17:AQ17) -> 11.470938
B18: =B17 -> NJ | C18: 44583 | D18: 2179.2291 | E18: 444.275 | F18: 230.3075 | G18: 138.71922 | H18: 96684.372 | I18: =SUM(D18:G18) -> 2992.5308 | J18: =YEAR(C18) -> 2022 | K18: =IF(B18=B17,K17+1,1) -> 4 | L18: =K18^2 -> 16 | M18: =LN(L18) -> 2.7725887 | N18: =IF(K18<127,1,0) -> 1 | O18: =MONTH(C18) -> 1 | P18: =IF($O18=P$13,1,0) -> 1 | Q18: =IF($O18=Q$13,1,0) -> 0 | R18: =IF($O18=R$13,1,0) -> 0 | S18: =IF($O18=S$13,1,0) -> 0 | T18: =IF($O18=T$13,1,0) -> 0 | U18: =IF($O18=U$13,1,0) -> 0 | V18: =IF($O18=V$13,1,0) -> 0 | W18: =IF($O18=W$13,1,0) -> 0 | ... AA18: =IF($O18=AA$13,1,0) -> 0 | AB18: =IF($B18=AB$13,1,0) -> 0 | AC18: =IF($B18=AC$13,1,0) -> 0 | AD18: =IF($B18=AD$13,1,0) -> 1 | AE18: =IF($B18=AE$13,1,0) -> 0 | AF18: =IF($B18=AF$13,1,0) -> 0 | AG18: 2179.2291 | AH18: 444.275 | AI18: 230.3075 | AJ18: 138.71922 | AK18: =LN(H18) -> 11.479207 | AL18: =LN(D18+'Models training data'!$Y$4) -> 7.8121498 | AM18: =LN(E18+'Models training data'!$Y$5) -> 6.2330119 | AN18: =LN(F18+'Models training data'!$Y$6) -> 5.6192625 | AO18: =LN(G18+'Models training data'!$Y$7) -> 5.2381567 | AP18: =V18+W18+X18+Y18+Z18 -> 0 | AQ18: =AA18+AC18+AD18+AE18+AF18 -> 1 | AR18: =$C$1+SUMPRODUCT($K$1:$AQ$1,K18:AQ18) -> 86318.928 | AS18: =$C$2+SUMPRODUCT($K$2:$AQ$2,K18:AQ18) -> 94863.404 | AT18: =$C$3+SUMPRODUCT($K$3:$AQ$3,K18:AQ18) -> 11.449445 | AU18: =$C$4+SUMPRODUCT($K$4:$AQ$4,K18:AQ18) -> 95753.411 | AV18: =$C$5+SUMPRODUCT($K$5:$AQ$5,K18:AQ18) -> 11.462349 | AW18: =$C$6+SUMPRODUCT($K$6:$AQ$6,K18:AQ18) -> 96120.839 | AX18: =$C$7+SUMPRODUCT($K$7:$AQ$7,K18:AQ18) -> 11.464855 | AY18: =$C$8+SUMPRODUCT($K$8:$AQ$8,K18:AQ18) -> 11.488324 | AZ18: =$C$9+SUMPRODUCT($K$9:$AQ$9,K18:AQ18) -> 11.476293
B19: =B18 -> NJ | C19: 44590 | D19: 2263.8804 | E19: 465.23875 | F19: 241.82188 | G19: 153.60006 | H19: 97892.975 | I19: =SUM(D19:G19) -> 3124.5411 | J19: =YEAR(C19) -> 2022 | K19: =IF(B19=B18,K18+1,1) -> 5 | L19: =K19^2 -> 25 | M19: =LN(L19) -> 3.2188758 | N19: =IF(K19<127,1,0) -> 1 | O19: =MONTH(C19) -> 1 | P19: =IF($O19=P$13,1,0) -> 1 | Q19: =IF($O19=Q$13,1,0) -> 0 | R19: =IF($O19=R$13,1,0) -> 0 | S19: =IF($O19=S$13,1,0) -> 0 | T19: =IF($O19=T$13,1,0) -> 0 | U19: =IF($O19=U$13,1,0) -> 0 | V19: =IF($O19=V$13,1,0) -> 0 | W19: =IF($O19=W$13,1,0) -> 0 | ... AA19: =IF($O19=AA$13,1,0) -> 0 | AB19: =IF($B19=AB$13,1,0) -> 0 | AC19: =IF($B19=AC$13,1,0) -> 0 | AD19: =IF($B19=AD$13,1,0) -> 1 | AE19: =IF($B19=AE$13,1,0) -> 0 | AF19: =IF($B19=AF$13,1,0) -> 0 | AG19: 2263.8804 | AH19: 465.23875 | AI19: 241.82188 | AJ19: 153.60006 | AK19: =LN(H19) -> 11.49163 | AL19: =LN(D19+'Models training data'!$Y$4) -> 7.8458416 | AM19: =LN(E19+'Models training data'!$Y$5) -> 6.2733502 | AN19: =LN(F19+'Models training data'!$Y$6) -> 5.6601801 | AO19: =LN(G19+'Models training data'!$Y$7) -> 5.3142079 | AP19: =V19+W19+X19+Y19+Z19 -> 0 | AQ19: =AA19+AC19+AD19+AE19+AF19 -> 1 | AR19: =$C$1+SUMPRODUCT($K$1:$AQ$1,K19:AQ19) -> 86294.538 | AS19: =$C$2+SUMPRODUCT($K$2:$AQ$2,K19:AQ19) -> 94839.306 | AT19: =$C$3+SUMPRODUCT($K$3:$AQ$3,K19:AQ19) -> 11.449187 | AU19: =$C$4+SUMPRODUCT($K$4:$AQ$4,K19:AQ19) -> 95659.838 | AV19: =$C$5+SUMPRODUCT($K$5:$AQ$5,K19:AQ19) -> 11.46109 | AW19: =$C$6+SUMPRODUCT($K$6:$AQ$6,K19:AQ19) -> 95797.971 | AX19: =$C$7+SUMPRODUCT($K$7:$AQ$7,K19:AQ19) -> 11.461138 | AY19: =$C$8+SUMPRODUCT($K$8:$AQ$8,K19:AQ19) -> 11.495967 | AZ19: =$C$9+SUMPRODUCT($K$9:$AQ$9,K19:AQ19) -> 11.491571
B20: =B19 -> NJ | C20: 44597 | D20: 2360.0573 | E20: 487.87569 | F20: 253.91287 | G20: 180.36505 | H20: 99097.406 | I20: =SUM(D20:G20) -> 3282.2109 | J20: =YEAR(C20) -> 2022 | K20: =IF(B20=B19,K19+1,1) -> 6 | L20: =K20^2 -> 36 | M20: =LN(L20) -> 3.5835189 | N20: =IF(K20<127,1,0) -> 1 | O20: =MONTH(C20) -> 2 | P20: =IF($O20=P$13,1,0) -> 0 | Q20: =IF($O20=Q$13,1,0) -> 1 | R20: =IF($O20=R$13,1,0) -> 0 | S20: =IF($O20=S$13,1,0) -> 0 | T20: =IF($O20=T$13,1,0) -> 0 | U20: =IF($O20=U$13,1,0) -> 0 | V20: =IF($O20=V$13,1,0) -> 0 | W20: =IF($O20=W$13,1,0) -> 0 | ... AA20: =IF($O20=AA$13,1,0) -> 0 | AB20: =IF($B20=AB$13,1,0) -> 0 | AC20: =IF($B20=AC$13,1,0) -> 0 | AD20: =IF($B20=AD$13,1,0) -> 1 | AE20: =IF($B20=AE$13,1,0) -> 0 | AF20: =IF($B20=AF$13,1,0) -> 0 | AG20: 2360.0573 | AH20: 487.87569 | AI20: 253.91287 | AJ20: 180.36505 | AK20: =LN(H20) -> 11.503859 | AL20: =LN(D20+'Models training data'!$Y$4) -> 7.8827918 | AM20: =LN(E20+'Models training data'!$Y$5) -> 6.315155 | AN20: =LN(F20+'Models training data'!$Y$6) -> 5.7014175 | AO20: =LN(G20+'Models training data'!$Y$7) -> 5.4379423 | AP20: =V20+W20+X20+Y20+Z20 -> 0 | AQ20: =AA20+AC20+AD20+AE20+AF20 -> 1 | AR20: =$C$1+SUMPRODUCT($K$1:$AQ$1,K20:AQ20) -> 85220.436 | AS20: =$C$2+SUMPRODUCT($K$2:$AQ$2,K20:AQ20) -> 93763.098 | AT20: =$C$3+SUMPRODUCT($K$3:$AQ$3,K20:AQ20) -> 11.437235 | AU20: =$C$4+SUMPRODUCT($K$4:$AQ$4,K20:AQ20) -> 94635.478 | AV20: =$C$5+SUMPRODUCT($K$5:$AQ$5,K20:AQ20) -> 11.4499 | AW20: =$C$6+SUMPRODUCT($K$6:$AQ$6,K20:AQ20) -> 95091.862 | AX20: =$C$7+SUMPRODUCT($K$7:$AQ$7,K20:AQ20) -> 11.453589 | AY20: =$C$8+SUMPRODUCT($K$8:$AQ$8,K20:AQ20) -> 11.506003 | AZ20: =$C$9+SUMPRODUCT($K$9:$AQ$9,K20:AQ20) -> 11.512903
B21: =B20 -> NJ | C21: 44604 | D21: 2466.1482 | E21: 511.95697 | F21: 266.6085 | G21: 155.09789 | H21: 98883.709 | I21: =SUM(D21:G21) -> 3399.8116 | J21: =YEAR(C21) -> 2022 | K21: =IF(B21=B20,K20+1,1) -> 7 | L21: =K21^2 -> 49 | M21: =LN(L21) -> 3.8918203 | N21: =IF(K21<127,1,0) -> 1 | O21: =MONTH(C21) -> 2 | P21: =IF($O21=P$13,1,0) -> 0 | Q21: =IF($O21=Q$13,1,0) -> 1 | R21: =IF($O21=R$13,1,0) -> 0 | S21: =IF($O21=S$13,1,0) -> 0 | T21: =IF($O21=T$13,1,0) -> 0 | U21: =IF($O21=U$13,1,0) -> 0 | V21: =IF($O21=V$13,1,0) -> 0 | W21: =IF($O21=W$13,1,0) -> 0 | ... AA21: =IF($O21=AA$13,1,0) -> 0 | AB21: =IF($B21=AB$13,1,0) -> 0 | AC21: =IF($B21=AC$13,1,0) -> 0 | AD21: =IF($B21=AD$13,1,0) -> 1 | AE21: =IF($B21=AE$13,1,0) -> 0 | AF21: =IF($B21=AF$13,1,0) -> 0 | AG21: 2466.1482 | AH21: 511.95697 | AI21: 266.6085 | AJ21: 155.09789 | AK21: =LN(H21) -> 11.5017 | AL21: =LN(D21+'Models training data'!$Y$4) -> 7.9220272 | AM21: =LN(E21+'Models training data'!$Y$5) -> 6.3577886 | AN21: =LN(F21+'Models training data'!$Y$6) -> 5.7429615 | AO21: =LN(G21+'Models training data'!$Y$7) -> 5.321552 | AP21: =V21+W21+X21+Y21+Z21 -> 0 | AQ21: =AA21+AC21+AD21+AE21+AF21 -> 1 | AR21: =$C$1+SUMPRODUCT($K$1:$AQ$1,K21:AQ21) -> 85196.046 | AS21: =$C$2+SUMPRODUCT($K$2:$AQ$2,K21:AQ21) -> 93739.001 | AT21: =$C$3+SUMPRODUCT($K$3:$AQ$3,K21:AQ21) -> 11.436978 | AU21: =$C$4+SUMPRODUCT($K$4:$AQ$4,K21:AQ21) -> 94544.262 | AV21: =$C$5+SUMPRODUCT($K$5:$AQ$5,K21:AQ21) -> 11.448675 | AW21: =$C$6+SUMPRODUCT($K$6:$AQ$6,K21:AQ21) -> 94868.82 | AX21: =$C$7+SUMPRODUCT($K$7:$AQ$7,K21:AQ21) -> 11.451021 | AY21: =$C$8+SUMPRODUCT($K$8:$AQ$8,K21:AQ21) -> 11.508179 | AZ21: =$C$9+SUMPRODUCT($K$9:$AQ$9,K21:AQ21) -> 11.50447
B22: =B21 -> NJ | C22: 44611 | D22: 2581.1173 | E22: 537.39857 | F22: 279.93893 | G22: 203.85299 | H22: 101098.12 | I22: =SUM(D22:G22) -> 3602.3078 | J22: =YEAR(C22) -> 2022 | K22: =IF(B22=B21,K21+1,1) -> 8 | L22: =K22^2 -> 64 | M22: =LN(L22) -> 4.1588831 | N22: =IF(K22<127,1,0) -> 1 | O22: =MONTH(C22) -> 2 | P22: =IF($O22=P$13,1,0) -> 0 | Q22: =IF($O22=Q$13,1,0) -> 1 | R22: =IF($O22=R$13,1,0) -> 0 | S22: =IF($O22=S$13,1,0) -> 0 | T22: =IF($O22=T$13,1,0) -> 0 | U22: =IF($O22=U$13,1,0) -> 0 | V22: =IF($O22=V$13,1,0) -> 0 | W22: =IF($O22=W$13,1,0) -> 0 | ... AA22: =IF($O22=AA$13,1,0) -> 0 | AB22: =IF($B22=AB$13,1,0) -> 0 | AC22: =IF($B22=AC$13,1,0) -> 0 | AD22: =IF($B22=AD$13,1,0) -> 1 | AE22: =IF($B22=AE$13,1,0) -> 0 | AF22: =IF($B22=AF$13,1,0) -> 0 | AG22: 2581.1173 | AH22: 537.39857 | AI22: 279.93893 | AJ22: 203.85299 | AK22: =LN(H22) -> 11.523847 | AL22: =LN(D22+'Models training data'!$Y$4) -> 7.9628767 | AM22: =LN(E22+'Models training data'!$Y$5) -> 6.4009394 | AN22: =LN(F22+'Models training data'!$Y$6) -> 5.7848014 | AO22: =LN(G22+'Models training data'!$Y$7) -> 5.5351919 | AP22: =V22+W22+X22+Y22+Z22 -> 0 | AQ22: =AA22+AC22+AD22+AE22+AF22 -> 1 | AR22: =$C$1+SUMPRODUCT($K$1:$AQ$1,K22:AQ22) -> 85171.656 | AS22: =$C$2+SUMPRODUCT($K$2:$AQ$2,K22:AQ22) -> 93714.903 | AT22: =$C$3+SUMPRODUCT($K$3:$AQ$3,K22:AQ22) -> 11.43672 | AU22: =$C$4+SUMPRODUCT($K$4:$AQ$4,K22:AQ22) -> 94454.225 | AV22: =$C$5+SUMPRODUCT($K$5:$AQ$5,K22:AQ22) -> 11.447467 | AW22: =$C$6+SUMPRODUCT($K$6:$AQ$6,K22:AQ22) -> 94675.613 | AX22: =$C$7+SUMPRODUCT($K$7:$AQ$7,K22:AQ22) -> 11.448797 | AY22: =$C$8+SUMPRODUCT($K$8:$AQ$8,K22:AQ22) -> 11.522571 | AZ22: =$C$9+SUMPRODUCT($K$9:$AQ$9,K22:AQ22) -> 11.53713
B23: =B22 -> NJ | C23: 44618 | D23: 2704.3363 | E23: 564.19037 | F23: 293.93587 | G23: 217.17695 | H23: 102116.02 | I23: =SUM(D23:G23) -> 3779.6395 | J23: =YEAR(C23) -> 2022 | K23: =IF(B23=B22,K22+1,1) -> 9 | L23: =K23^2 -> 81 | M23: =LN(L23) -> 4.3944492 | N23: =IF(K23<127,1,0) -> 1 | O23: =MONTH(C23) -> 2 | P23: =IF($O23=P$13,1,0) -> 0 | Q23: =IF($O23=Q$13,1,0) -> 1 | R23: =IF($O23=R$13,1,0) -> 0 | S23: =IF($O23=S$13,1,0) -> 0 | T23: =IF($O23=T$13,1,0) -> 0 | U23: =IF($O23=U$13,1,0) -> 0 | V23: =IF($O23=V$13,1,0) -> 0 | W23: =IF($O23=W$13,1,0) -> 0 | ... AA23: =IF($O23=AA$13,1,0) -> 0 | AB23: =IF($B23=AB$13,1,0) -> 0 | AC23: =IF($B23=AC$13,1,0) -> 0 | AD23: =IF($B23=AD$13,1,0) -> 1 | AE23: =IF($B23=AE$13,1,0) -> 0 | AF23: =IF($B23=AF$13,1,0) -> 0 | AG23: 2704.3363 | AH23: 564.19037 | AI23: 293.93587 | AJ23: 217.17695 | AK23: =LN(H23) -> 11.533865 | AL23: =LN(D23+'Models training data'!$Y$4) -> 8.0048808 | AM23: =LN(E23+'Models training data'!$Y$5) -> 6.4444531 | AN23: =LN(F23+'Models training data'!$Y$6) -> 5.826927 | AO23: =LN(G23+'Models training data'!$Y$7) -> 5.5864258 | AP23: =V23+W23+X23+Y23+Z23 -> 0 | AQ23: =AA23+AC23+AD23+AE23+AF23 -> 1 | AR23: =$C$1+SUMPRODUCT($K$1:$AQ$1,K23:AQ23) -> 85147.265 | AS23: =$C$2+SUMPRODUCT($K$2:$AQ$2,K23:AQ23) -> 93690.806 | AT23: =$C$3+SUMPRODUCT($K$3:$AQ$3,K23:AQ23) -> 11.436462 | AU23: =$C$4+SUMPRODUCT($K$4:$AQ$4,K23:AQ23) -> 94365.366 | AV23: =$C$5+SUMPRODUCT($K$5:$AQ$5,K23:AQ23) -> 11.446276 | AW23: =$C$6+SUMPRODUCT($K$6:$AQ$6,K23:AQ23) -> 94505.192 | AX23: =$C$7+SUMPRODUCT($K$7:$AQ$7,K23:AQ23) -> 11.446836 | AY23: =$C$8+SUMPRODUCT($K$8:$AQ$8,K23:AQ23) -> 11.531709 | AZ23: =$C$9+SUMPRODUCT($K$9:$AQ$9,K23:AQ23) -> 11.549653
B24: =B23 -> NJ | C24: 44625 | D24: 2835.4673 | E24: 592.36083 | F24: 308.63267 | G24: 223.61963 | H24: 102941.19 | I24: =SUM(D24:G24) -> 3960.0804 | J24: =YEAR(C24) -> 2022 | K24: =IF(B24=B23,K23+1,1) -> 10 | L24: =K24^2 -> 100 | M24: =LN(L24) -> 4.6051702 | N24: =IF(K24<127,1,0) -> 1 | O24: =MONTH(C24) -> 3 | P24: =IF($O24=P$13,1,0) -> 0 | Q24: =IF($O24=Q$13,1,0) -> 0 | R24: =IF($O24=R$13,1,0) -> 1 | S24: =IF($O24=S$13,1,0) -> 0 | T24: =IF($O24=T$13,1,0) -> 0 | U24: =IF($O24=U$13,1,0) -> 0 | V24: =IF($O24=V$13,1,0) -> 0 | W24: =IF($O24=W$13,1,0) -> 0 | ... AA24: =IF($O24=AA$13,1,0) -> 0 | AB24: =IF($B24=AB$13,1,0) -> 0 | AC24: =IF($B24=AC$13,1,0) -> 0 | AD24: =IF($B24=AD$13,1,0) -> 1 | AE24: =IF($B24=AE$13,1,0) -> 0 | AF24: =IF($B24=AF$13,1,0) -> 0 | AG24: 2835.4673 | AH24: 592.36083 | AI24: 308.63267 | AJ24: 223.61963 | AK24: =LN(H24) -> 11.541913 | AL24: =LN(D24+'Models training data'!$Y$4) -> 8.0477251 | AM24: =LN(E24+'Models training data'!$Y$5) -> 6.4882515 | AN24: =LN(F24+'Models training data'!$Y$6) -> 5.8693284 | AO24: =LN(G24+'Models training data'!$Y$7) -> 5.6102886 | AP24: =V24+W24+X24+Y24+Z24 -> 0 | AQ24: =AA24+AC24+AD24+AE24+AF24 -> 1 | AR24: =$C$1+SUMPRODUCT($K$1:$AQ$1,K24:AQ24) -> 84207.664 | AS24: =$C$2+SUMPRODUCT($K$2:$AQ$2,K24:AQ24) -> 92749.098 | AT24: =$C$3+SUMPRODUCT($K$3:$AQ$3,K24:AQ24) -> 11.425398 | AU24: =$C$4+SUMPRODUCT($K$4:$AQ$4,K24:AQ24) -> 93316.08 | AV24: =$C$5+SUMPRODUCT($K$5:$AQ$5,K24:AQ24) -> 11.433681 | AW24: =$C$6+SUMPRODUCT($K$6:$AQ$6,K24:AQ24) -> 93605.781 | AX24: =$C$7+SUMPRODUCT($K$7:$AQ$7,K24:AQ24) -> 11.4364 | AY24: =$C$8+SUMPRODUCT($K$8:$AQ$8,K24:AQ24) -> 11.540147 | AZ24: =$C$9+SUMPRODUCT($K$9:$AQ$9,K24:AQ24) -> 11.558819
B25: =B24 -> NJ | C25: 44632 | D25: 2974.3806 | E25: 621.95934 | F25: 324.0643 | G25: 202.337 | H25: 103029.42 | I25: =SUM(D25:G25) -> 4122.7412 | J25: =YEAR(C25) -> 2022 | K25: =IF(B25=B24,K24+1,1) -> 11 | L25: =K25^2 -> 121 | M25: =LN(L25) -> 4.7957905 | N25: =IF(K25<127,1,0) -> 1 | O25: =MONTH(C25) -> 3 | P25: =IF($O25=P$13,1,0) -> 0 | Q25: =IF($O25=Q$13,1,0) -> 0 | R25: =IF($O25=R$13,1,0) -> 1 | S25: =IF($O25=S$13,1,0) -> 0 | T25: =IF($O25=T$13,1,0) -> 0 | U25: =IF($O25=U$13,1,0) -> 0 | V25: =IF($O25=V$13,1,0) -> 0 | W25: =IF($O25=W$13,1,0) -> 0 | ... AA25: =IF($O25=AA$13,1,0) -> 0 | AB25: =IF($B25=AB$13,1,0) -> 0 | AC25: =IF($B25=AC$13,1,0) -> 0 | AD25: =IF($B25=AD$13,1,0) -> 1 | AE25: =IF($B25=AE$13,1,0) -> 0 | AF25: =IF($B25=AF$13,1,0) -> 0 | AG25: 2974.3806 | AH25: 621.95934 | AI25: 324.0643 | AJ25: 202.337 | AK25: =LN(H25) -> 11.54277 | AL25: =LN(D25+'Models training data'!$Y$4) -> 8.0911949 | AM25: =LN(E25+'Models training data'!$Y$5) -> 6.5322927 | AN25: =LN(F25+'Models training data'!$Y$6) -> 5.9119959 | AO25: =LN(G25+'Models training data'!$Y$7) -> 5.5291927 | AP25: =V25+W25+X25+Y25+Z25 -> 0 | AQ25: =AA25+AC25+AD25+AE25+AF25 -> 1 | AR25: =$C$1+SUMPRODUCT($K$1:$AQ$1,K25:AQ25) -> 84183.274 | AS25: =$C$2+SUMPRODUCT($K$2:$AQ$2,K25:AQ25) -> 92725.001 | AT25: =$C$3+SUMPRODUCT($K$3:$AQ$3,K25:AQ25) -> 11.42514 | AU25: =$C$4+SUMPRODUCT($K$4:$AQ$4,K25:AQ25) -> 93229.579 | AV25: =$C$5+SUMPRODUCT($K$5:$AQ$5,K25:AQ25) -> 11.432524 | AW25: =$C$6+SUMPRODUCT($K$6:$AQ$6,K25:AQ25) -> 93467.876 | AX25: =$C$7+SUMPRODUCT($K$7:$AQ$7,K25:AQ25) -> 11.434812 | AY25: =$C$8+SUMPRODUCT($K$8:$AQ$8,K25:AQ25) -> 11.544566 | AZ25: =$C$9+SUMPRODUCT($K$9:$AQ$9,K25:AQ25) -> 11.554976
B26: =B25 -> NJ | C26: 44639 | D26: 3121.0976 | E26: 653.04754 | F26: 340.26751 | G26: 225.30118 | H26: 104303.66 | I26: =SUM(D26:G26) -> 4339.7138 | J26: =YEAR(C26) -> 2022 | K26: =IF(B26=B25,K25+1,1) -> 12 | L26: =K26^2 -> 144 | M26: =LN(L26) -> 4.9698133 | N26: =IF(K26<127,1,0) -> 1 | O26: =MONTH(C26) -> 3 | P26: =IF($O26=P$13,1,0) -> 0 | Q26: =IF($O26=Q$13,1,0) -> 0 | R26: =IF($O26=R$13,1,0) -> 1 | S26: =IF($O26=S$13,1,0) -> 0 | T26: =IF($O26=T$13,1,0) -> 0 | U26: =IF($O26=U$13,1,0) -> 0 | V26: =IF($O26=V$13,1,0) -> 0 | W26: =IF($O26=W$13,1,0) -> 0 | ... AA26: =IF($O26=AA$13,1,0) -> 0 | AB26: =IF($B26=AB$13,1,0) -> 0 | AC26: =IF($B26=AC$13,1,0) -> 0 | AD26: =IF($B26=AD$13,1,0) -> 1 | AE26: =IF($B26=AE$13,1,0) -> 0 | AF26: =IF($B26=AF$13,1,0) -> 0 | AG26: 3121.0976 | AH26: 653.04754 | AI26: 340.26751 | AJ26: 225.30118 | AK26: =LN(H26) -> 11.555062 | AL26: =LN(D26+'Models training data'!$Y$4) -> 8.1351431 | AM26: =LN(E26+'Models training data'!$Y$5) -> 6.5765526 | AN26: =LN(F26+'Models training data'!$Y$6) -> 5.9549198 | AO26: =LN(G26+'Models training data'!$Y$7) -> 5.6164242 | AP26: =V26+W26+X26+Y26+Z26 -> 0 | AQ26: =AA26+AC26+AD26+AE26+AF26 -> 1 | AR26: =$C$1+SUMPRODUCT($K$1:$AQ$1,K26:AQ26) -> 84158.884 | AS26: =$C$2+SUMPRODUCT($K$2:$AQ$2,K26:AQ26) -> 92700.903 | AT26: =$C$3+SUMPRODUCT($K$3:$AQ$3,K26:AQ26) -> 11.424882 | AU26: =$C$4+SUMPRODUCT($K$4:$AQ$4,K26:AQ26) -> 93144.256 | AV26: =$C$5+SUMPRODUCT($K$5:$AQ$5,K26:AQ26) -> 11.431384 | AW26: =$C$6+SUMPRODUCT($K$6:$AQ$6,K26:AQ26) -> 93341.979 | AX26: =$C$7+SUMPRODUCT($K$7:$AQ$7,K26:AQ26) -> 11.433363 | AY26: =$C$8+SUMPRODUCT($K$8:$AQ$8,K26:AQ26) -> 11.556457 | AZ26: =$C$9+SUMPRODUCT($K$9:$AQ$9,K26:AQ26) -> 11.572096
B27: =B26 -> NJ | C27: 44646 | D27: 3275.751 | E27: 685.69504 | F27: 357.28089 | G27: 241.64169 | H27: 105364.32 | I27: =SUM(D27:G27) -> 4560.3686 | J27: =YEAR(C27) -> 2022 | K27: =IF(B27=B26,K26+1,1) -> 13 | L27: =K27^2 -> 169 | M27: =LN(L27) -> 5.1298987 | N27: =IF(K27<127,1,0) -> 1 | O27: =MONTH(C27) -> 3 | P27: =IF($O27=P$13,1,0) -> 0 | Q27: =IF($O27=Q$13,1,0) -> 0 | R27: =IF($O27=R$13,1,0) -> 1 | S27: =IF($O27=S$13,1,0) -> 0 | T27: =IF($O27=T$13,1,0) -> 0 | U27: =IF($O27=U$13,1,0) -> 0 | V27: =IF($O27=V$13,1,0) -> 0 | W27: =IF($O27=W$13,1,0) -> 0 | ... AA27: =IF($O27=AA$13,1,0) -> 0 | AB27: =IF($B27=AB$13,1,0) -> 0 | AC27: =IF($B27=AC$13,1,0) -> 0 | AD27: =IF($B27=AD$13,1,0) -> 1 | AE27: =IF($B27=AE$13,1,0) -> 0 | AF27: =IF($B27=AF$13,1,0) -> 0 | AG27: 3275.751 | AH27: 685.69504 | AI27: 357.28089 | AJ27: 241.64169 | AK27: =LN(H27) -> 11.565179 | AL27: =LN(D27+'Models training data'!$Y$4) -> 8.1794683 | AM27: =LN(E27+'Models training data'!$Y$5) -> 6.6210156 | AN27: =LN(F27+'Models training data'!$Y$6) -> 5.998091 | AO27: =LN(G27+'Models training data'!$Y$7) -> 5.6741653 | AP27: =V27+W27+X27+Y27+Z27 -> 0 | AQ27: =AA27+AC27+AD27+AE27+AF27 -> 1 | AR27: =$C$1+SUMPRODUCT($K$1:$AQ$1,K27:AQ27) -> 84134.493 | AS27: =$C$2+SUMPRODUCT($K$2:$AQ$2,K27:AQ27) -> 92676.806 | AT27: =$C$3+SUMPRODUCT($K$3:$AQ$3,K27:AQ27) -> 11.424625 | AU27: =$C$4+SUMPRODUCT($K$4:$AQ$4,K27:AQ27) -> 93060.112 | AV27: =$C$5+SUMPRODUCT($K$5:$AQ$5,K27:AQ27) -> 11.430261 | AW27: =$C$6+SUMPRODUCT($K$6:$AQ$6,K27:AQ27) -> 93226.165 | AX27: =$C$7+SUMPRODUCT($K$7:$AQ$7,K27:AQ27) -> 11.43203 | AY27: =$C$8+SUMPRODUCT($K$8:$AQ$8,K27:AQ27) -> 11.567721 | AZ27: =$C$9+SUMPRODUCT($K$9:$AQ$9,K27:AQ27) -> 11.585584
... B171: =B170 -> NJ | C171: 45654 | D171: 1256.8316 | E171: 251.51938 | F171: 126.86524 | G171: 91.913501 | H171: 89534.355 | I171: =SUM(D171:G171) -> 1727.1297 | J171: =YEAR(C171) -> 2024 | K171: =IF(B171=B170,K170+1,1) -> 157 | L171: =K171^2 -> 24649 | M171: =LN(L171) -> 10.112492 | N171: =IF(K171<127,1,0) -> 0 | O171: =MONTH(C171) -> 12 | P171: =IF($O171=P$13,1,0) -> 0 | Q171: =IF($O171=Q$13,1,0) -> 0 | R171: =IF($O171=R$13,1,0) -> 0 | S171: =IF($O171=S$13,1,0) -> 0 | T171: =IF($O171=T$13,1,0) -> 0 | U171: =IF($O171=U$13,1,0) -> 0 | V171: =IF($O171=V$13,1,0) -> 0 | W171: =IF($O171=W$13,1,0) -> 0 | ... AA171: =IF($O171=AA$13,1,0) -> 1 | AB171: =IF($B171=AB$13,1,0) -> 0 | AC171: =IF($B171=AC$13,1,0) -> 0 | AD171: =IF($B171=AD$13,1,0) -> 1 | AE171: =IF($B171=AE$13,1,0) -> 0 | AF171: =IF($B171=AF$13,1,0) -> 0 | AG171: 1256.8316 | AH171: 251.51938 | AI171: 126.86524 | AJ171: 91.913501 | AK171: =LN(H171) -> 11.402378 | AL171: =LN(D171+'Models training data'!$Y$4) -> 7.3447438 | AM171: =LN(E171+'Models training data'!$Y$5) -> 5.7574226 | AN171: =LN(F171+'Models training data'!$Y$6) -> 5.1489105 | AO171: =LN(G171+'Models training data'!$Y$7) -> 4.9524194 | AP171: =V171+W171+X171+Y171+Z171 -> 0 | AQ171: =AA171+AC171+AD171+AE171+AF171 -> 2 | AR171: =$C$1+SUMPRODUCT($K$1:$AQ$1,K171:AQ171) -> 81456.478 | AS171: =$C$2+SUMPRODUCT($K$2:$AQ$2,K171:AQ171) -> 90038.245 | AT171: =$C$3+SUMPRODUCT($K$3:$AQ$3,K171:AQ171) -> 11.395954 | AU171: =$C$4+SUMPRODUCT($K$4:$AQ$4,K171:AQ171) -> 94688.864 | AV171: =$C$5+SUMPRODUCT($K$5:$AQ$5,K171:AQ171) -> 11.462628 | AW171: =$C$6+SUMPRODUCT($K$6:$AQ$6,K171:AQ171) -> 90847.277 | AX171: =$C$7+SUMPRODUCT($K$7:$AQ$7,K171:AQ171) -> 11.403685 | AY171: =$C$8+SUMPRODUCT($K$8:$AQ$8,K171:AQ171) -> 11.329816 | AZ171: =$C$9+SUMPRODUCT($K$9:$AQ$9,K171:AQ171) -> 11.381172
B172: NY | C172: 44562 | D172: 4050 | E172: 800 | F172: 400 | G172: 283.73677 | H172: 111249.41 | I172: =SUM(D172:G172) -> 5533.7368 | J172: =YEAR(C172) -> 2022 | K172: =IF(B172=B171,K171+1,1) -> 1 | L172: =K172^2 -> 1 | M172: =LN(L172) -> 0 | N172: =IF(K172<127,1,0) -> 1 | O172: =MONTH(C172) -> 1 | P172: =IF($O172=P$13,1,0) -> 1 | Q172: =IF($O172=Q$13,1,0) -> 0 | R172: =IF($O172=R$13,1,0) -> 0 | S172: =IF($O172=S$13,1,0) -> 0 | T172: =IF($O172=T$13,1,0) -> 0 | U172: =IF($O172=U$13,1,0) -> 0 | V172: =IF($O172=V$13,1,0) -> 0 | W172: =IF($O172=W$13,1,0) -> 0 | ... AA172: =IF($O172=AA$13,1,0) -> 0 | AB172: =IF($B172=AB$13,1,0) -> 0 | AC172: =IF($B172=AC$13,1,0) -> 0 | AD172: =IF($B172=AD$13,1,0) -> 0 | AE172: =IF($B172=AE$13,1,0) -> 1 | AF172: =IF($B172=AF$13,1,0) -> 0 | AG172: 4050 | AH172: 800 | AI172: 400 | AJ172: 283.73677 | AK172: =LN(H172) -> 11.61953 | AL172: =LN(D172+'Models training data'!$Y$4) -> 8.3759076 | AM172: =LN(E172+'Models training data'!$Y$5) -> 6.7627435 | AN172: =LN(F172+'Models training data'!$Y$6) -> 6.0989244 | AO172: =LN(G172+'Models training data'!$Y$7) -> 5.8091636 | AP172: =V172+W172+X172+Y172+Z172 -> 0 | AQ172: =AA172+AC172+AD172+AE172+AF172 -> 1 | AR172: =$C$1+SUMPRODUCT($K$1:$AQ$1,K172:AQ172) -> 86392.099 | AS172: =$C$2+SUMPRODUCT($K$2:$AQ$2,K172:AQ172) -> 110385.63 | AT172: =$C$3+SUMPRODUCT($K$3:$AQ$3,K172:AQ172) -> 11.599395 | AU172: =$C$4+SUMPRODUCT($K$4:$AQ$4,K172:AQ172) -> 111491.14 | AV172: =$C$5+SUMPRODUCT($K$5:$AQ$5,K172:AQ172) -> 11.615403 | AW172: =$C$6+SUMPRODUCT($K$6:$AQ$6,K172:AQ172) -> 113576.61 | AX172: =$C$7+SUMPRODUCT($K$7:$AQ$7,K172:AQ172) -> 11.637121 | AY172: =$C$8+SUMPRODUCT($K$8:$AQ$8,K172:AQ172) -> 11.659233 | AZ172: =$C$9+SUMPRODUCT($K$9:$AQ$9,K172:AQ172) -> 11.621665
B173: =B172 -> NY | C173: 44569 | D173: 4110.75 | E173: 820 | F173: 418 | G173: 291.26661 | H173: 111854.26 | I173: =SUM(D173:G173) -> 5640.0166 | J173: =YEAR(C173) -> 2022 | K173: =IF(B173=B172,K172+1,1) -> 2 | L173: =K173^2 -> 4 | M173: =LN(L173) -> 1.3862944 | N173: =IF(K173<127,1,0) -> 1 | O173: =MONTH(C173) -> 1 | P173: =IF($O173=P$13,1,0) -> 1 | Q173: =IF($O173=Q$13,1,0) -> 0 | R173: =IF($O173=R$13,1,0) -> 0 | S173: =IF($O173=S$13,1,0) -> 0 | T173: =IF($O173=T$13,1,0) -> 0 | U173: =IF($O173=U$13,1,0) -> 0 | V173: =IF($O173=V$13,1,0) -> 0 | W173: =IF($O173=W$13,1,0) -> 0 | ... AA173: =IF($O173=AA$13,1,0) -> 0 | AB173: =IF($B173=AB$13,1,0) -> 0 | AC173: =IF($B173=AC$13,1,0) -> 0 | AD173: =IF($B173=AD$13,1,0) -> 0 | AE173: =IF($B173=AE$13,1,0) -> 1 | AF173: =IF($B173=AF$13,1,0) -> 0 | AG173: 4110.75 | AH173: 820 | AI173: 418 | AJ173: 291.26661 | AK173: =LN(H173) -> 11.624952 | AL173: =LN(D173+'Models training data'!$Y$4) -> 8.3898044 | AM173: =LN(E173+'Models training data'!$Y$5) -> 6.7856013 | AN173: =LN(F173+'Models training data'!$Y$6) -> 6.1385442 | AO173: =LN(G173+'Models training data'!$Y$7) -> 5.8315013 | AP173: =V173+W173+X173+Y173+Z173 -> 0 | AQ173: =AA173+AC173+AD173+AE173+AF173 -> 1 | AR173: =$C$1+SUMPRODUCT($K$1:$AQ$1,K173:AQ173) -> 86367.709 | AS173: =$C$2+SUMPRODUCT($K$2:$AQ$2,K173:AQ173) -> 110361.53 | AT173: =$C$3+SUMPRODUCT($K$3:$AQ$3,K173:AQ173) -> 11.599137 | AU173: =$C$4+SUMPRODUCT($K$4:$AQ$4,K173:AQ173) -> 111394.03 | AV173: =$C$5+SUMPRODUCT($K$5:$AQ$5,K173:AQ173) -> 11.614094 | AW173: =$C$6+SUMPRODUCT($K$6:$AQ$6,K173:AQ173) -> 112573.69 | AX173: =$C$7+SUMPRODUCT($K$7:$AQ$7,K173:AQ173) -> 11.625577 | AY173: =$C$8+SUMPRODUCT($K$8:$AQ$8,K173:AQ173) -> 11.665654 | AZ173: =$C$9+SUMPRODUCT($K$9:$AQ$9,K173:AQ173) -> 11.629178
B174: =B173 -> NY | C174: 44576 | D174: 4217.0625 | E174: 851 | F174: 438.7 | G174: 320.78537 | H174: 112964.4 | I174: =SUM(D174:G174) -> 5827.5479 | J174: =YEAR(C174) -> 2022 | K174: =IF(B174=B173,K173+1,1) -> 3 | L174: =K174^2 -> 9 | M174: =LN(L174) -> 2.1972246 | N174: =IF(K174<127,1,0) -> 1 | O174: =MONTH(C174) -> 1 | P174: =IF($O174=P$13,1,0) -> 1 | Q174: =IF($O174=Q$13,1,0) -> 0 | R174: =IF($O174=R$13,1,0) -> 0 | S174: =IF($O174=S$13,1,0) -> 0 | T174: =IF($O174=T$13,1,0) -> 0 | U174: =IF($O174=U$13,1,0) -> 0 | V174: =IF($O174=V$13,1,0) -> 0 | W174: =IF($O174=W$13,1,0) -> 0 | ... AA174: =IF($O174=AA$13,1,0) -> 0 | AB174: =IF($B174=AB$13,1,0) -> 0 | AC174: =IF($B174=AC$13,1,0) -> 0 | AD174: =IF($B174=AD$13,1,0) -> 0 | AE174: =IF($B174=AE$13,1,0) -> 1 | AF174: =IF($B174=AF$13,1,0) -> 0 | AG174: 4217.0625 | AH174: 851 | AI174: 438.7 | AJ174: 320.78537 | AK174: =LN(H174) -> 11.634828 | AL174: =LN(D174+'Models training data'!$Y$4) -> 8.4136686 | AM174: =LN(E174+'Models training data'!$Y$5) -> 6.8200296 | AN174: =LN(F174+'Models training data'!$Y$6) -> 6.1822471 | AO174: =LN(G174+'Models training data'!$Y$7) -> 5.9145533 | AP174: =V174+W174+X174+Y174+Z174 -> 0 | AQ174: =AA174+AC174+AD174+AE174+AF174 -> 1 | AR174: =$C$1+SUMPRODUCT($K$1:$AQ$1,K174:AQ174) -> 86343.318 | AS174: =$C$2+SUMPRODUCT($K$2:$AQ$2,K174:AQ174) -> 110337.43 | AT174: =$C$3+SUMPRODUCT($K$3:$AQ$3,K174:AQ174) -> 11.598879 | AU174: =$C$4+SUMPRODUCT($K$4:$AQ$4,K174:AQ174) -> 111298.1 | AV174: =$C$5+SUMPRODUCT($K$5:$AQ$5,K174:AQ174) -> 11.612801 | AW174: =$C$6+SUMPRODUCT($K$6:$AQ$6,K174:AQ174) -> 111987.02 | AX174: =$C$7+SUMPRODUCT($K$7:$AQ$7,K174:AQ174) -> 11.618823 | AY174: =$C$8+SUMPRODUCT($K$8:$AQ$8,K174:AQ174) -> 11.678126 | AZ174: =$C$9+SUMPRODUCT($K$9:$AQ$9,K174:AQ174) -> 11.645205
B175: =B174 -> NY | C175: 44583 | D175: 4358.4581 | E175: 888.55 | F175: 460.615 | G175: 310.30932 | H175: 113377.68 | I175: =SUM(D175:G175) -> 6017.9324 | J175: =YEAR(C175) -> 2022 | K175: =IF(B175=B174,K174+1,1) -> 4 | L175: =K175^2 -> 16 | M175: =LN(L175) -> 2.7725887 | N175: =IF(K175<127,1,0) -> 1 | O175: =MONTH(C175) -> 1 | P175: =IF($O175=P$13,1,0) -> 1 | Q175: =IF($O175=Q$13,1,0) -> 0 | R175: =IF($O175=R$13,1,0) -> 0 | S175: =IF($O175=S$13,1,0) -> 0 | T175: =IF($O175=T$13,1,0) -> 0 | U175: =IF($O175=U$13,1,0) -> 0 | V175: =IF($O175=V$13,1,0) -> 0 | W175: =IF($O175=W$13,1,0) -> 0 | ... AA175: =IF($O175=AA$13,1,0) -> 0 | AB175: =IF($B175=AB$13,1,0) -> 0 | AC175: =IF($B175=AC$13,1,0) -> 0 | AD175: =IF($B175=AD$13,1,0) -> 0 | AE175: =IF($B175=AE$13,1,0) -> 1 | AF175: =IF($B175=AF$13,1,0) -> 0 | AG175: 4358.4581 | AH175: 888.55 | AI175: 460.615 | AJ175: 310.30932 | AK175: =LN(H175) -> 11.63848 | AL175: =LN(D175+'Models training data'!$Y$4) -> 8.4445504 | AM175: =LN(E175+'Models training data'!$Y$5) -> 6.8602045 | AN175: =LN(F175+'Models training data'!$Y$6) -> 6.2265238 | AO175: =LN(G175+'Models training data'!$Y$7) -> 5.8858616 | AP175: =V175+W175+X175+Y175+Z175 -> 0 | AQ175: =AA175+AC175+AD175+AE175+AF175 -> 1 | AR175: =$C$1+SUMPRODUCT($K$1:$AQ$1,K175:AQ175) -> 86318.928 | AS175: =$C$2+SUMPRODUCT($K$2:$AQ$2,K175:AQ175) -> 110313.34 | AT175: =$C$3+SUMPRODUCT($K$3:$AQ$3,K175:AQ175) -> 11.598622 | AU175: =$C$4+SUMPRODUCT($K$4:$AQ$4,K175:AQ175) -> 111203.34 | AV175: =$C$5+SUMPRODUCT($K$5:$AQ$5,K175:AQ175) -> 11.611525 | AW175: =$C$6+SUMPRODUCT($K$6:$AQ$6,K175:AQ175) -> 111570.77 | AX175: =$C$7+SUMPRODUCT($K$7:$AQ$7,K175:AQ175) -> 11.614032 | AY175: =$C$8+SUMPRODUCT($K$8:$AQ$8,K175:AQ175) -> 11.685864 | AZ175: =$C$9+SUMPRODUCT($K$9:$AQ$9,K175:AQ175) -> 11.647717
B176: =B175 -> NY | C176: 44590 | D176: 4527.7608 | E176: 930.4775 | F176: 483.64375 | G176: 330.64792 | H176: 114366.87 | I176: =SUM(D176:G176) -> 6272.53 | J176: =YEAR(C176) -> 2022 | K176: =IF(B176=B175,K175+1,1) -> 5 | L176: =K176^2 -> 25 | M176: =LN(L176) -> 3.2188758 | N176: =IF(K176<127,1,0) -> 1 | O176: =MONTH(C176) -> 1 | P176: =IF($O176=P$13,1,0) -> 1 | Q176: =IF($O176=Q$13,1,0) -> 0 | R176: =IF($O176=R$13,1,0) -> 0 | S176: =IF($O176=S$13,1,0) -> 0 | T176: =IF($O176=T$13,1,0) -> 0 | U176: =IF($O176=U$13,1,0) -> 0 | V176: =IF($O176=V$13,1,0) -> 0 | W176: =IF($O176=W$13,1,0) -> 0 | ... AA176: =IF($O176=AA$13,1,0) -> 0 | AB176: =IF($B176=AB$13,1,0) -> 0 | AC176: =IF($B176=AC$13,1,0) -> 0 | AD176: =IF($B176=AD$13,1,0) -> 0 | AE176: =IF($B176=AE$13,1,0) -> 1 | AF176: =IF($B176=AF$13,1,0) -> 0 | AG176: 4527.7608 | AH176: 930.4775 | AI176: 483.64375 | AJ176: 330.64792 | AK176: =LN(H176) -> 11.647167 | AL176: =LN(D176+'Models training data'!$Y$4) -> 8.480315 | AM176: =LN(E176+'Models training data'!$Y$5) -> 6.9032347 | AN176: =LN(F176+'Models training data'!$Y$6) -> 6.2710305 | AO176: =LN(G176+'Models training data'!$Y$7) -> 5.9408325 | AP176: =V176+W176+X176+Y176+Z176 -> 0 | AQ176: =AA176+AC176+AD176+AE176+AF176 -> 1 | AR176: =$C$1+SUMPRODUCT($K$1:$AQ$1,K176:AQ176) -> 86294.538 | AS176: =$C$2+SUMPRODUCT($K$2:$AQ$2,K176:AQ176) -> 110289.24 | AT176: =$C$3+SUMPRODUCT($K$3:$AQ$3,K176:AQ176) -> 11.598364 | AU176: =$C$4+SUMPRODUCT($K$4:$AQ$4,K176:AQ176) -> 111109.77 | AV176: =$C$5+SUMPRODUCT($K$5:$AQ$5,K176:AQ176) -> 11.610267 | AW176: =$C$6+SUMPRODUCT($K$6:$AQ$6,K176:AQ176) -> 111247.9 | AX176: =$C$7+SUMPRODUCT($K$7:$AQ$7,K176:AQ176) -> 11.610315 | AY176: =$C$8+SUMPRODUCT($K$8:$AQ$8,K176:AQ176) -> 11.699739 | AZ176: =$C$9+SUMPRODUCT($K$9:$AQ$9,K176:AQ176) -> 11.660825
B177: =B176 -> NY | C177: 44597 | D177: 3944.7736 | E177: 720.49506 | F177: 278.09506 | G177: 168.48767 | H177: 105053.67 | I177: =SUM(D177:G177) -> 5111.8514 | J177: =YEAR(C177) -> 2022 | K177: =IF(B177=B176,K176+1,1) -> 6 | L177: =K177^2 -> 36 | M177: =LN(L177) -> 3.5835189 | N177: =IF(K177<127,1,0) -> 1 | O177: =MONTH(C177) -> 2 | P177: =IF($O177=P$13,1,0) -> 0 | Q177: =IF($O177=Q$13,1,0) -> 1 | R177: =IF($O177=R$13,1,0) -> 0 | S177: =IF($O177=S$13,1,0) -> 0 | T177: =IF($O177=T$13,1,0) -> 0 | U177: =IF($O177=U$13,1,0) -> 0 | V177: =IF($O177=V$13,1,0) -> 0 | W177: =IF($O177=W$13,1,0) -> 0 | ... AA177: =IF($O177=AA$13,1,0) -> 0 | AB177: =IF($B177=AB$13,1,0) -> 0 | AC177: =IF($B177=AC$13,1,0) -> 0 | AD177: =IF($B177=AD$13,1,0) -> 0 | AE177: =IF($B177=AE$13,1,0) -> 1 | AF177: =IF($B177=AF$13,1,0) -> 0 | AG177: 3944.7736 | AH177: 720.49506 | AI177: 278.09506 | AJ177: 168.48767 | AK177: =LN(H177) -> 11.562227 | AL177: =LN(D177+'Models training data'!$Y$4) -> 8.3513701 | AM177: =LN(E177+'Models training data'!$Y$5) -> 6.6663296 | AN177: =LN(F177+'Models training data'!$Y$6) -> 5.7791173 | AO177: =LN(G177+'Models training data'!$Y$7) -> 5.3849129 | AP177: =V177+W177+X177+Y177+Z177 -> 0 | AQ177: =AA177+AC177+AD177+AE177+AF177 -> 1 | AR177: =$C$1+SUMPRODUCT($K$1:$AQ$1,K177:AQ177) -> 85220.436 | AS177: =$C$2+SUMPRODUCT($K$2:$AQ$2,K177:AQ177) -> 109213.03 | AT177: =$C$3+SUMPRODUCT($K$3:$AQ$3,K177:AQ177) -> 11.586412 | AU177: =$C$4+SUMPRODUCT($K$4:$AQ$4,K177:AQ177) -> 110085.41 | AV177: =$C$5+SUMPRODUCT($K$5:$AQ$5,K177:AQ177) -> 11.599077 | AW177: =$C$6+SUMPRODUCT($K$6:$AQ$6,K177:AQ177) -> 110541.79 | AX177: =$C$7+SUMPRODUCT($K$7:$AQ$7,K177:AQ177) -> 11.602766 | AY177: =$C$8+SUMPRODUCT($K$8:$AQ$8,K177:AQ177) -> 11.61769 | AZ177: =$C$9+SUMPRODUCT($K$9:$AQ$9,K177:AQ177) -> 11.537516
B178: =B177 -> NY | C178: 44604 | D178: 3575.4496 | E178: 628.26666 | F178: 269.02672 | G178: 164.21279 | H178: 103928.3 | I178: =SUM(D178:G178) -> 4636.9558 | J178: =YEAR(C178) -> 2022 | K178: =IF(B178=B177,K177+1,1) -> 7 | L178: =K178^2 -> 49 | M178: =LN(L178) -> 3.8918203 | N178: =IF(K178<127,1,0) -> 1 | O178: =MONTH(C178) -> 2 | P178: =IF($O178=P$13,1,0) -> 0 | Q178: =IF($O178=Q$13,1,0) -> 1 | R178: =IF($O178=R$13,1,0) -> 0 | S178: =IF($O178=S$13,1,0) -> 0 | T178: =IF($O178=T$13,1,0) -> 0 | U178: =IF($O178=U$13,1,0) -> 0 | V178: =IF($O178=V$13,1,0) -> 0 | W178: =IF($O178=W$13,1,0) -> 0 | ... AA178: =IF($O178=AA$13,1,0) -> 0 | AB178: =IF($B178=AB$13,1,0) -> 0 | AC178: =IF($B178=AC$13,1,0) -> 0 | AD178: =IF($B178=AD$13,1,0) -> 0 | AE178: =IF($B178=AE$13,1,0) -> 1 | AF178: =IF($B178=AF$13,1,0) -> 0 | AG178: 3575.4496 | AH178: 628.26666 | AI178: 269.02672 | AJ178: 164.21279 | AK178: =LN(H178) -> 11.551457 | AL178: =LN(D178+'Models training data'!$Y$4) -> 8.2601454 | AM178: =LN(E178+'Models training data'!$Y$5) -> 6.5414321 | AN178: =LN(F178+'Models training data'!$Y$6) -> 5.7506826 | AO178: =LN(G178+'Models training data'!$Y$7) -> 5.3651169 | AP178: =V178+W178+X178+Y178+Z178 -> 0 | AQ178: =AA178+AC178+AD178+AE178+AF178 -> 1 | AR178: =$C$1+SUMPRODUCT($K$1:$AQ$1,K178:AQ178) -> 85196.046 | AS178: =$C$2+SUMPRODUCT($K$2:$AQ$2,K178:AQ178) -> 109188.93 | AT178: =$C$3+SUMPRODUCT($K$3:$AQ$3,K178:AQ178) -> 11.586155 | AU178: =$C$4+SUMPRODUCT($K$4:$AQ$4,K178:AQ178) -> 109994.19 | AV178: =$C$5+SUMPRODUCT($K$5:$AQ$5,K178:AQ178) -> 11.597852 | AW178: =$C$6+SUMPRODUCT($K$6:$AQ$6,K178:AQ178) -> 110318.75 | AX178: =$C$7+SUMPRODUCT($K$7:$AQ$7,K178:AQ178) -> 11.600198 | AY178: =$C$8+SUMPRODUCT($K$8:$AQ$8,K178:AQ178) -> 11.597061 | AZ178: =$C$9+SUMPRODUCT($K$9:$AQ$9,K178:AQ178) -> 11.526297
B179: =B178 -> NY | C179: 44611 | D179: 3357.6282 | E179: 595.55341 | F179: 280.18075 | G179: 205.93131 | H179: 105163.14 | I179: =SUM(D179:G179) -> 4439.2937 | J179: =YEAR(C179) -> 2022 | K179: =IF(B179=B178,K178+1,1) -> 8 | L179: =K179^2 -> 64 | M179: =LN(L179) -> 4.1588831 | N179: =IF(K179<127,1,0) -> 1 | O179: =MONTH(C179) -> 2 | P179: =IF($O179=P$13,1,0) -> 0 | Q179: =IF($O179=Q$13,1,0) -> 1 | R179: =IF($O179=R$13,1,0) -> 0 | S179: =IF($O179=S$13,1,0) -> 0 | T179: =IF($O179=T$13,1,0) -> 0 | U179: =IF($O179=U$13,1,0) -> 0 | V179: =IF($O179=V$13,1,0) -> 0 | W179: =IF($O179=W$13,1,0) -> 0 | ... AA179: =IF($O179=AA$13,1,0) -> 0 | AB179: =IF($B179=AB$13,1,0) -> 0 | AC179: =IF($B179=AC$13,1,0) -> 0 | AD179: =IF($B179=AD$13,1,0) -> 0 | AE179: =IF($B179=AE$13,1,0) -> 1 | AF179: =IF($B179=AF$13,1,0) -> 0 | AG179: 3357.6282 | AH179: 595.55341 | AI179: 280.18075 | AJ179: 205.93131 | AK179: =LN(H179) -> 11.563268 | AL179: =LN(D179+'Models training data'!$Y$4) -> 8.2021632 | AM179: =LN(E179+'Models training data'!$Y$5) -> 6.4930963 | AN179: =LN(F179+'Models training data'!$Y$6) -> 5.7855444 | AO179: =LN(G179+'Models training data'!$Y$7) -> 5.5433584 | AP179: =V179+W179+X179+Y179+Z179 -> 0 | AQ179: =AA179+AC179+AD179+AE179+AF179 -> 1 | AR179: =$C$1+SUMPRODUCT($K$1:$AQ$1,K179:AQ179) -> 85171.656 | AS179: =$C$2+SUMPRODUCT($K$2:$AQ$2,K179:AQ179) -> 109164.84 | AT179: =$C$3+SUMPRODUCT($K$3:$AQ$3,K179:AQ179) -> 11.585897 | AU179: =$C$4+SUMPRODUCT($K$4:$AQ$4,K179:AQ179) -> 109904.16 | AV179: =$C$5+SUMPRODUCT($K$5:$AQ$5,K179:AQ179) -> 11.596644 | AW179: =$C$6+SUMPRODUCT($K$6:$AQ$6,K179:AQ179) -> 110125.55 | AX179: =$C$7+SUMPRODUCT($K$7:$AQ$7,K179:AQ179) -> 11.597974 | AY179: =$C$8+SUMPRODUCT($K$8:$AQ$8,K179:AQ179) -> 11.596018 | AZ179: =$C$9+SUMPRODUCT($K$9:$AQ$9,K179:AQ179) -> 11.548898
B180: =B179 -> NY | C180: 44618 | D180: 3247.894 | E180: 593.2678 | F180: 293.96005 | G180: 196.9667 | H180: 105167.52 | I180: =SUM(D180:G180) -> 4332.0885 | J180: =YEAR(C180) -> 2022 | K180: =IF(B180=B179,K179+1,1) -> 9 | L180: =K180^2 -> 81 | M180: =LN(L180) -> 4.3944492 | N180: =IF(K180<127,1,0) -> 1 | O180: =MONTH(C180) -> 2 | P180: =IF($O180=P$13,1,0) -> 0 | Q180: =IF($O180=Q$13,1,0) -> 1 | R180: =IF($O180=R$13,1,0) -> 0 | S180: =IF($O180=S$13,1,0) -> 0 | T180: =IF($O180=T$13,1,0) -> 0 | U180: =IF($O180=U$13,1,0) -> 0 | V180: =IF($O180=V$13,1,0) -> 0 | W180: =IF($O180=W$13,1,0) -> 0 | ... AA180: =IF($O180=AA$13,1,0) -> 0 | AB180: =IF($B180=AB$13,1,0) -> 0 | AC180: =IF($B180=AC$13,1,0) -> 0 | AD180: =IF($B180=AD$13,1,0) -> 0 | AE180: =IF($B180=AE$13,1,0) -> 1 | AF180: =IF($B180=AF$13,1,0) -> 0 | AG180: 3247.894 | AH180: 593.2678 | AI180: 293.96005 | AJ180: 196.9667 | AK180: =LN(H180) -> 11.56331 | AL180: =LN(D180+'Models training data'!$Y$4) -> 8.1716279 | AM180: =LN(E180+'Models training data'!$Y$5) -> 6.4896302 | AN180: =LN(F180+'Models training data'!$Y$6) -> 5.8269982 | AO180: =LN(G180+'Models training data'!$Y$7) -> 5.5076465 | AP180: =V180+W180+X180+Y180+Z180 -> 0 | AQ180: =AA180+AC180+AD180+AE180+AF180 -> 1 | AR180: =$C$1+SUMPRODUCT($K$1:$AQ$1,K180:AQ180) -> 85147.265 | AS180: =$C$2+SUMPRODUCT($K$2:$AQ$2,K180:AQ180) -> 109140.74 | AT180: =$C$3+SUMPRODUCT($K$3:$AQ$3,K180:AQ180) -> 11.585639 | AU180: =$C$4+SUMPRODUCT($K$4:$AQ$4,K180:AQ180) -> 109815.3 | AV180: =$C$5+SUMPRODUCT($K$5:$AQ$5,K180:AQ180) -> 11.595453 | AW180: =$C$6+SUMPRODUCT($K$6:$AQ$6,K180:AQ180) -> 109955.12 | AX180: =$C$7+SUMPRODUCT($K$7:$AQ$7,K180:AQ180) -> 11.596013 | AY180: =$C$8+SUMPRODUCT($K$8:$AQ$8,K180:AQ180) -> 11.593119 | AZ180: =$C$9+SUMPRODUCT($K$9:$AQ$9,K180:AQ180) -> 11.547735
B181: =B180 -> NY | C181: 44625 | D181: 3215.9577 | E181: 606.89954 | F181: 308.63508 | G181: 186.84934 | H181: 105289.32 | I181: =SUM(D181:G181) -> 4318.3416 | J181: =YEAR(C181) -> 2022 | K181: =IF(B181=B180,K180+1,1) -> 10 | L181: =K181^2 -> 100 | M181: =LN(L181) -> 4.6051702 | N181: =IF(K181<127,1,0) -> 1 | O181: =MONTH(C181) -> 3 | P181: =IF($O181=P$13,1,0) -> 0 | Q181: =IF($O181=Q$13,1,0) -> 0 | R181: =IF($O181=R$13,1,0) -> 1 | S181: =IF($O181=S$13,1,0) -> 0 | T181: =IF($O181=T$13,1,0) -> 0 | U181: =IF($O181=U$13,1,0) -> 0 | V181: =IF($O181=V$13,1,0) -> 0 | W181: =IF($O181=W$13,1,0) -> 0 | ... AA181: =IF($O181=AA$13,1,0) -> 0 | AB181: =IF($B181=AB$13,1,0) -> 0 | AC181: =IF($B181=AC$13,1,0) -> 0 | AD181: =IF($B181=AD$13,1,0) -> 0 | AE181: =IF($B181=AE$13,1,0) -> 1 | AF181: =IF($B181=AF$13,1,0) -> 0 | AG181: 3215.9577 | AH181: 606.89954 | AI181: 308.63508 | AJ181: 186.84934 | AK181: =LN(H181) -> 11.564467 | AL181: =LN(D181+'Models training data'!$Y$4) -> 8.1625631 | AM181: =LN(E181+'Models training data'!$Y$5) -> 6.5101268 | AN181: =LN(F181+'Models training data'!$Y$6) -> 5.8693352 | AO181: =LN(G181+'Models training data'!$Y$7) -> 5.4657485 | AP181: =V181+W181+X181+Y181+Z181 -> 0 | AQ181: =AA181+AC181+AD181+AE181+AF181 -> 1 | AR181: =$C$1+SUMPRODUCT($K$1:$AQ$1,K181:AQ181) -> 84207.664 | AS181: =$C$2+SUMPRODUCT($K$2:$AQ$2,K181:AQ181) -> 108199.03 | AT181: =$C$3+SUMPRODUCT($K$3:$AQ$3,K181:AQ181) -> 11.574575 | AU181: =$C$4+SUMPRODUCT($K$4:$AQ$4,K181:AQ181) -> 108766.01 | AV181: =$C$5+SUMPRODUCT($K$5:$AQ$5,K181:AQ181) -> 11.582858 | AW181: =$C$6+SUMPRODUCT($K$6:$AQ$6,K181:AQ181) -> 109055.71 | AX181: =$C$7+SUMPRODUCT($K$7:$AQ$7,K181:AQ181) -> 11.585577 | AY181: =$C$8+SUMPRODUCT($K$8:$AQ$8,K181:AQ181) -> 11.5937 | AZ181: =$C$9+SUMPRODUCT($K$9:$AQ$9,K181:AQ181) -> 11.547158
B182: =B181 -> NY | C182: 44632 | D182: 3240.7238 | E182: 629.2287 | F182: 324.06454 | G182: 226.82025 | H182: 106913.68 | I182: =SUM(D182:G182) -> 4420.8373 | J182: =YEAR(C182) -> 2022 | K182: =IF(B182=B181,K181+1,1) -> 11 | L182: =K182^2 -> 121 | M182: =LN(L182) -> 4.7957905 | N182: =IF(K182<127,1,0) -> 1 | O182: =MONTH(C182) -> 3 | P182: =IF($O182=P$13,1,0) -> 0 | Q182: =IF($O182=Q$13,1,0) -> 0 | R182: =IF($O182=R$13,1,0) -> 1 | S182: =IF($O182=S$13,1,0) -> 0 | T182: =IF($O182=T$13,1,0) -> 0 | U182: =IF($O182=U$13,1,0) -> 0 | V182: =IF($O182=V$13,1,0) -> 0 | W182: =IF($O182=W$13,1,0) -> 0 | ... AA182: =IF($O182=AA$13,1,0) -> 0 | AB182: =IF($B182=AB$13,1,0) -> 0 | AC182: =IF($B182=AC$13,1,0) -> 0 | AD182: =IF($B182=AD$13,1,0) -> 0 | AE182: =IF($B182=AE$13,1,0) -> 1 | AF182: =IF($B182=AF$13,1,0) -> 0 | AG182: 3240.7238 | AH182: 629.2287 | AI182: 324.06454 | AJ182: 226.82025 | AK182: =LN(H182) -> 11.579777 | AL182: =LN(D182+'Models training data'!$Y$4) -> 8.1695999 | AM182: =LN(E182+'Models training data'!$Y$5) -> 6.5428188 | AN182: =LN(F182+'Models training data'!$Y$6) -> 5.9119965 | AO182: =LN(G182+'Models training data'!$Y$7) -> 5.6219348 | AP182: =V182+W182+X182+Y182+Z182 -> 0 | AQ182: =AA182+AC182+AD182+AE182+AF182 -> 1 | AR182: =$C$1+SUMPRODUCT($K$1:$AQ$1,K182:AQ182) -> 84183.274 | AS182: =$C$2+SUMPRODUCT($K$2:$AQ$2,K182:AQ182) -> 108174.93 | AT182: =$C$3+SUMPRODUCT($K$3:$AQ$3,K182:AQ182) -> 11.574317 | AU182: =$C$4+SUMPRODUCT($K$4:$AQ$4,K182:AQ182) -> 108679.51 | AV182: =$C$5+SUMPRODUCT($K$5:$AQ$5,K182:AQ182) -> 11.581701 | AW182: =$C$6+SUMPRODUCT($K$6:$AQ$6,K182:AQ182) -> 108917.81 | AX182: =$C$7+SUMPRODUCT($K$7:$AQ$7,K182:AQ182) -> 11.583989 | AY182: =$C$8+SUMPRODUCT($K$8:$AQ$8,K182:AQ182) -> 11.604595 | AZ182: =$C$9+SUMPRODUCT($K$9:$AQ$9,K182:AQ182) -> 11.571938
B183: =B182 -> NY | C183: 44639 | D183: 3307.5379 | E183: 656.68222 | F183: 340.26754 | G183: 242.17362 | H183: 107860.35 | I183: =SUM(D183:G183) -> 4546.6612 | J183: =YEAR(C183) -> 2022 | K183: =IF(B183=B182,K182+1,1) -> 12 | L183: =K183^2 -> 144 | M183: =LN(L183) -> 4.9698133 | N183: =IF(K183<127,1,0) -> 1 | O183: =MONTH(C183) -> 3 | P183: =IF($O183=P$13,1,0) -> 0 | Q183: =IF($O183=Q$13,1,0) -> 0 | R183: =IF($O183=R$13,1,0) -> 1 | S183: =IF($O183=S$13,1,0) -> 0 | T183: =IF($O183=T$13,1,0) -> 0 | U183: =IF($O183=U$13,1,0) -> 0 | V183: =IF($O183=V$13,1,0) -> 0 | W183: =IF($O183=W$13,1,0) -> 0 | ... AA183: =IF($O183=AA$13,1,0) -> 0 | AB183: =IF($B183=AB$13,1,0) -> 0 | AC183: =IF($B183=AC$13,1,0) -> 0 | AD183: =IF($B183=AD$13,1,0) -> 0 | AE183: =IF($B183=AE$13,1,0) -> 1 | AF183: =IF($B183=AF$13,1,0) -> 0 | AG183: 3307.5379 | AH183: 656.68222 | AI183: 340.26754 | AJ183: 242.17362 | AK183: =LN(H183) -> 11.588593 | AL183: =LN(D183+'Models training data'!$Y$4) -> 8.1883403 | AM183: =LN(E183+'Models training data'!$Y$5) -> 6.5816016 | AN183: =LN(F183+'Models training data'!$Y$6) -> 5.9549199 | AO183: =LN(G183+'Models training data'!$Y$7) -> 5.67599 | AP183: =V183+W183+X183+Y183+Z183 -> 0 | AQ183: =AA183+AC183+AD183+AE183+AF183 -> 1 | AR183: =$C$1+SUMPRODUCT($K$1:$AQ$1,K183:AQ183) -> 84158.884 | AS183: =$C$2+SUMPRODUCT($K$2:$AQ$2,K183:AQ183) -> 108150.84 | AT183: =$C$3+SUMPRODUCT($K$3:$AQ$3,K183:AQ183) -> 11.574059 | AU183: =$C$4+SUMPRODUCT($K$4:$AQ$4,K183:AQ183) -> 108594.19 | AV183: =$C$5+SUMPRODUCT($K$5:$AQ$5,K183:AQ183) -> 11.580561 | AW183: =$C$6+SUMPRODUCT($K$6:$AQ$6,K183:AQ183) -> 108791.91 | AX183: =$C$7+SUMPRODUCT($K$7:$AQ$7,K183:AQ183) -> 11.58254 | AY183: =$C$8+SUMPRODUCT($K$8:$AQ$8,K183:AQ183) -> 11.613144 | AZ183: =$C$9+SUMPRODUCT($K$9:$AQ$9,K183:AQ183) -> 11.584433
B184: =B183 -> NY | C184: 44646 | D184: 3406.2592 | E184: 687.51237 | F184: 357.28089 | G184: 241.59452 | H184: 108452.52 | I184: =SUM(D184:G184) -> 4692.647 | J184: =YEAR(C184) -> 2022 | K184: =IF(B184=B183,K183+1,1) -> 13 | L184: =K184^2 -> 169 | M184: =LN(L184) -> 5.1298987 | N184: =IF(K184<127,1,0) -> 1 | O184: =MONTH(C184) -> 3 | P184: =IF($O184=P$13,1,0) -> 0 | Q184: =IF($O184=Q$13,1,0) -> 0 | R184: =IF($O184=R$13,1,0) -> 1 | S184: =IF($O184=S$13,1,0) -> 0 | T184: =IF($O184=T$13,1,0) -> 0 | U184: =IF($O184=U$13,1,0) -> 0 | V184: =IF($O184=V$13,1,0) -> 0 | W184: =IF($O184=W$13,1,0) -> 0 | ... AA184: =IF($O184=AA$13,1,0) -> 0 | AB184: =IF($B184=AB$13,1,0) -> 0 | AC184: =IF($B184=AC$13,1,0) -> 0 | AD184: =IF($B184=AD$13,1,0) -> 0 | AE184: =IF($B184=AE$13,1,0) -> 1 | AF184: =IF($B184=AF$13,1,0) -> 0 | AG184: 3406.2592 | AH184: 687.51237 | AI184: 357.28089 | AJ184: 241.59452 | AK184: =LN(H184) -> 11.594068 | AL184: =LN(D184+'Models training data'!$Y$4) -> 8.215403 | AM184: =LN(E184+'Models training data'!$Y$5) -> 6.6234335 | AN184: =LN(F184+'Models training data'!$Y$6) -> 5.998091 | AO184: =LN(G184+'Models training data'!$Y$7) -> 5.6740033 | AP184: =V184+W184+X184+Y184+Z184 -> 0 | AQ184: =AA184+AC184+AD184+AE184+AF184 -> 1 | AR184: =$C$1+SUMPRODUCT($K$1:$AQ$1,K184:AQ184) -> 84134.493 | AS184: =$C$2+SUMPRODUCT($K$2:$AQ$2,K184:AQ184) -> 108126.74 | AT184: =$C$3+SUMPRODUCT($K$3:$AQ$3,K184:AQ184) -> 11.573802 | AU184: =$C$4+SUMPRODUCT($K$4:$AQ$4,K184:AQ184) -> 108510.04 | AV184: =$C$5+SUMPRODUCT($K$5:$AQ$5,K184:AQ184) -> 11.579438 | AW184: =$C$6+SUMPRODUCT($K$6:$AQ$6,K184:AQ184) -> 108676.1 | AX184: =$C$7+SUMPRODUCT($K$7:$AQ$7,K184:AQ184) -> 11.581207 | AY184: =$C$8+SUMPRODUCT($K$8:$AQ$8,K184:AQ184) -> 11.620308 | AZ184: =$C$9+SUMPRODUCT($K$9:$AQ$9,K184:AQ184) -> 11.590203
... B328: =B327 -> NY | C328: 45654 | D328: 3770.4463 | E328: 754.55793 | F328: 380.59572 | G328: 273.09806 | H328: 113175.25 | I328: =SUM(D328:G328) -> 5178.698 | J328: =YEAR(C328) -> 2024 | K328: =IF(B328=B327,K327+1,1) -> 157 | L328: =K328^2 -> 24649 | M328: =LN(L328) -> 10.112492 | N328: =IF(K328<127,1,0) -> 0 | O328: =MONTH(C328) -> 12 | P328: =IF($O328=P$13,1,0) -> 0 | Q328: =IF($O328=Q$13,1,0) -> 0 | R328: =IF($O328=R$13,1,0) -> 0 | S328: =IF($O328=S$13,1,0) -> 0 | T328: =IF($O328=T$13,1,0) -> 0 | U328: =IF($O328=U$13,1,0) -> 0 | V328: =IF($O328=V$13,1,0) -> 0 | W328: =IF($O328=W$13,1,0) -> 0 | ... AA328: =IF($O328=AA$13,1,0) -> 1 | AB328: =IF($B328=AB$13,1,0) -> 0 | AC328: =IF($B328=AC$13,1,0) -> 0 | AD328: =IF($B328=AD$13,1,0) -> 0 | AE328: =IF($B328=AE$13,1,0) -> 1 | AF328: =IF($B328=AF$13,1,0) -> 0 | AG328: 3770.4463 | AH328: 754.55793 | AI328: 380.59572 | AJ328: 273.09806 | AK328: =LN(H328) -> 11.636693 | AL328: =LN(D328+'Models training data'!$Y$4) -> 8.3093453 | AM328: =LN(E328+'Models training data'!$Y$5) -> 6.7087798 | AN328: =LN(F328+'Models training data'!$Y$6) -> 6.0543788 | AO328: =LN(G328+'Models training data'!$Y$7) -> 5.7767277 | AP328: =V328+W328+X328+Y328+Z328 -> 0 | AQ328: =AA328+AC328+AD328+AE328+AF328 -> 2 | AR328: =$C$1+SUMPRODUCT($K$1:$AQ$1,K328:AQ328) -> 81456.478 | AS328: =$C$2+SUMPRODUCT($K$2:$AQ$2,K328:AQ328) -> 105488.18 | AT328: =$C$3+SUMPRODUCT($K$3:$AQ$3,K328:AQ328) -> 11.545131 | AU328: =$C$4+SUMPRODUCT($K$4:$AQ$4,K328:AQ328) -> 110138.8 | AV328: =$C$5+SUMPRODUCT($K$5:$AQ$5,K328:AQ328) -> 11.611805 | AW328: =$C$6+SUMPRODUCT($K$6:$AQ$6,K328:AQ328) -> 106297.21 | AX328: =$C$7+SUMPRODUCT($K$7:$AQ$7,K328:AQ328) -> 11.552862 | AY328: =$C$8+SUMPRODUCT($K$8:$AQ$8,K328:AQ328) -> 11.545182 | AZ328: =$C$9+SUMPRODUCT($K$9:$AQ$9,K328:AQ328) -> 11.618082
B329: PA | C329: 44562 | D329: 1822.5 | E329: 360 | F329: 180 | G329: 97.882806 | H329: 95794.566 | I329: =SUM(D329:G329) -> 2460.3828 | J329: =YEAR(C329) -> 2022 | K329: =IF(B329=B328,K328+1,1) -> 1 | L329: =K329^2 -> 1 | M329: =LN(L329) -> 0 | N329: =IF(K329<127,1,0) -> 1 | O329: =MONTH(C329) -> 1 | P329: =IF($O329=P$13,1,0) -> 1 | Q329: =IF($O329=Q$13,1,0) -> 0 | R329: =IF($O329=R$13,1,0) -> 0 | S329: =IF($O329=S$13,1,0) -> 0 | T329: =IF($O329=T$13,1,0) -> 0 | U329: =IF($O329=U$13,1,0) -> 0 | V329: =IF($O329=V$13,1,0) -> 0 | W329: =IF($O329=W$13,1,0) -> 0 | ... AA329: =IF($O329=AA$13,1,0) -> 0 | AB329: =IF($B329=AB$13,1,0) -> 0 | AC329: =IF($B329=AC$13,1,0) -> 0 | AD329: =IF($B329=AD$13,1,0) -> 0 | AE329: =IF($B329=AE$13,1,0) -> 0 | AF329: =IF($B329=AF$13,1,0) -> 1 | AG329: 1822.5 | AH329: 360 | AI329: 180 | AJ329: 97.882806 | AK329: =LN(H329) -> 11.469961 | AL329: =LN(D329+'Models training data'!$Y$4) -> 7.6561984 | AM329: =LN(E329+'Models training data'!$Y$5) -> 6.0521176 | AN329: =LN(F329+'Models training data'!$Y$6) -> 5.4177811 | AO329: =LN(G329+'Models training data'!$Y$7) -> 4.9937349 | AP329: =V329+W329+X329+Y329+Z329 -> 0 | AQ329: =AA329+AC329+AD329+AE329+AF329 -> 1 | AR329: =$C$1+SUMPRODUCT($K$1:$AQ$1,K329:AQ329) -> 86392.099 | AS329: =$C$2+SUMPRODUCT($K$2:$AQ$2,K329:AQ329) -> 97419.007 | AT329: =$C$3+SUMPRODUCT($K$3:$AQ$3,K329:AQ329) -> 11.47582 | AU329: =$C$4+SUMPRODUCT($K$4:$AQ$4,K329:AQ329) -> 98524.515 | AV329: =$C$5+SUMPRODUCT($K$5:$AQ$5,K329:AQ329) -> 11.491829 | AW329: =$C$6+SUMPRODUCT($K$6:$AQ$6,K329:AQ329) -> 100609.99 | AX329: =$C$7+SUMPRODUCT($K$7:$AQ$7,K329:AQ329) -> 11.513547 | AY329: =$C$8+SUMPRODUCT($K$8:$AQ$8,K329:AQ329) -> 11.527965 | AZ329: =$C$9+SUMPRODUCT($K$9:$AQ$9,K329:AQ329) -> 11.46238
B330: =B329 -> PA | C330: 44569 | D330: 1849.8375 | E330: 369 | F330: 188.1 | G330: 121.11893 | H330: 97466.371 | I330: =SUM(D330:G330) -> 2528.0564 | J330: =YEAR(C330) -> 2022 | K330: =IF(B330=B329,K329+1,1) -> 2 | L330: =K330^2 -> 4 | M330: =LN(L330) -> 1.3862944 | N330: =IF(K330<127,1,0) -> 1 | O330: =MONTH(C330) -> 1 | P330: =IF($O330=P$13,1,0) -> 1 | Q330: =IF($O330=Q$13,1,0) -> 0 | R330: =IF($O330=R$13,1,0) -> 0 | S330: =IF($O330=S$13,1,0) -> 0 | T330: =IF($O330=T$13,1,0) -> 0 | U330: =IF($O330=U$13,1,0) -> 0 | V330: =IF($O330=V$13,1,0) -> 0 | W330: =IF($O330=W$13,1,0) -> 0 | ... AA330: =IF($O330=AA$13,1,0) -> 0 | AB330: =IF($B330=AB$13,1,0) -> 0 | AC330: =IF($B330=AC$13,1,0) -> 0 | AD330: =IF($B330=AD$13,1,0) -> 0 | AE330: =IF($B330=AE$13,1,0) -> 0 | AF330: =IF($B330=AF$13,1,0) -> 1 | AG330: 1849.8375 | AH330: 369 | AI330: 188.1 | AJ330: 121.11893 | AK330: =LN(H330) -> 11.487263 | AL330: =LN(D330+'Models training data'!$Y$4) -> 7.6690489 | AM330: =LN(E330+'Models training data'!$Y$5) -> 6.0730724 | AN330: =LN(F330+'Models training data'!$Y$6) -> 5.4530899 | AO330: =LN(G330+'Models training data'!$Y$7) -> 5.1400386 | AP330: =V330+W330+X330+Y330+Z330 -> 0 | AQ330: =AA330+AC330+AD330+AE330+AF330 -> 1 | AR330: =$C$1+SUMPRODUCT($K$1:$AQ$1,K330:AQ330) -> 86367.709 | AS330: =$C$2+SUMPRODUCT($K$2:$AQ$2,K330:AQ330) -> 97394.91 | AT330: =$C$3+SUMPRODUCT($K$3:$AQ$3,K330:AQ330) -> 11.475563 | AU330: =$C$4+SUMPRODUCT($K$4:$AQ$4,K330:AQ330) -> 98427.405 | AV330: =$C$5+SUMPRODUCT($K$5:$AQ$5,K330:AQ330) -> 11.49052 | AW330: =$C$6+SUMPRODUCT($K$6:$AQ$6,K330:AQ330) -> 99607.069 | AX330: =$C$7+SUMPRODUCT($K$7:$AQ$7,K330:AQ330) -> 11.502003 | AY330: =$C$8+SUMPRODUCT($K$8:$AQ$8,K330:AQ330) -> 11.533969 | AZ330: =$C$9+SUMPRODUCT($K$9:$AQ$9,K330:AQ330) -> 11.484837
B331: =B330 -> PA | C331: 44576 | D331: 1897.6781 | E331: 382.95 | F331: 197.415 | G331: 139.89572 | H331: 98848.329 | I331: =SUM(D331:G331) -> 2617.9388 | J331: =YEAR(C331) -> 2022 | K331: =IF(B331=B330,K330+1,1) -> 3 | L331: =K331^2 -> 9 | M331: =LN(L331) -> 2.1972246 | N331: =IF(K331<127,1,0) -> 1 | O331: =MONTH(C331) -> 1 | P331: =IF($O331=P$13,1,0) -> 1 | Q331: =IF($O331=Q$13,1,0) -> 0 | R331: =IF($O331=R$13,1,0) -> 0 | S331: =IF($O331=S$13,1,0) -> 0 | T331: =IF($O331=T$13,1,0) -> 0 | U331: =IF($O331=U$13,1,0) -> 0 | V331: =IF($O331=V$13,1,0) -> 0 | W331: =IF($O331=W$13,1,0) -> 0 | ... AA331: =IF($O331=AA$13,1,0) -> 0 | AB331: =IF($B331=AB$13,1,0) -> 0 | AC331: =IF($B331=AC$13,1,0) -> 0 | AD331: =IF($B331=AD$13,1,0) -> 0 | AE331: =IF($B331=AE$13,1,0) -> 0 | AF331: =IF($B331=AF$13,1,0) -> 1 | AG331: 1897.6781 | AH331: 382.95 | AI331: 197.415 | AJ331: 139.89572 | AK331: =LN(H331) -> 11.501342 | AL331: =LN(D331+'Models training data'!$Y$4) -> 7.6911475 | AM331: =LN(E331+'Models training data'!$Y$5) -> 6.1047086 | AN331: =LN(F331+'Models training data'!$Y$6) -> 5.4922112 | AO331: =LN(G331+'Models training data'!$Y$7) -> 5.2443845 | AP331: =V331+W331+X331+Y331+Z331 -> 0 | AQ331: =AA331+AC331+AD331+AE331+AF331 -> 1 | AR331: =$C$1+SUMPRODUCT($K$1:$AQ$1,K331:AQ331) -> 86343.318 | AS331: =$C$2+SUMPRODUCT($K$2:$AQ$2,K331:AQ331) -> 97370.812 | AT331: =$C$3+SUMPRODUCT($K$3:$AQ$3,K331:AQ331) -> 11.475305 | AU331: =$C$4+SUMPRODUCT($K$4:$AQ$4,K331:AQ331) -> 98331.474 | AV331: =$C$5+SUMPRODUCT($K$5:$AQ$5,K331:AQ331) -> 11.489227 | AW331: =$C$6+SUMPRODUCT($K$6:$AQ$6,K331:AQ331) -> 99020.399 | AX331: =$C$7+SUMPRODUCT($K$7:$AQ$7,K331:AQ331) -> 11.495249 | AY331: =$C$8+SUMPRODUCT($K$8:$AQ$8,K331:AQ331) -> 11.540406 | AZ331: =$C$9+SUMPRODUCT($K$9:$AQ$9,K331:AQ331) -> 11.502974
B332: =B331 -> PA | C332: 44583 | D332: 1961.3062 | E332: 399.8475 | F332: 207.27675 | G332: 146.87385 | H332: 99729.253 | I332: =SUM(D332:G332) -> 2715.3043 | J332: =YEAR(C332) -> 2022 | K332: =IF(B332=B331,K331+1,1) -> 4 | L332: =K332^2 -> 16 | M332: =LN(L332) -> 2.7725887 | N332: =IF(K332<127,1,0) -> 1 | O332: =MONTH(C332) -> 1 | P332: =IF($O332=P$13,1,0) -> 1 | Q332: =IF($O332=Q$13,1,0) -> 0 | R332: =IF($O332=R$13,1,0) -> 0 | S332: =IF($O332=S$13,1,0) -> 0 | T332: =IF($O332=T$13,1,0) -> 0 | U332: =IF($O332=U$13,1,0) -> 0 | V332: =IF($O332=V$13,1,0) -> 0 | W332: =IF($O332=W$13,1,0) -> 0 | ... AA332: =IF($O332=AA$13,1,0) -> 0 | AB332: =IF($B332=AB$13,1,0) -> 0 | AC332: =IF($B332=AC$13,1,0) -> 0 | AD332: =IF($B332=AD$13,1,0) -> 0 | AE332: =IF($B332=AE$13,1,0) -> 0 | AF332: =IF($B332=AF$13,1,0) -> 1 | AG332: 1961.3062 | AH332: 399.8475 | AI332: 207.27675 | AJ332: 146.87385 | AK332: =LN(H332) -> 11.510214 | AL332: =LN(D332+'Models training data'!$Y$4) -> 7.7198017 | AM332: =LN(E332+'Models training data'!$Y$5) -> 6.1417354 | AN332: =LN(F332+'Models training data'!$Y$6) -> 5.5320258 | AO332: =LN(G332+'Models training data'!$Y$7) -> 5.2805468 | AP332: =V332+W332+X332+Y332+Z332 -> 0 | AQ332: =AA332+AC332+AD332+AE332+AF332 -> 1 | AR332: =$C$1+SUMPRODUCT($K$1:$AQ$1,K332:AQ332) -> 86318.928 | AS332: =$C$2+SUMPRODUCT($K$2:$AQ$2,K332:AQ332) -> 97346.715 | AT332: =$C$3+SUMPRODUCT($K$3:$AQ$3,K332:AQ332) -> 11.475048 | AU332: =$C$4+SUMPRODUCT($K$4:$AQ$4,K332:AQ332) -> 98236.722 | AV332: =$C$5+SUMPRODUCT($K$5:$AQ$5,K332:AQ332) -> 11.487951 | AW332: =$C$6+SUMPRODUCT($K$6:$AQ$6,K332:AQ332) -> 98604.15 | AX332: =$C$7+SUMPRODUCT($K$7:$AQ$7,K332:AQ332) -> 11.490458 | AY332: =$C$8+SUMPRODUCT($K$8:$AQ$8,K332:AQ332) -> 11.545702 | AZ332: =$C$9+SUMPRODUCT($K$9:$AQ$9,K332:AQ332) -> 11.513
B333: =B332 -> PA | C333: 44590 | D333: 2037.4924 | E333: 418.71488 | F333: 217.63969 | G333: 148.35573 | H333: 100413.19 | I333: =SUM(D333:G333) -> 2822.2026 | J333: =YEAR(C333) -> 2022 | K333: =IF(B333=B332,K332+1,1) -> 5 | L333: =K333^2 -> 25 | M333: =LN(L333) -> 3.2188758 | N333: =IF(K333<127,1,0) -> 1 | O333: =MONTH(C333) -> 1 | P333: =IF($O333=P$13,1,0) -> 1 | Q333: =IF($O333=Q$13,1,0) -> 0 | R333: =IF($O333=R$13,1,0) -> 0 | S333: =IF($O333=S$13,1,0) -> 0 | T333: =IF($O333=T$13,1,0) -> 0 | U333: =IF($O333=U$13,1,0) -> 0 | V333: =IF($O333=V$13,1,0) -> 0 | W333: =IF($O333=W$13,1,0) -> 0 | ... AA333: =IF($O333=AA$13,1,0) -> 0 | AB333: =IF($B333=AB$13,1,0) -> 0 | AC333: =IF($B333=AC$13,1,0) -> 0 | AD333: =IF($B333=AD$13,1,0) -> 0 | AE333: =IF($B333=AE$13,1,0) -> 0 | AF333: =IF($B333=AF$13,1,0) -> 1 | AG333: 2037.4924 | AH333: 418.71488 | AI333: 217.63969 | AJ333: 148.35573 | AK333: =LN(H333) -> 11.517049 | AL333: =LN(D333+'Models training data'!$Y$4) -> 7.7530651 | AM333: =LN(E333+'Models training data'!$Y$5) -> 6.1815206 | AN333: =LN(F333+'Models training data'!$Y$6) -> 5.5722231 | AO333: =LN(G333+'Models training data'!$Y$7) -> 5.2880608 | AP333: =V333+W333+X333+Y333+Z333 -> 0 | AQ333: =AA333+AC333+AD333+AE333+AF333 -> 1 | AR333: =$C$1+SUMPRODUCT($K$1:$AQ$1,K333:AQ333) -> 86294.538 | AS333: =$C$2+SUMPRODUCT($K$2:$AQ$2,K333:AQ333) -> 97322.617 | AT333: =$C$3+SUMPRODUCT($K$3:$AQ$3,K333:AQ333) -> 11.47479 | AU333: =$C$4+SUMPRODUCT($K$4:$AQ$4,K333:AQ333) -> 98143.149 | AV333: =$C$5+SUMPRODUCT($K$5:$AQ$5,K333:AQ333) -> 11.486693 | AW333: =$C$6+SUMPRODUCT($K$6:$AQ$6,K333:AQ333) -> 98281.282 | AX333: =$C$7+SUMPRODUCT($K$7:$AQ$7,K333:AQ333) -> 11.486741 | AY333: =$C$8+SUMPRODUCT($K$8:$AQ$8,K333:AQ333) -> 11.550671 | AZ333: =$C$9+SUMPRODUCT($K$9:$AQ$9,K333:AQ333) -> 11.519666
B334: =B333 -> PA | C334: 44597 | D334: 2124.0516 | E334: 439.08812 | F334: 228.52158 | G334: 150.14247 | H334: 100768.57 | I334: =SUM(D334:G334) -> 2941.8038 | J334: =YEAR(C334) -> 2022 | K334: =IF(B334=B333,K333+1,1) -> 6 | L334: =K334^2 -> 36 | M334: =LN(L334) -> 3.5835189 | N334: =IF(K334<127,1,0) -> 1 | O334: =MONTH(C334) -> 2 | P334: =IF($O334=P$13,1,0) -> 0 | Q334: =IF($O334=Q$13,1,0) -> 1 | R334: =IF($O334=R$13,1,0) -> 0 | S334: =IF($O334=S$13,1,0) -> 0 | T334: =IF($O334=T$13,1,0) -> 0 | U334: =IF($O334=U$13,1,0) -> 0 | V334: =IF($O334=V$13,1,0) -> 0 | W334: =IF($O334=W$13,1,0) -> 0 | ... AA334: =IF($O334=AA$13,1,0) -> 0 | AB334: =IF($B334=AB$13,1,0) -> 0 | AC334: =IF($B334=AC$13,1,0) -> 0 | AD334: =IF($B334=AD$13,1,0) -> 0 | AE334: =IF($B334=AE$13,1,0) -> 0 | AF334: =IF($B334=AF$13,1,0) -> 1 | AG334: 2124.0516 | AH334: 439.08812 | AI334: 228.52158 | AJ334: 150.14247 | AK334: =LN(H334) -> 11.520582 | AL334: =LN(D334+'Models training data'!$Y$4) -> 7.7895615 | AM334: =LN(E334+'Models training data'!$Y$5) -> 6.2227751 | AN334: =LN(F334+'Models training data'!$Y$6) -> 5.6127633 | AO334: =LN(G334+'Models training data'!$Y$7) -> 5.2970461 | AP334: =V334+W334+X334+Y334+Z334 -> 0 | AQ334: =AA334+AC334+AD334+AE334+AF334 -> 1 | AR334: =$C$1+SUMPRODUCT($K$1:$AQ$1,K334:AQ334) -> 85220.436 | AS334: =$C$2+SUMPRODUCT($K$2:$AQ$2,K334:AQ334) -> 96246.409 | AT334: =$C$3+SUMPRODUCT($K$3:$AQ$3,K334:AQ334) -> 11.462838 | AU334: =$C$4+SUMPRODUCT($K$4:$AQ$4,K334:AQ334) -> 97118.789 | AV334: =$C$5+SUMPRODUCT($K$5:$AQ$5,K334:AQ334) -> 11.475503 | AW334: =$C$6+SUMPRODUCT($K$6:$AQ$6,K334:AQ334) -> 97575.173 | AX334: =$C$7+SUMPRODUCT($K$7:$AQ$7,K334:AQ334) -> 11.479192 | AY334: =$C$8+SUMPRODUCT($K$8:$AQ$8,K334:AQ334) -> 11.556137 | AZ334: =$C$9+SUMPRODUCT($K$9:$AQ$9,K334:AQ334) -> 11.526643
B335: =B334 -> PA | C335: 44604 | D335: 2219.5334 | E335: 460.76127 | F335: 239.94765 | G335: 171.47501 | H335: 102175.66 | I335: =SUM(D335:G335) -> 3091.7173 | J335: =YEAR(C335) -> 2022 | K335: =IF(B335=B334,K334+1,1) -> 7 | L335: =K335^2 -> 49 | M335: =LN(L335) -> 3.8918203 | N335: =IF(K335<127,1,0) -> 1 | O335: =MONTH(C335) -> 2 | P335: =IF($O335=P$13,1,0) -> 0 | Q335: =IF($O335=Q$13,1,0) -> 1 | R335: =IF($O335=R$13,1,0) -> 0 | S335: =IF($O335=S$13,1,0) -> 0 | T335: =IF($O335=T$13,1,0) -> 0 | U335: =IF($O335=U$13,1,0) -> 0 | V335: =IF($O335=V$13,1,0) -> 0 | W335: =IF($O335=W$13,1,0) -> 0 | ... AA335: =IF($O335=AA$13,1,0) -> 0 | AB335: =IF($B335=AB$13,1,0) -> 0 | AC335: =IF($B335=AC$13,1,0) -> 0 | AD335: =IF($B335=AD$13,1,0) -> 0 | AE335: =IF($B335=AE$13,1,0) -> 0 | AF335: =IF($B335=AF$13,1,0) -> 1 | AG335: 2219.5334 | AH335: 460.76127 | AI335: 239.94765 | AJ335: 171.47501 | AK335: =LN(H335) -> 11.534449 | AL335: =LN(D335+'Models training data'!$Y$4) -> 7.8283329 | AM335: =LN(E335+'Models training data'!$Y$5) -> 6.2648702 | AN335: =LN(F335+'Models training data'!$Y$6) -> 5.6536329 | AO335: =LN(G335+'Models training data'!$Y$7) -> 5.3985176 | AP335: =V335+W335+X335+Y335+Z335 -> 0 | AQ335: =AA335+AC335+AD335+AE335+AF335 -> 1 | AR335: =$C$1+SUMPRODUCT($K$1:$AQ$1,K335:AQ335) -> 85196.046 | AS335: =$C$2+SUMPRODUCT($K$2:$AQ$2,K335:AQ335) -> 96222.312 | AT335: =$C$3+SUMPRODUCT($K$3:$AQ$3,K335:AQ335) -> 11.462581 | AU335: =$C$4+SUMPRODUCT($K$4:$AQ$4,K335:AQ335) -> 97027.573 | AV335: =$C$5+SUMPRODUCT($K$5:$AQ$5,K335:AQ335) -> 11.474278 | AW335: =$C$6+SUMPRODUCT($K$6:$AQ$6,K335:AQ335) -> 97352.131 | AX335: =$C$7+SUMPRODUCT($K$7:$AQ$7,K335:AQ335) -> 11.476624 | AY335: =$C$8+SUMPRODUCT($K$8:$AQ$8,K335:AQ335) -> 11.565116 | AZ335: =$C$9+SUMPRODUCT($K$9:$AQ$9,K335:AQ335) -> 11.545207
B336: =B335 -> PA | C336: 44611 | D336: 2323.0055 | E336: 483.65871 | F336: 251.94503 | G336: 163.84136 | H336: 102568.8 | I336: =SUM(D336:G336) -> 3222.4506 | J336: =YEAR(C336) -> 2022 | K336: =IF(B336=B335,K335+1,1) -> 8 | L336: =K336^2 -> 64 | M336: =LN(L336) -> 4.1588831 | N336: =IF(K336<127,1,0) -> 1 | O336: =MONTH(C336) -> 2 | P336: =IF($O336=P$13,1,0) -> 0 | Q336: =IF($O336=Q$13,1,0) -> 1 | R336: =IF($O336=R$13,1,0) -> 0 | S336: =IF($O336=S$13,1,0) -> 0 | T336: =IF($O336=T$13,1,0) -> 0 | U336: =IF($O336=U$13,1,0) -> 0 | V336: =IF($O336=V$13,1,0) -> 0 | W336: =IF($O336=W$13,1,0) -> 0 | ... AA336: =IF($O336=AA$13,1,0) -> 0 | AB336: =IF($B336=AB$13,1,0) -> 0 | AC336: =IF($B336=AC$13,1,0) -> 0 | AD336: =IF($B336=AD$13,1,0) -> 0 | AE336: =IF($B336=AE$13,1,0) -> 0 | AF336: =IF($B336=AF$13,1,0) -> 1 | AG336: 2323.0055 | AH336: 483.65871 | AI336: 251.94503 | AJ336: 163.84136 | AK336: =LN(H336) -> 11.538289 | AL336: =LN(D336+'Models training data'!$Y$4) -> 7.8687181 | AM336: =LN(E336+'Models training data'!$Y$5) -> 6.3074986 | AN336: =LN(F336+'Models training data'!$Y$6) -> 5.6948208 | AO336: =LN(G336+'Models training data'!$Y$7) -> 5.3633782 | AP336: =V336+W336+X336+Y336+Z336 -> 0 | AQ336: =AA336+AC336+AD336+AE336+AF336 -> 1 | AR336: =$C$1+SUMPRODUCT($K$1:$AQ$1,K336:AQ336) -> 85171.656 | AS336: =$C$2+SUMPRODUCT($K$2:$AQ$2,K336:AQ336) -> 96198.215 | AT336: =$C$3+SUMPRODUCT($K$3:$AQ$3,K336:AQ336) -> 11.462323 | AU336: =$C$4+SUMPRODUCT($K$4:$AQ$4,K336:AQ336) -> 96937.536 | AV336: =$C$5+SUMPRODUCT($K$5:$AQ$5,K336:AQ336) -> 11.47307 | AW336: =$C$6+SUMPRODUCT($K$6:$AQ$6,K336:AQ336) -> 97158.924 | AX336: =$C$7+SUMPRODUCT($K$7:$AQ$7,K336:AQ336) -> 11.4744 | AY336: =$C$8+SUMPRODUCT($K$8:$AQ$8,K336:AQ336) -> 11.569843 | AZ336: =$C$9+SUMPRODUCT($K$9:$AQ$9,K336:AQ336) -> 11.546856
B337: =B336 -> PA | C337: 44618 | D337: 2433.9026 | E337: 507.77134 | F337: 264.54229 | G337: 173.56463 | H337: 103554.35 | I337: =SUM(D337:G337) -> 3379.7809 | J337: =YEAR(C337) -> 2022 | K337: =IF(B337=B336,K336+1,1) -> 9 | L337: =K337^2 -> 81 | M337: =LN(L337) -> 4.3944492 | N337: =IF(K337<127,1,0) -> 1 | O337: =MONTH(C337) -> 2 | P337: =IF($O337=P$13,1,0) -> 0 | Q337: =IF($O337=Q$13,1,0) -> 1 | R337: =IF($O337=R$13,1,0) -> 0 | S337: =IF($O337=S$13,1,0) -> 0 | T337: =IF($O337=T$13,1,0) -> 0 | U337: =IF($O337=U$13,1,0) -> 0 | V337: =IF($O337=V$13,1,0) -> 0 | W337: =IF($O337=W$13,1,0) -> 0 | ... AA337: =IF($O337=AA$13,1,0) -> 0 | AB337: =IF($B337=AB$13,1,0) -> 0 | AC337: =IF($B337=AC$13,1,0) -> 0 | AD337: =IF($B337=AD$13,1,0) -> 0 | AE337: =IF($B337=AE$13,1,0) -> 0 | AF337: =IF($B337=AF$13,1,0) -> 1 | AG337: 2433.9026 | AH337: 507.77134 | AI337: 264.54229 | AJ337: 173.56463 | AK337: =LN(H337) -> 11.547852 | AL337: =LN(D337+'Models training data'!$Y$4) -> 7.9102638 | AM337: =LN(E337+'Models training data'!$Y$5) -> 6.3505077 | AN337: =LN(F337+'Models training data'!$Y$6) -> 5.7363167 | AO337: =LN(G337+'Models training data'!$Y$7) -> 5.4079251 | AP337: =V337+W337+X337+Y337+Z337 -> 0 | AQ337: =AA337+AC337+AD337+AE337+AF337 -> 1 | AR337: =$C$1+SUMPRODUCT($K$1:$AQ$1,K337:AQ337) -> 85147.265 | AS337: =$C$2+SUMPRODUCT($K$2:$AQ$2,K337:AQ337) -> 96174.117 | AT337: =$C$3+SUMPRODUCT($K$3:$AQ$3,K337:AQ337) -> 11.462065 | AU337: =$C$4+SUMPRODUCT($K$4:$AQ$4,K337:AQ337) -> 96848.677 | AV337: =$C$5+SUMPRODUCT($K$5:$AQ$5,K337:AQ337) -> 11.471879 | AW337: =$C$6+SUMPRODUCT($K$6:$AQ$6,K337:AQ337) -> 96988.503 | AX337: =$C$7+SUMPRODUCT($K$7:$AQ$7,K337:AQ337) -> 11.472438 | AY337: =$C$8+SUMPRODUCT($K$8:$AQ$8,K337:AQ337) -> 11.577696 | AZ337: =$C$9+SUMPRODUCT($K$9:$AQ$9,K337:AQ337) -> 11.558466
B338: =B337 -> PA | C338: 44625 | D338: 2551.9206 | E338: 533.12475 | F338: 277.7694 | G338: 187.29485 | H338: 104647.4 | I338: =SUM(D338:G338) -> 3550.1096 | J338: =YEAR(C338) -> 2022 | K338: =IF(B338=B337,K337+1,1) -> 10 | L338: =K338^2 -> 100 | M338: =LN(L338) -> 4.6051702 | N338: =IF(K338<127,1,0) -> 1 | O338: =MONTH(C338) -> 3 | P338: =IF($O338=P$13,1,0) -> 0 | Q338: =IF($O338=Q$13,1,0) -> 0 | R338: =IF($O338=R$13,1,0) -> 1 | S338: =IF($O338=S$13,1,0) -> 0 | T338: =IF($O338=T$13,1,0) -> 0 | U338: =IF($O338=U$13,1,0) -> 0 | V338: =IF($O338=V$13,1,0) -> 0 | W338: =IF($O338=W$13,1,0) -> 0 | ... AA338: =IF($O338=AA$13,1,0) -> 0 | AB338: =IF($B338=AB$13,1,0) -> 0 | AC338: =IF($B338=AC$13,1,0) -> 0 | AD338: =IF($B338=AD$13,1,0) -> 0 | AE338: =IF($B338=AE$13,1,0) -> 0 | AF338: =IF($B338=AF$13,1,0) -> 1 | AG338: 2551.9206 | AH338: 533.12475 | AI338: 277.7694 | AJ338: 187.29485 | AK338: =LN(H338) -> 11.558352 | AL338: =LN(D338+'Models training data'!$Y$4) -> 7.9526599 | AM338: =LN(E338+'Models training data'!$Y$5) -> 6.3938195 | AN338: =LN(F338+'Models training data'!$Y$6) -> 5.7781101 | AO338: =LN(G338+'Models training data'!$Y$7) -> 5.4676309 | AP338: =V338+W338+X338+Y338+Z338 -> 0 | AQ338: =AA338+AC338+AD338+AE338+AF338 -> 1 | AR338: =$C$1+SUMPRODUCT($K$1:$AQ$1,K338:AQ338) -> 84207.664 | AS338: =$C$2+SUMPRODUCT($K$2:$AQ$2,K338:AQ338) -> 95232.409 | AT338: =$C$3+SUMPRODUCT($K$3:$AQ$3,K338:AQ338) -> 11.451 | AU338: =$C$4+SUMPRODUCT($K$4:$AQ$4,K338:AQ338) -> 95799.391 | AV338: =$C$5+SUMPRODUCT($K$5:$AQ$5,K338:AQ338) -> 11.459284 | AW338: =$C$6+SUMPRODUCT($K$6:$AQ$6,K338:AQ338) -> 96089.092 | AX338: =$C$7+SUMPRODUCT($K$7:$AQ$7,K338:AQ338) -> 11.462003 | AY338: =$C$8+SUMPRODUCT($K$8:$AQ$8,K338:AQ338) -> 11.586546 | AZ338: =$C$9+SUMPRODUCT($K$9:$AQ$9,K338:AQ338) -> 11.572009
B339: =B338 -> PA | C339: 44632 | D339: 2676.9425 | E339: 559.76341 | F339: 291.65787 | G339: 187.05114 | H339: 105299.4 | I339: =SUM(D339:G339) -> 3715.4149 | J339: =YEAR(C339) -> 2022 | K339: =IF(B339=B338,K338+1,1) -> 11 | L339: =K339^2 -> 121 | M339: =LN(L339) -> 4.7957905 | N339: =IF(K339<127,1,0) -> 1 | O339: =MONTH(C339) -> 3 | P339: =IF($O339=P$13,1,0) -> 0 | Q339: =IF($O339=Q$13,1,0) -> 0 | R339: =IF($O339=R$13,1,0) -> 1 | S339: =IF($O339=S$13,1,0) -> 0 | T339: =IF($O339=T$13,1,0) -> 0 | U339: =IF($O339=U$13,1,0) -> 0 | V339: =IF($O339=V$13,1,0) -> 0 | W339: =IF($O339=W$13,1,0) -> 0 | ... AA339: =IF($O339=AA$13,1,0) -> 0 | AB339: =IF($B339=AB$13,1,0) -> 0 | AC339: =IF($B339=AC$13,1,0) -> 0 | AD339: =IF($B339=AD$13,1,0) -> 0 | AE339: =IF($B339=AE$13,1,0) -> 0 | AF339: =IF($B339=AF$13,1,0) -> 1 | AG339: 2676.9425 | AH339: 559.76341 | AI339: 291.65787 | AJ339: 187.05114 | AK339: =LN(H339) -> 11.564563 | AL339: =LN(D339+'Models training data'!$Y$4) -> 7.9956939 | AM339: =LN(E339+'Models training data'!$Y$5) -> 6.4373924 | AN339: =LN(F339+'Models training data'!$Y$6) -> 5.8201908 | AO339: =LN(G339+'Models training data'!$Y$7) -> 5.4666016 | AP339: =V339+W339+X339+Y339+Z339 -> 0 | AQ339: =AA339+AC339+AD339+AE339+AF339 -> 1 | AR339: =$C$1+SUMPRODUCT($K$1:$AQ$1,K339:AQ339) -> 84183.274 | AS339: =$C$2+SUMPRODUCT($K$2:$AQ$2,K339:AQ339) -> 95208.312 | AT339: =$C$3+SUMPRODUCT($K$3:$AQ$3,K339:AQ339) -> 11.450743 | AU339: =$C$4+SUMPRODUCT($K$4:$AQ$4,K339:AQ339) -> 95712.89 | AV339: =$C$5+SUMPRODUCT($K$5:$AQ$5,K339:AQ339) -> 11.458127 | AW339: =$C$6+SUMPRODUCT($K$6:$AQ$6,K339:AQ339) -> 95951.187 | AX339: =$C$7+SUMPRODUCT($K$7:$AQ$7,K339:AQ339) -> 11.460415 | AY339: =$C$8+SUMPRODUCT($K$8:$AQ$8,K339:AQ339) -> 11.59353 | AZ339: =$C$9+SUMPRODUCT($K$9:$AQ$9,K339:AQ339) -> 11.578044
B340: =B339 -> PA | C340: 44639 | D340: 2808.9878 | E340: 587.74279 | F340: 306.24076 | G340: 199.33389 | H340: 106322.88 | I340: =SUM(D340:G340) -> 3902.3053 | J340: =YEAR(C340) -> 2022 | K340: =IF(B340=B339,K339+1,1) -> 12 | L340: =K340^2 -> 144 | M340: =LN(L340) -> 4.9698133 | N340: =IF(K340<127,1,0) -> 1 | O340: =MONTH(C340) -> 3 | P340: =IF($O340=P$13,1,0) -> 0 | Q340: =IF($O340=Q$13,1,0) -> 0 | R340: =IF($O340=R$13,1,0) -> 1 | S340: =IF($O340=S$13,1,0) -> 0 | T340: =IF($O340=T$13,1,0) -> 0 | U340: =IF($O340=U$13,1,0) -> 0 | V340: =IF($O340=V$13,1,0) -> 0 | W340: =IF($O340=W$13,1,0) -> 0 | ... AA340: =IF($O340=AA$13,1,0) -> 0 | AB340: =IF($B340=AB$13,1,0) -> 0 | AC340: =IF($B340=AC$13,1,0) -> 0 | AD340: =IF($B340=AD$13,1,0) -> 0 | AE340: =IF($B340=AE$13,1,0) -> 0 | AF340: =IF($B340=AF$13,1,0) -> 1 | AG340: 2808.9878 | AH340: 587.74279 | AI340: 306.24076 | AJ340: 199.33389 | AK340: =LN(H340) -> 11.574236 | AL340: =LN(D340+'Models training data'!$Y$4) -> 8.0392201 | AM340: =LN(E340+'Models training data'!$Y$5) -> 6.4812017 | AN340: =LN(F340+'Models training data'!$Y$6) -> 5.8625489 | AO340: =LN(G340+'Models training data'!$Y$7) -> 5.5172012 | AP340: =V340+W340+X340+Y340+Z340 -> 0 | AQ340: =AA340+AC340+AD340+AE340+AF340 -> 1 | AR340: =$C$1+SUMPRODUCT($K$1:$AQ$1,K340:AQ340) -> 84158.884 | AS340: =$C$2+SUMPRODUCT($K$2:$AQ$2,K340:AQ340) -> 95184.214 | AT340: =$C$3+SUMPRODUCT($K$3:$AQ$3,K340:AQ340) -> 11.450485 | AU340: =$C$4+SUMPRODUCT($K$4:$AQ$4,K340:AQ340) -> 95627.567 | AV340: =$C$5+SUMPRODUCT($K$5:$AQ$5,K340:AQ340) -> 11.456987 | AW340: =$C$6+SUMPRODUCT($K$6:$AQ$6,K340:AQ340) -> 95825.29 | AX340: =$C$7+SUMPRODUCT($K$7:$AQ$7,K340:AQ340) -> 11.458966 | AY340: =$C$8+SUMPRODUCT($K$8:$AQ$8,K340:AQ340) -> 11.602885 | AZ340: =$C$9+SUMPRODUCT($K$9:$AQ$9,K340:AQ340) -> 11.590537
B341: =B340 -> PA | C341: 44646 | D341: 2948.1759 | E341: 617.12553 | F341: 321.5528 | G341: 231.02083 | H341: 107826.23 | I341: =SUM(D341:G341) -> 4117.8751 | J341: =YEAR(C341) -> 2022 | K341: =IF(B341=B340,K340+1,1) -> 13 | L341: =K341^2 -> 169 | M341: =LN(L341) -> 5.1298987 | N341: =IF(K341<127,1,0) -> 1 | O341: =MONTH(C341) -> 3 | P341: =IF($O341=P$13,1,0) -> 0 | Q341: =IF($O341=Q$13,1,0) -> 0 | R341: =IF($O341=R$13,1,0) -> 1 | S341: =IF($O341=S$13,1,0) -> 0 | T341: =IF($O341=T$13,1,0) -> 0 | U341: =IF($O341=U$13,1,0) -> 0 | V341: =IF($O341=V$13,1,0) -> 0 | W341: =IF($O341=W$13,1,0) -> 0 | ... AA341: =IF($O341=AA$13,1,0) -> 0 | AB341: =IF($B341=AB$13,1,0) -> 0 | AC341: =IF($B341=AC$13,1,0) -> 0 | AD341: =IF($B341=AD$13,1,0) -> 0 | AE341: =IF($B341=AE$13,1,0) -> 0 | AF341: =IF($B341=AF$13,1,0) -> 1 | AG341: 2948.1759 | AH341: 617.12553 | AI341: 321.5528 | AJ341: 231.02083 | AK341: =LN(H341) -> 11.588276 | AL341: =LN(D341+'Models training data'!$Y$4) -> 8.083138 | AM341: =LN(E341+'Models training data'!$Y$5) -> 6.5252314 | AN341: =LN(F341+'Models training data'!$Y$6) -> 5.9051746 | AO341: =LN(G341+'Models training data'!$Y$7) -> 5.6370166 | AP341: =V341+W341+X341+Y341+Z341 -> 0 | AQ341: =AA341+AC341+AD341+AE341+AF341 -> 1 | AR341: =$C$1+SUMPRODUCT($K$1:$AQ$1,K341:AQ341) -> 84134.493 | AS341: =$C$2+SUMPRODUCT($K$2:$AQ$2,K341:AQ341) -> 95160.117 | AT341: =$C$3+SUMPRODUCT($K$3:$AQ$3,K341:AQ341) -> 11.450228 | AU341: =$C$4+SUMPRODUCT($K$4:$AQ$4,K341:AQ341) -> 95543.423 | AV341: =$C$5+SUMPRODUCT($K$5:$AQ$5,K341:AQ341) -> 11.455864 | AW341: =$C$6+SUMPRODUCT($K$6:$AQ$6,K341:AQ341) -> 95709.476 | AX341: =$C$7+SUMPRODUCT($K$7:$AQ$7,K341:AQ341) -> 11.457633 | AY341: =$C$8+SUMPRODUCT($K$8:$AQ$8,K341:AQ341) -> 11.615722 | AZ341: =$C$9+SUMPRODUCT($K$9:$AQ$9,K341:AQ341) -> 11.611671
... B485: =B484 -> PA | C485: 45654 | D485: 1131.1517 | E485: 226.36738 | F485: 114.17871 | G485: 72.408792 | H485: 90890.694 | I485: =SUM(D485:G485) -> 1544.1066 | J485: =YEAR(C485) -> 2024 | K485: =IF(B485=B484,K484+1,1) -> 157 | L485: =K485^2 -> 24649 | M485: =LN(L485) -> 10.112492 | N485: =IF(K485<127,1,0) -> 0 | O485: =MONTH(C485) -> 12 | P485: =IF($O485=P$13,1,0) -> 0 | Q485: =IF($O485=Q$13,1,0) -> 0 | R485: =IF($O485=R$13,1,0) -> 0 | S485: =IF($O485=S$13,1,0) -> 0 | T485: =IF($O485=T$13,1,0) -> 0 | U485: =IF($O485=U$13,1,0) -> 0 | V485: =IF($O485=V$13,1,0) -> 0 | W485: =IF($O485=W$13,1,0) -> 0 | ... AA485: =IF($O485=AA$13,1,0) -> 1 | AB485: =IF($B485=AB$13,1,0) -> 0 | AC485: =IF($B485=AC$13,1,0) -> 0 | AD485: =IF($B485=AD$13,1,0) -> 0 | AE485: =IF($B485=AE$13,1,0) -> 0 | AF485: =IF($B485=AF$13,1,0) -> 1 | AG485: 1131.1517 | AH485: 226.36738 | AI485: 114.17871 | AJ485: 72.408792 | AK485: =LN(H485) -> 11.417413 | AL485: =LN(D485+'Models training data'!$Y$4) -> 7.2600716 | AM485: =LN(E485+'Models training data'!$Y$5) -> 5.6746264 | AN485: =LN(F485+'Models training data'!$Y$6) -> 5.0724025 | AO485: =LN(G485+'Models training data'!$Y$7) -> 4.8041212 | AP485: =V485+W485+X485+Y485+Z485 -> 0 | AQ485: =AA485+AC485+AD485+AE485+AF485 -> 2 | AR485: =$C$1+SUMPRODUCT($K$1:$AQ$1,K485:AQ485) -> 81456.478 | AS485: =$C$2+SUMPRODUCT($K$2:$AQ$2,K485:AQ485) -> 92521.556 | AT485: =$C$3+SUMPRODUCT($K$3:$AQ$3,K485:AQ485) -> 11.421557 | AU485: =$C$4+SUMPRODUCT($K$4:$AQ$4,K485:AQ485) -> 97172.175 | AV485: =$C$5+SUMPRODUCT($K$5:$AQ$5,K485:AQ485) -> 11.488231 | AW485: =$C$6+SUMPRODUCT($K$6:$AQ$6,K485:AQ485) -> 93330.588 | AX485: =$C$7+SUMPRODUCT($K$7:$AQ$7,K485:AQ485) -> 11.429288 | AY485: =$C$8+SUMPRODUCT($K$8:$AQ$8,K485:AQ485) -> 11.387995 | AZ485: =$C$9+SUMPRODUCT($K$9:$AQ$9,K485:AQ485) -> 11.395554
B486: CT | C486: 44562 | D486: 1215 | E486: 240 | F486: 120 | G486: 86.001096 | H486: 77079.506 | I486: =SUM(D486:G486) -> 1661.0011 | J486: =YEAR(C486) -> 2022 | K486: =IF(B486=B485,K485+1,1) -> 1 | L486: =K486^2 -> 1 | M486: =LN(L486) -> 0 | N486: =IF(K486<127,1,0) -> 1 | O486: =MONTH(C486) -> 1 | P486: =IF($O486=P$13,1,0) -> 1 | Q486: =IF($O486=Q$13,1,0) -> 0 | R486: =IF($O486=R$13,1,0) -> 0 | S486: =IF($O486=S$13,1,0) -> 0 | T486: =IF($O486=T$13,1,0) -> 0 | U486: =IF($O486=U$13,1,0) -> 0 | V486: =IF($O486=V$13,1,0) -> 0 | W486: =IF($O486=W$13,1,0) -> 0 | ... AA486: =IF($O486=AA$13,1,0) -> 0 | AB486: =IF($B486=AB$13,1,0) -> 0 | AC486: =IF($B486=AC$13,1,0) -> 0 | AD486: =IF($B486=AD$13,1,0) -> 0 | AE486: =IF($B486=AE$13,1,0) -> 0 | AF486: =IF($B486=AF$13,1,0) -> 0 | AG486: 1215 | AH486: 240 | AI486: 120 | AJ486: 86.001096 | AK486: =LN(H486) -> 11.252593 | AL486: =LN(D486+'Models training data'!$Y$4) -> 7.3173497 | AM486: =LN(E486+'Models training data'!$Y$5) -> 5.7203514 | AN486: =LN(F486+'Models training data'!$Y$6) -> 5.1082367 | AO486: =LN(G486+'Models training data'!$Y$7) -> 4.9097428 | AP486: =V486+W486+X486+Y486+Z486 -> 0 | AQ486: =AA486+AC486+AD486+AE486+AF486 -> 0 | AR486: =$C$1+SUMPRODUCT($K$1:$AQ$1,K486:AQ486) -> 86392.099 | AS486: =$C$2+SUMPRODUCT($K$2:$AQ$2,K486:AQ486) -> 77010.324 | AT486: =$C$3+SUMPRODUCT($K$3:$AQ$3,K486:AQ486) -> 11.251525 | AU486: =$C$4+SUMPRODUCT($K$4:$AQ$4,K486:AQ486) -> 78115.832 | AV486: =$C$5+SUMPRODUCT($K$5:$AQ$5,K486:AQ486) -> 11.267534 | AW486: =$C$6+SUMPRODUCT($K$6:$AQ$6,K486:AQ486) -> 80201.305 | AX486: =$C$7+SUMPRODUCT($K$7:$AQ$7,K486:AQ486) -> 11.289252 | AY486: =$C$8+SUMPRODUCT($K$8:$AQ$8,K486:AQ486) -> 11.398457 | AZ486: =$C$9+SUMPRODUCT($K$9:$AQ$9,K486:AQ486) -> 11.260886
B487: =B486 -> CT | C487: 44569 | D487: 1233.225 | E487: 246 | F487: 125.4 | G487: 75.158057 | H487: 76765.045 | I487: =SUM(D487:G487) -> 1679.7831 | J487: =YEAR(C487) -> 2022 | K487: =IF(B487=B486,K486+1,1) -> 2 | L487: =K487^2 -> 4 | M487: =LN(L487) -> 1.3862944 | N487: =IF(K487<127,1,0) -> 1 | O487: =MONTH(C487) -> 1 | P487: =IF($O487=P$13,1,0) -> 1 | Q487: =IF($O487=Q$13,1,0) -> 0 | R487: =IF($O487=R$13,1,0) -> 0 | S487: =IF($O487=S$13,1,0) -> 0 | T487: =IF($O487=T$13,1,0) -> 0 | U487: =IF($O487=U$13,1,0) -> 0 | V487: =IF($O487=V$13,1,0) -> 0 | W487: =IF($O487=W$13,1,0) -> 0 | ... AA487: =IF($O487=AA$13,1,0) -> 0 | AB487: =IF($B487=AB$13,1,0) -> 0 | AC487: =IF($B487=AC$13,1,0) -> 0 | AD487: =IF($B487=AD$13,1,0) -> 0 | AE487: =IF($B487=AE$13,1,0) -> 0 | AF487: =IF($B487=AF$13,1,0) -> 0 | AG487: 1233.225 | AH487: 246 | AI487: 125.4 | AJ487: 75.158057 | AK487: =LN(H487) -> 11.248505 | AL487: =LN(D487+'Models training data'!$Y$4) -> 7.329377 | AM487: =LN(E487+'Models training data'!$Y$5) -> 5.7398318 | AN487: =LN(F487+'Models training data'!$Y$6) -> 5.1403673 | AO487: =LN(G487+'Models training data'!$Y$7) -> 4.8264038 | AP487: =V487+W487+X487+Y487+Z487 -> 0 | AQ487: =AA487+AC487+AD487+AE487+AF487 -> 0 | AR487: =$C$1+SUMPRODUCT($K$1:$AQ$1,K487:AQ487) -> 86367.709 | AS487: =$C$2+SUMPRODUCT($K$2:$AQ$2,K487:AQ487) -> 76986.227 | AT487: =$C$3+SUMPRODUCT($K$3:$AQ$3,K487:AQ487) -> 11.251267 | AU487: =$C$4+SUMPRODUCT($K$4:$AQ$4,K487:AQ487) -> 78018.722 | AV487: =$C$5+SUMPRODUCT($K$5:$AQ$5,K487:AQ487) -> 11.266224 | AW487: =$C$6+SUMPRODUCT($K$6:$AQ$6,K487:AQ487) -> 79198.386 | AX487: =$C$7+SUMPRODUCT($K$7:$AQ$7,K487:AQ487) -> 11.277707 | AY487: =$C$8+SUMPRODUCT($K$8:$AQ$8,K487:AQ487) -> 11.398228 | AZ487: =$C$9+SUMPRODUCT($K$9:$AQ$9,K487:AQ487) -> 11.254445
B488: =B487 -> CT | C488: 44576 | D488: 1265.1187 | E488: 255.3 | F488: 131.61 | G488: 85.551266 | H488: 78063.605 | I488: =SUM(D488:G488) -> 1737.58 | J488: =YEAR(C488) -> 2022 | K488: =IF(B488=B487,K487+1,1) -> 3 | L488: =K488^2 -> 9 | M488: =LN(L488) -> 2.1972246 | N488: =IF(K488<127,1,0) -> 1 | O488: =MONTH(C488) -> 1 | P488: =IF($O488=P$13,1,0) -> 1 | Q488: =IF($O488=Q$13,1,0) -> 0 | R488: =IF($O488=R$13,1,0) -> 0 | S488: =IF($O488=S$13,1,0) -> 0 | T488: =IF($O488=T$13,1,0) -> 0 | U488: =IF($O488=U$13,1,0) -> 0 | V488: =IF($O488=V$13,1,0) -> 0 | W488: =IF($O488=W$13,1,0) -> 0 | ... AA488: =IF($O488=AA$13,1,0) -> 0 | AB488: =IF($B488=AB$13,1,0) -> 0 | AC488: =IF($B488=AC$13,1,0) -> 0 | AD488: =IF($B488=AD$13,1,0) -> 0 | AE488: =IF($B488=AE$13,1,0) -> 0 | AF488: =IF($B488=AF$13,1,0) -> 0 | AG488: 1265.1187 | AH488: 255.3 | AI488: 131.61 | AJ488: 85.551266 | AK488: =LN(H488) -> 11.265279 | AL488: =LN(D488+'Models training data'!$Y$4) -> 7.3500829 | AM488: =LN(E488+'Models training data'!$Y$5) -> 5.7692958 | AN488: =LN(F488+'Models training data'!$Y$6) -> 5.1760847 | AO488: =LN(G488+'Models training data'!$Y$7) -> 4.90642 | AP488: =V488+W488+X488+Y488+Z488 -> 0 | AQ488: =AA488+AC488+AD488+AE488+AF488 -> 0 | AR488: =$C$1+SUMPRODUCT($K$1:$AQ$1,K488:AQ488) -> 86343.318 | AS488: =$C$2+SUMPRODUCT($K$2:$AQ$2,K488:AQ488) -> 76962.129 | AT488: =$C$3+SUMPRODUCT($K$3:$AQ$3,K488:AQ488) -> 11.25101 | AU488: =$C$4+SUMPRODUCT($K$4:$AQ$4,K488:AQ488) -> 77922.791 | AV488: =$C$5+SUMPRODUCT($K$5:$AQ$5,K488:AQ488) -> 11.264931 | AW488: =$C$6+SUMPRODUCT($K$6:$AQ$6,K488:AQ488) -> 78611.716 | AX488: =$C$7+SUMPRODUCT($K$7:$AQ$7,K488:AQ488) -> 11.270954 | AY488: =$C$8+SUMPRODUCT($K$8:$AQ$8,K488:AQ488) -> 11.40215 | AZ488: =$C$9+SUMPRODUCT($K$9:$AQ$9,K488:AQ488) -> 11.269153
B489: =B488 -> CT | C489: 44583 | D489: 1307.5374 | E489: 266.565 | F489: 138.1845 | G489: 79.937326 | H489: 78278.861 | I489: =SUM(D489:G489) -> 1792.2243 | J489: =YEAR(C489) -> 2022 | K489: =IF(B489=B488,K488+1,1) -> 4 | L489: =K489^2 -> 16 | M489: =LN(L489) -> 2.7725887 | N489: =IF(K489<127,1,0) -> 1 | O489: =MONTH(C489) -> 1 | P489: =IF($O489=P$13,1,0) -> 1 | Q489: =IF($O489=Q$13,1,0) -> 0 | R489: =IF($O489=R$13,1,0) -> 0 | S489: =IF($O489=S$13,1,0) -> 0 | T489: =IF($O489=T$13,1,0) -> 0 | U489: =IF($O489=U$13,1,0) -> 0 | V489: =IF($O489=V$13,1,0) -> 0 | W489: =IF($O489=W$13,1,0) -> 0 | ... AA489: =IF($O489=AA$13,1,0) -> 0 | AB489: =IF($B489=AB$13,1,0) -> 0 | AC489: =IF($B489=AC$13,1,0) -> 0 | AD489: =IF($B489=AD$13,1,0) -> 0 | AE489: =IF($B489=AE$13,1,0) -> 0 | AF489: =IF($B489=AF$13,1,0) -> 0 | AG489: 1307.5374 | AH489: 266.565 | AI489: 138.1845 | AJ489: 79.937326 | AK489: =LN(H489) -> 11.268033 | AL489: =LN(D489+'Models training data'!$Y$4) -> 7.3769737 | AM489: =LN(E489+'Models training data'!$Y$5) -> 5.8038603 | AN489: =LN(F489+'Models training data'!$Y$6) -> 5.2125578 | AO489: =LN(G489+'Models training data'!$Y$7) -> 4.8639956 | AP489: =V489+W489+X489+Y489+Z489 -> 0 | AQ489: =AA489+AC489+AD489+AE489+AF489 -> 0 | AR489: =$C$1+SUMPRODUCT($K$1:$AQ$1,K489:AQ489) -> 86318.928 | AS489: =$C$2+SUMPRODUCT($K$2:$AQ$2,K489:AQ489) -> 76938.032 | AT489: =$C$3+SUMPRODUCT($K$3:$AQ$3,K489:AQ489) -> 11.250752 | AU489: =$C$4+SUMPRODUCT($K$4:$AQ$4,K489:AQ489) -> 77828.039 | AV489: =$C$5+SUMPRODUCT($K$5:$AQ$5,K489:AQ489) -> 11.263656 | AW489: =$C$6+SUMPRODUCT($K$6:$AQ$6,K489:AQ489) -> 78195.467 | AX489: =$C$7+SUMPRODUCT($K$7:$AQ$7,K489:AQ489) -> 11.266162 | AY489: =$C$8+SUMPRODUCT($K$8:$AQ$8,K489:AQ489) -> 11.404012 | AZ489: =$C$9+SUMPRODUCT($K$9:$AQ$9,K489:AQ489) -> 11.268993
B490: =B489 -> CT | C490: 44590 | D490: 1358.3282 | E490: 279.14325 | F490: 145.09313 | G490: 78.673846 | H490: 78814.469 | I490: =SUM(D490:G490) -> 1861.2385 | J490: =YEAR(C490) -> 2022 | K490: =IF(B490=B489,K489+1,1) -> 5 | L490: =K490^2 -> 25 | M490: =LN(L490) -> 3.2188758 | N490: =IF(K490<127,1,0) -> 1 | O490: =MONTH(C490) -> 1 | P490: =IF($O490=P$13,1,0) -> 1 | Q490: =IF($O490=Q$13,1,0) -> 0 | R490: =IF($O490=R$13,1,0) -> 0 | S490: =IF($O490=S$13,1,0) -> 0 | T490: =IF($O490=T$13,1,0) -> 0 | U490: =IF($O490=U$13,1,0) -> 0 | V490: =IF($O490=V$13,1,0) -> 0 | W490: =IF($O490=W$13,1,0) -> 0 | ... AA490: =IF($O490=AA$13,1,0) -> 0 | AB490: =IF($B490=AB$13,1,0) -> 0 | AC490: =IF($B490=AC$13,1,0) -> 0 | AD490: =IF($B490=AD$13,1,0) -> 0 | AE490: =IF($B490=AE$13,1,0) -> 0 | AF490: =IF($B490=AF$13,1,0) -> 0 | AG490: 1358.3282 | AH490: 279.14325 | AI490: 145.09313 | AJ490: 78.673846 | AK490: =LN(H490) -> 11.274852 | AL490: =LN(D490+'Models training data'!$Y$4) -> 7.4082487 | AM490: =LN(E490+'Models training data'!$Y$5) -> 5.8410931 | AN490: =LN(F490+'Models training data'!$Y$6) -> 5.2495031 | AO490: =LN(G490+'Models training data'!$Y$7) -> 4.8541942 | AP490: =V490+W490+X490+Y490+Z490 -> 0 | AQ490: =AA490+AC490+AD490+AE490+AF490 -> 0 | AR490: =$C$1+SUMPRODUCT($K$1:$AQ$1,K490:AQ490) -> 86294.538 | AS490: =$C$2+SUMPRODUCT($K$2:$AQ$2,K490:AQ490) -> 76913.934 | AT490: =$C$3+SUMPRODUCT($K$3:$AQ$3,K490:AQ490) -> 11.250494 | AU490: =$C$4+SUMPRODUCT($K$4:$AQ$4,K490:AQ490) -> 77734.466 | AV490: =$C$5+SUMPRODUCT($K$5:$AQ$5,K490:AQ490) -> 11.262397 | AW490: =$C$6+SUMPRODUCT($K$6:$AQ$6,K490:AQ490) -> 77872.599 | AX490: =$C$7+SUMPRODUCT($K$7:$AQ$7,K490:AQ490) -> 11.262445 | AY490: =$C$8+SUMPRODUCT($K$8:$AQ$8,K490:AQ490) -> 11.406934 | AZ490: =$C$9+SUMPRODUCT($K$9:$AQ$9,K490:AQ490) -> 11.273092
B491: =B490 -> CT | C491: 44597 | D491: 1416.0344 | E491: 292.72541 | F491: 152.34772 | G491: 104.44593 | H491: 80719.856 | I491: =SUM(D491:G491) -> 1965.5535 | J491: =YEAR(C491) -> 2022 | K491: =IF(B491=B490,K490+1,1) -> 6 | L491: =K491^2 -> 36 | M491: =LN(L491) -> 3.5835189 | N491: =IF(K491<127,1,0) -> 1 | O491: =MONTH(C491) -> 2 | P491: =IF($O491=P$13,1,0) -> 0 | Q491: =IF($O491=Q$13,1,0) -> 1 | R491: =IF($O491=R$13,1,0) -> 0 | S491: =IF($O491=S$13,1,0) -> 0 | T491: =IF($O491=T$13,1,0) -> 0 | U491: =IF($O491=U$13,1,0) -> 0 | V491: =IF($O491=V$13,1,0) -> 0 | W491: =IF($O491=W$13,1,0) -> 0 | ... AA491: =IF($O491=AA$13,1,0) -> 0 | AB491: =IF($B491=AB$13,1,0) -> 0 | AC491: =IF($B491=AC$13,1,0) -> 0 | AD491: =IF($B491=AD$13,1,0) -> 0 | AE491: =IF($B491=AE$13,1,0) -> 0 | AF491: =IF($B491=AF$13,1,0) -> 0 | AG491: 1416.0344 | AH491: 292.72541 | AI491: 152.34772 | AJ491: 104.44593 | AK491: =LN(H491) -> 11.29874 | AL491: =LN(D491+'Models training data'!$Y$4) -> 7.442634 | AM491: =LN(E491+'Models training data'!$Y$5) -> 5.8797995 | AN491: =LN(F491+'Models training data'!$Y$6) -> 5.2868833 | AO491: =LN(G491+'Models training data'!$Y$7) -> 5.0372731 | AP491: =V491+W491+X491+Y491+Z491 -> 0 | AQ491: =AA491+AC491+AD491+AE491+AF491 -> 0 | AR491: =$C$1+SUMPRODUCT($K$1:$AQ$1,K491:AQ491) -> 85220.436 | AS491: =$C$2+SUMPRODUCT($K$2:$AQ$2,K491:AQ491) -> 75837.726 | AT491: =$C$3+SUMPRODUCT($K$3:$AQ$3,K491:AQ491) -> 11.238543 | AU491: =$C$4+SUMPRODUCT($K$4:$AQ$4,K491:AQ491) -> 76710.106 | AV491: =$C$5+SUMPRODUCT($K$5:$AQ$5,K491:AQ491) -> 11.251207 | AW491: =$C$6+SUMPRODUCT($K$6:$AQ$6,K491:AQ491) -> 77166.49 | AX491: =$C$7+SUMPRODUCT($K$7:$AQ$7,K491:AQ491) -> 11.254896 | AY491: =$C$8+SUMPRODUCT($K$8:$AQ$8,K491:AQ491) -> 11.414468 | AZ491: =$C$9+SUMPRODUCT($K$9:$AQ$9,K491:AQ491) -> 11.301305
B492: =B491 -> CT | C492: 44604 | D492: 1479.6889 | E492: 307.17418 | F492: 159.9651 | G492: 114.79982 | H492: 81908.017 | I492: =SUM(D492:G492) -> 2061.628 | J492: =YEAR(C492) -> 2022 | K492: =IF(B492=B491,K491+1,1) -> 7 | L492: =K492^2 -> 49 | M492: =LN(L492) -> 3.8918203 | N492: =IF(K492<127,1,0) -> 1 | O492: =MONTH(C492) -> 2 | P492: =IF($O492=P$13,1,0) -> 0 | Q492: =IF($O492=Q$13,1,0) -> 1 | R492: =IF($O492=R$13,1,0) -> 0 | S492: =IF($O492=S$13,1,0) -> 0 | T492: =IF($O492=T$13,1,0) -> 0 | U492: =IF($O492=U$13,1,0) -> 0 | V492: =IF($O492=V$13,1,0) -> 0 | W492: =IF($O492=W$13,1,0) -> 0 | ... AA492: =IF($O492=AA$13,1,0) -> 0 | AB492: =IF($B492=AB$13,1,0) -> 0 | AC492: =IF($B492=AC$13,1,0) -> 0 | AD492: =IF($B492=AD$13,1,0) -> 0 | AE492: =IF($B492=AE$13,1,0) -> 0 | AF492: =IF($B492=AF$13,1,0) -> 0 | AG492: 1479.6889 | AH492: 307.17418 | AI492: 159.9651 | AJ492: 114.79982 | AK492: =LN(H492) -> 11.313352 | AL492: =LN(D492+'Models training data'!$Y$4) -> 7.4792407 | AM492: =LN(E492+'Models training data'!$Y$5) -> 5.9193945 | AN492: =LN(F492+'Models training data'!$Y$6) -> 5.3246846 | AO492: =LN(G492+'Models training data'!$Y$7) -> 5.1023222 | AP492: =V492+W492+X492+Y492+Z492 -> 0 | AQ492: =AA492+AC492+AD492+AE492+AF492 -> 0 | AR492: =$C$1+SUMPRODUCT($K$1:$AQ$1,K492:AQ492) -> 85196.046 | AS492: =$C$2+SUMPRODUCT($K$2:$AQ$2,K492:AQ492) -> 75813.629 | AT492: =$C$3+SUMPRODUCT($K$3:$AQ$3,K492:AQ492) -> 11.238285 | AU492: =$C$4+SUMPRODUCT($K$4:$AQ$4,K492:AQ492) -> 76618.89 | AV492: =$C$5+SUMPRODUCT($K$5:$AQ$5,K492:AQ492) -> 11.249982 | AW492: =$C$6+SUMPRODUCT($K$6:$AQ$6,K492:AQ492) -> 76943.448 | AX492: =$C$7+SUMPRODUCT($K$7:$AQ$7,K492:AQ492) -> 11.252329 | AY492: =$C$8+SUMPRODUCT($K$8:$AQ$8,K492:AQ492) -> 11.419806 | AZ492: =$C$9+SUMPRODUCT($K$9:$AQ$9,K492:AQ492) -> 11.314943
B493: =B492 -> CT | C493: 44611 | D493: 1548.6704 | E493: 322.43914 | F493: 167.96336 | G493: 93.330244 | H493: 81378.715 | I493: =SUM(D493:G493) -> 2132.4031 | J493: =YEAR(C493) -> 2022 | K493: =IF(B493=B492,K492+1,1) -> 8 | L493: =K493^2 -> 64 | M493: =LN(L493) -> 4.1588831 | N493: =IF(K493<127,1,0) -> 1 | O493: =MONTH(C493) -> 2 | P493: =IF($O493=P$13,1,0) -> 0 | Q493: =IF($O493=Q$13,1,0) -> 1 | R493: =IF($O493=R$13,1,0) -> 0 | S493: =IF($O493=S$13,1,0) -> 0 | T493: =IF($O493=T$13,1,0) -> 0 | U493: =IF($O493=U$13,1,0) -> 0 | V493: =IF($O493=V$13,1,0) -> 0 | W493: =IF($O493=W$13,1,0) -> 0 | ... AA493: =IF($O493=AA$13,1,0) -> 0 | AB493: =IF($B493=AB$13,1,0) -> 0 | AC493: =IF($B493=AC$13,1,0) -> 0 | AD493: =IF($B493=AD$13,1,0) -> 0 | AE493: =IF($B493=AE$13,1,0) -> 0 | AF493: =IF($B493=AF$13,1,0) -> 0 | AG493: 1548.6704 | AH493: 322.43914 | AI493: 167.96336 | AJ493: 93.330244 | AK493: =LN(H493) -> 11.306869 | AL493: =LN(D493+'Models training data'!$Y$4) -> 7.517454 | AM493: =LN(E493+'Models training data'!$Y$5) -> 5.95959 | AN493: =LN(F493+'Models training data'!$Y$6) -> 5.3628958 | AO493: =LN(G493+'Models training data'!$Y$7) -> 4.9623807 | AP493: =V493+W493+X493+Y493+Z493 -> 0 | AQ493: =AA493+AC493+AD493+AE493+AF493 -> 0 | AR493: =$C$1+SUMPRODUCT($K$1:$AQ$1,K493:AQ493) -> 85171.656 | AS493: =$C$2+SUMPRODUCT($K$2:$AQ$2,K493:AQ493) -> 75789.532 | AT493: =$C$3+SUMPRODUCT($K$3:$AQ$3,K493:AQ493) -> 11.238027 | AU493: =$C$4+SUMPRODUCT($K$4:$AQ$4,K493:AQ493) -> 76528.853 | AV493: =$C$5+SUMPRODUCT($K$5:$AQ$5,K493:AQ493) -> 11.248774 | AW493: =$C$6+SUMPRODUCT($K$6:$AQ$6,K493:AQ493) -> 76750.241 | AX493: =$C$7+SUMPRODUCT($K$7:$AQ$7,K493:AQ493) -> 11.250105 | AY493: =$C$8+SUMPRODUCT($K$8:$AQ$8,K493:AQ493) -> 11.420313 | AZ493: =$C$9+SUMPRODUCT($K$9:$AQ$9,K493:AQ493) -> 11.303175
B494: =B493 -> CT | C494: 44618 | D494: 1622.6018 | E494: 338.51422 | F494: 176.36152 | G494: 125.45134 | H494: 83724.296 | I494: =SUM(D494:G494) -> 2262.9289 | J494: =YEAR(C494) -> 2022 | K494: =IF(B494=B493,K493+1,1) -> 9 | L494: =K494^2 -> 81 | M494: =LN(L494) -> 4.3944492 | N494: =IF(K494<127,1,0) -> 1 | O494: =MONTH(C494) -> 2 | P494: =IF($O494=P$13,1,0) -> 0 | Q494: =IF($O494=Q$13,1,0) -> 1 | R494: =IF($O494=R$13,1,0) -> 0 | S494: =IF($O494=S$13,1,0) -> 0 | T494: =IF($O494=T$13,1,0) -> 0 | U494: =IF($O494=U$13,1,0) -> 0 | V494: =IF($O494=V$13,1,0) -> 0 | W494: =IF($O494=W$13,1,0) -> 0 | ... AA494: =IF($O494=AA$13,1,0) -> 0 | AB494: =IF($B494=AB$13,1,0) -> 0 | AC494: =IF($B494=AC$13,1,0) -> 0 | AD494: =IF($B494=AD$13,1,0) -> 0 | AE494: =IF($B494=AE$13,1,0) -> 0 | AF494: =IF($B494=AF$13,1,0) -> 0 | AG494: 1622.6018 | AH494: 338.51422 | AI494: 176.36152 | AJ494: 125.45134 | AK494: =LN(H494) -> 11.335284 | AL494: =LN(D494+'Models training data'!$Y$4) -> 7.5568505 | AM494: =LN(E494+'Models training data'!$Y$5) -> 6.0002417 | AN494: =LN(F494+'Models training data'!$Y$6) -> 5.4015056 | AO494: =LN(G494+'Models training data'!$Y$7) -> 5.1650989 | AP494: =V494+W494+X494+Y494+Z494 -> 0 | AQ494: =AA494+AC494+AD494+AE494+AF494 -> 0 | AR494: =$C$1+SUMPRODUCT($K$1:$AQ$1,K494:AQ494) -> 85147.265 | AS494: =$C$2+SUMPRODUCT($K$2:$AQ$2,K494:AQ494) -> 75765.434 | AT494: =$C$3+SUMPRODUCT($K$3:$AQ$3,K494:AQ494) -> 11.23777 | AU494: =$C$4+SUMPRODUCT($K$4:$AQ$4,K494:AQ494) -> 76439.994 | AV494: =$C$5+SUMPRODUCT($K$5:$AQ$5,K494:AQ494) -> 11.247584 | AW494: =$C$6+SUMPRODUCT($K$6:$AQ$6,K494:AQ494) -> 76579.82 | AX494: =$C$7+SUMPRODUCT($K$7:$AQ$7,K494:AQ494) -> 11.248143 | AY494: =$C$8+SUMPRODUCT($K$8:$AQ$8,K494:AQ494) -> 11.429607 | AZ494: =$C$9+SUMPRODUCT($K$9:$AQ$9,K494:AQ494) -> 11.334073
B495: =B494 -> CT | C495: 44625 | D495: 1701.2804 | E495: 355.4165 | F495: 185.1796 | G495: 112.54865 | H495: 83762.625 | I495: =SUM(D495:G495) -> 2354.4251 | J495: =YEAR(C495) -> 2022 | K495: =IF(B495=B494,K494+1,1) -> 10 | L495: =K495^2 -> 100 | M495: =LN(L495) -> 4.6051702 | N495: =IF(K495<127,1,0) -> 1 | O495: =MONTH(C495) -> 3 | P495: =IF($O495=P$13,1,0) -> 0 | Q495: =IF($O495=Q$13,1,0) -> 0 | R495: =IF($O495=R$13,1,0) -> 1 | S495: =IF($O495=S$13,1,0) -> 0 | T495: =IF($O495=T$13,1,0) -> 0 | U495: =IF($O495=U$13,1,0) -> 0 | V495: =IF($O495=V$13,1,0) -> 0 | W495: =IF($O495=W$13,1,0) -> 0 | ... AA495: =IF($O495=AA$13,1,0) -> 0 | AB495: =IF($B495=AB$13,1,0) -> 0 | AC495: =IF($B495=AC$13,1,0) -> 0 | AD495: =IF($B495=AD$13,1,0) -> 0 | AE495: =IF($B495=AE$13,1,0) -> 0 | AF495: =IF($B495=AF$13,1,0) -> 0 | AG495: 1701.2804 | AH495: 355.4165 | AI495: 185.1796 | AJ495: 112.54865 | AK495: =LN(H495) -> 11.335742 | AL495: =LN(D495+'Models training data'!$Y$4) -> 7.5971389 | AM495: =LN(E495+'Models training data'!$Y$5) -> 6.0412746 | AN495: =LN(F495+'Models training data'!$Y$6) -> 5.4405028 | AO495: =LN(G495+'Models training data'!$Y$7) -> 5.0885347 | AP495: =V495+W495+X495+Y495+Z495 -> 0 | AQ495: =AA495+AC495+AD495+AE495+AF495 -> 0 | AR495: =$C$1+SUMPRODUCT($K$1:$AQ$1,K495:AQ495) -> 84207.664 | AS495: =$C$2+SUMPRODUCT($K$2:$AQ$2,K495:AQ495) -> 74823.726 | AT495: =$C$3+SUMPRODUCT($K$3:$AQ$3,K495:AQ495) -> 11.226705 | AU495: =$C$4+SUMPRODUCT($K$4:$AQ$4,K495:AQ495) -> 75390.708 | AV495: =$C$5+SUMPRODUCT($K$5:$AQ$5,K495:AQ495) -> 11.234989 | AW495: =$C$6+SUMPRODUCT($K$6:$AQ$6,K495:AQ495) -> 75680.409 | AX495: =$C$7+SUMPRODUCT($K$7:$AQ$7,K495:AQ495) -> 11.237707 | AY495: =$C$8+SUMPRODUCT($K$8:$AQ$8,K495:AQ495) -> 11.431958 | AZ495: =$C$9+SUMPRODUCT($K$9:$AQ$9,K495:AQ495) -> 11.330311
B496: =B495 -> CT | C496: 44632 | D496: 1784.6283 | E496: 373.1756 | F496: 194.43858 | G496: 121.21065 | H496: 84845.538 | I496: =SUM(D496:G496) -> 2473.4532 | J496: =YEAR(C496) -> 2022 | K496: =IF(B496=B495,K495+1,1) -> 11 | L496: =K496^2 -> 121 | M496: =LN(L496) -> 4.7957905 | N496: =IF(K496<127,1,0) -> 1 | O496: =MONTH(C496) -> 3 | P496: =IF($O496=P$13,1,0) -> 0 | Q496: =IF($O496=Q$13,1,0) -> 0 | R496: =IF($O496=R$13,1,0) -> 1 | S496: =IF($O496=S$13,1,0) -> 0 | T496: =IF($O496=T$13,1,0) -> 0 | U496: =IF($O496=U$13,1,0) -> 0 | V496: =IF($O496=V$13,1,0) -> 0 | W496: =IF($O496=W$13,1,0) -> 0 | ... AA496: =IF($O496=AA$13,1,0) -> 0 | AB496: =IF($B496=AB$13,1,0) -> 0 | AC496: =IF($B496=AC$13,1,0) -> 0 | AD496: =IF($B496=AD$13,1,0) -> 0 | AE496: =IF($B496=AE$13,1,0) -> 0 | AF496: =IF($B496=AF$13,1,0) -> 0 | AG496: 1784.6283 | AH496: 373.1756 | AI496: 194.43858 | AJ496: 121.21065 | AK496: =LN(H496) -> 11.348588 | AL496: =LN(D496+'Models training data'!$Y$4) -> 7.6381188 | AM496: =LN(E496+'Models training data'!$Y$5) -> 6.0826473 | AN496: =LN(F496+'Models training data'!$Y$6) -> 5.4798764 | AO496: =LN(G496+'Models training data'!$Y$7) -> 5.1405758 | AP496: =V496+W496+X496+Y496+Z496 -> 0 | AQ496: =AA496+AC496+AD496+AE496+AF496 -> 0 | AR496: =$C$1+SUMPRODUCT($K$1:$AQ$1,K496:AQ496) -> 84183.274 | AS496: =$C$2+SUMPRODUCT($K$2:$AQ$2,K496:AQ496) -> 74799.629 | AT496: =$C$3+SUMPRODUCT($K$3:$AQ$3,K496:AQ496) -> 11.226447 | AU496: =$C$4+SUMPRODUCT($K$4:$AQ$4,K496:AQ496) -> 75304.207 | AV496: =$C$5+SUMPRODUCT($K$5:$AQ$5,K496:AQ496) -> 11.233832 | AW496: =$C$6+SUMPRODUCT($K$6:$AQ$6,K496:AQ496) -> 75542.504 | AX496: =$C$7+SUMPRODUCT($K$7:$AQ$7,K496:AQ496) -> 11.23612 | AY496: =$C$8+SUMPRODUCT($K$8:$AQ$8,K496:AQ496) -> 11.43799 | AZ496: =$C$9+SUMPRODUCT($K$9:$AQ$9,K496:AQ496) -> 11.342591
B497: =B496 -> CT | C497: 44639 | D497: 1872.6585 | E497: 391.82853 | F497: 204.16051 | G497: 137.02343 | H497: 86206.124 | I497: =SUM(D497:G497) -> 2605.671 | J497: =YEAR(C497) -> 2022 | K497: =IF(B497=B496,K496+1,1) -> 12 | L497: =K497^2 -> 144 | M497: =LN(L497) -> 4.9698133 | N497: =IF(K497<127,1,0) -> 1 | O497: =MONTH(C497) -> 3 | P497: =IF($O497=P$13,1,0) -> 0 | Q497: =IF($O497=Q$13,1,0) -> 0 | R497: =IF($O497=R$13,1,0) -> 1 | S497: =IF($O497=S$13,1,0) -> 0 | T497: =IF($O497=T$13,1,0) -> 0 | U497: =IF($O497=U$13,1,0) -> 0 | V497: =IF($O497=V$13,1,0) -> 0 | W497: =IF($O497=W$13,1,0) -> 0 | ... AA497: =IF($O497=AA$13,1,0) -> 0 | AB497: =IF($B497=AB$13,1,0) -> 0 | AC497: =IF($B497=AC$13,1,0) -> 0 | AD497: =IF($B497=AD$13,1,0) -> 0 | AE497: =IF($B497=AE$13,1,0) -> 0 | AF497: =IF($B497=AF$13,1,0) -> 0 | AG497: 1872.6585 | AH497: 391.82853 | AI497: 204.16051 | AJ497: 137.02343 | AK497: =LN(H497) -> 11.364496 | AL497: =LN(D497+'Models training data'!$Y$4) -> 7.6796514 | AM497: =LN(E497+'Models training data'!$Y$5) -> 6.1243346 | AN497: =LN(F497+'Models training data'!$Y$6) -> 5.5196152 | AO497: =LN(G497+'Models training data'!$Y$7) -> 5.2291112 | AP497: =V497+W497+X497+Y497+Z497 -> 0 | AQ497: =AA497+AC497+AD497+AE497+AF497 -> 0 | AR497: =$C$1+SUMPRODUCT($K$1:$AQ$1,K497:AQ497) -> 84158.884 | AS497: =$C$2+SUMPRODUCT($K$2:$AQ$2,K497:AQ497) -> 74775.531 | AT497: =$C$3+SUMPRODUCT($K$3:$AQ$3,K497:AQ497) -> 11.22619 | AU497: =$C$4+SUMPRODUCT($K$4:$AQ$4,K497:AQ497) -> 75218.884 | AV497: =$C$5+SUMPRODUCT($K$5:$AQ$5,K497:AQ497) -> 11.232691 | AW497: =$C$6+SUMPRODUCT($K$6:$AQ$6,K497:AQ497) -> 75416.607 | AX497: =$C$7+SUMPRODUCT($K$7:$AQ$7,K497:AQ497) -> 11.23467 | AY497: =$C$8+SUMPRODUCT($K$8:$AQ$8,K497:AQ497) -> 11.445412 | AZ497: =$C$9+SUMPRODUCT($K$9:$AQ$9,K497:AQ497) -> 11.359459
B498: =B497 -> CT | C498: 44646 | D498: 1965.4506 | E498: 411.41702 | F498: 214.36853 | G498: 143.42721 | H498: 87127.754 | I498: =SUM(D498:G498) -> 2734.6634 | J498: =YEAR(C498) -> 2022 | K498: =IF(B498=B497,K497+1,1) -> 13 | L498: =K498^2 -> 169 | M498: =LN(L498) -> 5.1298987 | N498: =IF(K498<127,1,0) -> 1 | O498: =MONTH(C498) -> 3 | P498: =IF($O498=P$13,1,0) -> 0 | Q498: =IF($O498=Q$13,1,0) -> 0 | R498: =IF($O498=R$13,1,0) -> 1 | S498: =IF($O498=S$13,1,0) -> 0 | T498: =IF($O498=T$13,1,0) -> 0 | U498: =IF($O498=U$13,1,0) -> 0 | V498: =IF($O498=V$13,1,0) -> 0 | W498: =IF($O498=W$13,1,0) -> 0 | ... AA498: =IF($O498=AA$13,1,0) -> 0 | AB498: =IF($B498=AB$13,1,0) -> 0 | AC498: =IF($B498=AC$13,1,0) -> 0 | AD498: =IF($B498=AD$13,1,0) -> 0 | AE498: =IF($B498=AE$13,1,0) -> 0 | AF498: =IF($B498=AF$13,1,0) -> 0 | AG498: 1965.4506 | AH498: 411.41702 | AI498: 214.36853 | AJ498: 143.42721 | AK498: =LN(H498) -> 11.375131 | AL498: =LN(D498+'Models training data'!$Y$4) -> 7.7216399 | AM498: =LN(E498+'Models training data'!$Y$5) -> 6.1663189 | AN498: =LN(F498+'Models training data'!$Y$6) -> 5.5597081 | AO498: =LN(G498+'Models training data'!$Y$7) -> 5.2628489 | AP498: =V498+W498+X498+Y498+Z498 -> 0 | AQ498: =AA498+AC498+AD498+AE498+AF498 -> 0 | AR498: =$C$1+SUMPRODUCT($K$1:$AQ$1,K498:AQ498) -> 84134.493 | AS498: =$C$2+SUMPRODUCT($K$2:$AQ$2,K498:AQ498) -> 74751.434 | AT498: =$C$3+SUMPRODUCT($K$3:$AQ$3,K498:AQ498) -> 11.225932 | AU498: =$C$4+SUMPRODUCT($K$4:$AQ$4,K498:AQ498) -> 75134.74 | AV498: =$C$5+SUMPRODUCT($K$5:$AQ$5,K498:AQ498) -> 11.231568 | AW498: =$C$6+SUMPRODUCT($K$6:$AQ$6,K498:AQ498) -> 75300.793 | AX498: =$C$7+SUMPRODUCT($K$7:$AQ$7,K498:AQ498) -> 11.233337 | AY498: =$C$8+SUMPRODUCT($K$8:$AQ$8,K498:AQ498) -> 11.451591 | AZ498: =$C$9+SUMPRODUCT($K$9:$AQ$9,K498:AQ498) -> 11.369563
... B642: =B641 -> CT | C642: 45654 | D642: 754.11185 | E642: 150.91159 | F642: 76.119143 | G642: 50 | H642: 70799.811 | I642: =SUM(D642:G642) -> 1031.1426 | J642: =YEAR(C642) -> 2024 | K642: =IF(B642=B641,K641+1,1) -> 157 | L642: =K642^2 -> 24649 | M642: =LN(L642) -> 10.112492 | N642: =IF(K642<127,1,0) -> 0 | O642: =MONTH(C642) -> 12 | P642: =IF($O642=P$13,1,0) -> 0 | Q642: =IF($O642=Q$13,1,0) -> 0 | R642: =IF($O642=R$13,1,0) -> 0 | S642: =IF($O642=S$13,1,0) -> 0 | T642: =IF($O642=T$13,1,0) -> 0 | U642: =IF($O642=U$13,1,0) -> 0 | V642: =IF($O642=V$13,1,0) -> 0 | W642: =IF($O642=W$13,1,0) -> 0 | ... AA642: =IF($O642=AA$13,1,0) -> 1 | AB642: =IF($B642=AB$13,1,0) -> 0 | AC642: =IF($B642=AC$13,1,0) -> 0 | AD642: =IF($B642=AD$13,1,0) -> 0 | AE642: =IF($B642=AE$13,1,0) -> 0 | AF642: =IF($B642=AF$13,1,0) -> 0 | AG642: 754.11185 | AH642: 150.91159 | AI642: 76.119143 | AJ642: 50 | AK642: =LN(H642) -> 11.167612 | AL642: =LN(D642+'Models training data'!$Y$4) -> 6.952077 | AM642: =LN(E642+'Models training data'!$Y$5) -> 5.374925 | AN642: =LN(F642+'Models training data'!$Y$6) -> 4.7998947 | AO642: =LN(G642+'Models training data'!$Y$7) -> 4.6011966 | AP642: =V642+W642+X642+Y642+Z642 -> 0 | AQ642: =AA642+AC642+AD642+AE642+AF642 -> 1 | AR642: =$C$1+SUMPRODUCT($K$1:$AQ$1,K642:AQ642) -> 81456.478 | AS642: =$C$2+SUMPRODUCT($K$2:$AQ$2,K642:AQ642) -> 72112.873 | AT642: =$C$3+SUMPRODUCT($K$3:$AQ$3,K642:AQ642) -> 11.197261 | AU642: =$C$4+SUMPRODUCT($K$4:$AQ$4,K642:AQ642) -> 76763.492 | AV642: =$C$5+SUMPRODUCT($K$5:$AQ$5,K642:AQ642) -> 11.263935 | AW642: =$C$6+SUMPRODUCT($K$6:$AQ$6,K642:AQ642) -> 72921.905 | AX642: =$C$7+SUMPRODUCT($K$7:$AQ$7,K642:AQ642) -> 11.204992 | AY642: =$C$8+SUMPRODUCT($K$8:$AQ$8,K642:AQ642) -> 11.269045 | AZ642: =$C$9+SUMPRODUCT($K$9:$AQ$9,K642:AQ642) -> 11.184212
B643: DL | C643: 44562 | D643: 607.5 | E643: 120 | F643: 60 | G643: 50 | H643: 65640.268 | I643: =SUM(D643:G643) -> 837.5 | J643: =YEAR(C643) -> 2022 | K643: =IF(B643=B642,K642+1,1) -> 1 | L643: =K643^2 -> 1 | M643: =LN(L643) -> 0 | N643: =IF(K643<127,1,0) -> 1 | O643: =MONTH(C643) -> 1 | P643: =IF($O643=P$13,1,0) -> 1 | Q643: =IF($O643=Q$13,1,0) -> 0 | R643: =IF($O643=R$13,1,0) -> 0 | S643: =IF($O643=S$13,1,0) -> 0 | T643: =IF($O643=T$13,1,0) -> 0 | U643: =IF($O643=U$13,1,0) -> 0 | V643: =IF($O643=V$13,1,0) -> 0 | W643: =IF($O643=W$13,1,0) -> 0 | ... AA643: =IF($O643=AA$13,1,0) -> 0 | AB643: =IF($B643=AB$13,1,0) -> 1 | AC643: =IF($B643=AC$13,1,0) -> 0 | AD643: =IF($B643=AD$13,1,0) -> 0 | AE643: =IF($B643=AE$13,1,0) -> 0 | AF643: =IF($B643=AF$13,1,0) -> 0 | AG643: 607.5 | AH643: 120 | AI643: 60 | AJ643: 50 | AK643: =LN(H643) -> 11.091945 | AL643: =LN(D643+'Models training data'!$Y$4) -> 6.8009568 | AM643: =LN(E643+'Models training data'!$Y$5) -> 5.2204212 | AN643: =LN(F643+'Models training data'!$Y$6) -> 4.6575585 | AO643: =LN(G643+'Models training data'!$Y$7) -> 4.6011966 | AP643: =V643+W643+X643+Y643+Z643 -> 0 | AQ643: =AA643+AC643+AD643+AE643+AF643 -> 0 | AR643: =$C$1+SUMPRODUCT($K$1:$AQ$1,K643:AQ643) -> 86392.099 | AS643: =$C$2+SUMPRODUCT($K$2:$AQ$2,K643:AQ643) -> 68495.362 | AT643: =$C$3+SUMPRODUCT($K$3:$AQ$3,K643:AQ643) -> 11.141741 | AU643: =$C$4+SUMPRODUCT($K$4:$AQ$4,K643:AQ643) -> 69600.87 | AV643: =$C$5+SUMPRODUCT($K$5:$AQ$5,K643:AQ643) -> 11.157749 | AW643: =$C$6+SUMPRODUCT($K$6:$AQ$6,K643:AQ643) -> 71686.343 | AX643: =$C$7+SUMPRODUCT($K$7:$AQ$7,K643:AQ643) -> 11.179468 | AY643: =$C$8+SUMPRODUCT($K$8:$AQ$8,K643:AQ643) -> 11.289224 | AZ643: =$C$9+SUMPRODUCT($K$9:$AQ$9,K643:AQ643) -> 11.132632
B644: =B643 -> DL | C644: 44569 | D644: 616.6125 | E644: 123 | F644: 62.7 | G644: 50 | H644: 66095.521 | I644: =SUM(D644:G644) -> 852.3125 | J644: =YEAR(C644) -> 2022 | K644: =IF(B644=B643,K643+1,1) -> 2 | L644: =K644^2 -> 4 | M644: =LN(L644) -> 1.3862944 | N644: =IF(K644<127,1,0) -> 1 | O644: =MONTH(C644) -> 1 | P644: =IF($O644=P$13,1,0) -> 1 | Q644: =IF($O644=Q$13,1,0) -> 0 | R644: =IF($O644=R$13,1,0) -> 0 | S644: =IF($O644=S$13,1,0) -> 0 | T644: =IF($O644=T$13,1,0) -> 0 | U644: =IF($O644=U$13,1,0) -> 0 | V644: =IF($O644=V$13,1,0) -> 0 | W644: =IF($O644=W$13,1,0) -> 0 | ... AA644: =IF($O644=AA$13,1,0) -> 0 | AB644: =IF($B644=AB$13,1,0) -> 1 | AC644: =IF($B644=AC$13,1,0) -> 0 | AD644: =IF($B644=AD$13,1,0) -> 0 | AE644: =IF($B644=AE$13,1,0) -> 0 | AF644: =IF($B644=AF$13,1,0) -> 0 | AG644: 616.6125 | AH644: 123 | AI644: 62.7 | AJ644: 50 | AK644: =LN(H644) -> 11.098856 | AL644: =LN(D644+'Models training data'!$Y$4) -> 6.8110453 | AM644: =LN(E644+'Models training data'!$Y$5) -> 5.2365062 | AN644: =LN(F644+'Models training data'!$Y$6) -> 4.6828577 | AO644: =LN(G644+'Models training data'!$Y$7) -> 4.6011966 | AP644: =V644+W644+X644+Y644+Z644 -> 0 | AQ644: =AA644+AC644+AD644+AE644+AF644 -> 0 | AR644: =$C$1+SUMPRODUCT($K$1:$AQ$1,K644:AQ644) -> 86367.709 | AS644: =$C$2+SUMPRODUCT($K$2:$AQ$2,K644:AQ644) -> 68471.265 | AT644: =$C$3+SUMPRODUCT($K$3:$AQ$3,K644:AQ644) -> 11.141483 | AU644: =$C$4+SUMPRODUCT($K$4:$AQ$4,K644:AQ644) -> 69503.761 | AV644: =$C$5+SUMPRODUCT($K$5:$AQ$5,K644:AQ644) -> 11.15644 | AW644: =$C$6+SUMPRODUCT($K$6:$AQ$6,K644:AQ644) -> 70683.424 | AX644: =$C$7+SUMPRODUCT($K$7:$AQ$7,K644:AQ644) -> 11.167923 | AY644: =$C$8+SUMPRODUCT($K$8:$AQ$8,K644:AQ644) -> 11.289928 | AZ644: =$C$9+SUMPRODUCT($K$9:$AQ$9,K644:AQ644) -> 11.135791
B645: =B644 -> DL | C645: 44576 | D645: 632.55937 | E645: 127.65 | F645: 65.805 | G645: 50 | H645: 66654.32 | I645: =SUM(D645:G645) -> 876.01437 | J645: =YEAR(C645) -> 2022 | K645: =IF(B645=B644,K644+1,1) -> 3 | L645: =K645^2 -> 9 | M645: =LN(L645) -> 2.1972246 | N645: =IF(K645<127,1,0) -> 1 | O645: =MONTH(C645) -> 1 | P645: =IF($O645=P$13,1,0) -> 1 | Q645: =IF($O645=Q$13,1,0) -> 0 | R645: =IF($O645=R$13,1,0) -> 0 | S645: =IF($O645=S$13,1,0) -> 0 | T645: =IF($O645=T$13,1,0) -> 0 | U645: =IF($O645=U$13,1,0) -> 0 | V645: =IF($O645=V$13,1,0) -> 0 | W645: =IF($O645=W$13,1,0) -> 0 | ... AA645: =IF($O645=AA$13,1,0) -> 0 | AB645: =IF($B645=AB$13,1,0) -> 1 | AC645: =IF($B645=AC$13,1,0) -> 0 | AD645: =IF($B645=AD$13,1,0) -> 0 | AE645: =IF($B645=AE$13,1,0) -> 0 | AF645: =IF($B645=AF$13,1,0) -> 0 | AG645: 632.55937 | AH645: 127.65 | AI645: 65.805 | AJ645: 50 | AK645: =LN(H645) -> 11.107275 | AL645: =LN(D645+'Models training data'!$Y$4) -> 6.8284589 | AM645: =LN(E645+'Models training data'!$Y$5) -> 5.2609378 | AN645: =LN(F645+'Models training data'!$Y$6) -> 4.7111818 | AO645: =LN(G645+'Models training data'!$Y$7) -> 4.6011966 | AP645: =V645+W645+X645+Y645+Z645 -> 0 | AQ645: =AA645+AC645+AD645+AE645+AF645 -> 0 | AR645: =$C$1+SUMPRODUCT($K$1:$AQ$1,K645:AQ645) -> 86343.318 | AS645: =$C$2+SUMPRODUCT($K$2:$AQ$2,K645:AQ645) -> 68447.168 | AT645: =$C$3+SUMPRODUCT($K$3:$AQ$3,K645:AQ645) -> 11.141225 | AU645: =$C$4+SUMPRODUCT($K$4:$AQ$4,K645:AQ645) -> 69407.83 | AV645: =$C$5+SUMPRODUCT($K$5:$AQ$5,K645:AQ645) -> 11.155147 | AW645: =$C$6+SUMPRODUCT($K$6:$AQ$6,K645:AQ645) -> 70096.754 | AX645: =$C$7+SUMPRODUCT($K$7:$AQ$7,K645:AQ645) -> 11.16117 | AY645: =$C$8+SUMPRODUCT($K$8:$AQ$8,K645:AQ645) -> 11.291013 | AZ645: =$C$9+SUMPRODUCT($K$9:$AQ$9,K645:AQ645) -> 11.139655
B646: =B645 -> DL | C646: 44583 | D646: 653.76872 | E646: 133.2825 | F646: 69.09225 | G646: 50 | H646: 67257.228 | I646: =SUM(D646:G646) -> 906.14347 | J646: =YEAR(C646) -> 2022 | K646: =IF(B646=B645,K645+1,1) -> 4 | L646: =K646^2 -> 16 | M646: =LN(L646) -> 2.7725887 | N646: =IF(K646<127,1,0) -> 1 | O646: =MONTH(C646) -> 1 | P646: =IF($O646=P$13,1,0) -> 1 | Q646: =IF($O646=Q$13,1,0) -> 0 | R646: =IF($O646=R$13,1,0) -> 0 | S646: =IF($O646=S$13,1,0) -> 0 | T646: =IF($O646=T$13,1,0) -> 0 | U646: =IF($O646=U$13,1,0) -> 0 | V646: =IF($O646=V$13,1,0) -> 0 | W646: =IF($O646=W$13,1,0) -> 0 | ... AA646: =IF($O646=AA$13,1,0) -> 0 | AB646: =IF($B646=AB$13,1,0) -> 1 | AC646: =IF($B646=AC$13,1,0) -> 0 | AD646: =IF($B646=AD$13,1,0) -> 0 | AE646: =IF($B646=AE$13,1,0) -> 0 | AF646: =IF($B646=AF$13,1,0) -> 0 | AG646: 653.76872 | AH646: 133.2825 | AI646: 69.09225 | AJ646: 50 | AK646: =LN(H646) -> 11.11628 | AL646: =LN(D646+'Models training data'!$Y$4) -> 6.8511589 | AM646: =LN(E646+'Models training data'!$Y$5) -> 5.2897537 | AN646: =LN(F646+'Models training data'!$Y$6) -> 4.7403192 | AO646: =LN(G646+'Models training data'!$Y$7) -> 4.6011966 | AP646: =V646+W646+X646+Y646+Z646 -> 0 | AQ646: =AA646+AC646+AD646+AE646+AF646 -> 0 | AR646: =$C$1+SUMPRODUCT($K$1:$AQ$1,K646:AQ646) -> 86318.928 | AS646: =$C$2+SUMPRODUCT($K$2:$AQ$2,K646:AQ646) -> 68423.07 | AT646: =$C$3+SUMPRODUCT($K$3:$AQ$3,K646:AQ646) -> 11.140968 | AU646: =$C$4+SUMPRODUCT($K$4:$AQ$4,K646:AQ646) -> 69313.078 | AV646: =$C$5+SUMPRODUCT($K$5:$AQ$5,K646:AQ646) -> 11.153872 | AW646: =$C$6+SUMPRODUCT($K$6:$AQ$6,K646:AQ646) -> 69680.505 | AX646: =$C$7+SUMPRODUCT($K$7:$AQ$7,K646:AQ646) -> 11.156378 | AY646: =$C$8+SUMPRODUCT($K$8:$AQ$8,K646:AQ646) -> 11.292345 | AZ646: =$C$9+SUMPRODUCT($K$9:$AQ$9,K646:AQ646) -> 11.143838
B647: =B646 -> DL | C647: 44590 | D647: 679.16412 | E647: 139.57163 | F647: 72.546563 | G647: 50 | H647: 67883.832 | I647: =SUM(D647:G647) -> 941.2823 | J647: =YEAR(C647) -> 2022 | K647: =IF(B647=B646,K646+1,1) -> 5 | L647: =K647^2 -> 25 | M647: =LN(L647) -> 3.2188758 | N647: =IF(K647<127,1,0) -> 1 | O647: =MONTH(C647) -> 1 | P647: =IF($O647=P$13,1,0) -> 1 | Q647: =IF($O647=Q$13,1,0) -> 0 | R647: =IF($O647=R$13,1,0) -> 0 | S647: =IF($O647=S$13,1,0) -> 0 | T647: =IF($O647=T$13,1,0) -> 0 | U647: =IF($O647=U$13,1,0) -> 0 | V647: =IF($O647=V$13,1,0) -> 0 | W647: =IF($O647=W$13,1,0) -> 0 | ... AA647: =IF($O647=AA$13,1,0) -> 0 | AB647: =IF($B647=AB$13,1,0) -> 1 | AC647: =IF($B647=AC$13,1,0) -> 0 | AD647: =IF($B647=AD$13,1,0) -> 0 | AE647: =IF($B647=AE$13,1,0) -> 0 | AF647: =IF($B647=AF$13,1,0) -> 0 | AG647: 679.16412 | AH647: 139.57163 | AI647: 72.546563 | AJ647: 50 | AK647: =LN(H647) -> 11.125553 | AL647: =LN(D647+'Models training data'!$Y$4) -> 6.8776783 | AM647: =LN(E647+'Models training data'!$Y$5) -> 5.3209772 | AN647: =LN(F647+'Models training data'!$Y$6) -> 4.7700492 | AO647: =LN(G647+'Models training data'!$Y$7) -> 4.6011966 | AP647: =V647+W647+X647+Y647+Z647 -> 0 | AQ647: =AA647+AC647+AD647+AE647+AF647 -> 0 | AR647: =$C$1+SUMPRODUCT($K$1:$AQ$1,K647:AQ647) -> 86294.538 | AS647: =$C$2+SUMPRODUCT($K$2:$AQ$2,K647:AQ647) -> 68398.973 | AT647: =$C$3+SUMPRODUCT($K$3:$AQ$3,K647:AQ647) -> 11.14071 | AU647: =$C$4+SUMPRODUCT($K$4:$AQ$4,K647:AQ647) -> 69219.504 | AV647: =$C$5+SUMPRODUCT($K$5:$AQ$5,K647:AQ647) -> 11.152613 | AW647: =$C$6+SUMPRODUCT($K$6:$AQ$6,K647:AQ647) -> 69357.637 | AX647: =$C$7+SUMPRODUCT($K$7:$AQ$7,K647:AQ647) -> 11.152661 | AY647: =$C$8+SUMPRODUCT($K$8:$AQ$8,K647:AQ647) -> 11.293861 | AZ647: =$C$9+SUMPRODUCT($K$9:$AQ$9,K647:AQ647) -> 11.148217
B648: =B647 -> DL | C648: 44597 | D648: 708.0172 | E648: 146.36271 | F648: 76.173861 | G648: 50 | H648: 68170.828 | I648: =SUM(D648:G648) -> 980.55376 | J648: =YEAR(C648) -> 2022 | K648: =IF(B648=B647,K647+1,1) -> 6 | L648: =K648^2 -> 36 | M648: =LN(L648) -> 3.5835189 | N648: =IF(K648<127,1,0) -> 1 | O648: =MONTH(C648) -> 2 | P648: =IF($O648=P$13,1,0) -> 0 | Q648: =IF($O648=Q$13,1,0) -> 1 | R648: =IF($O648=R$13,1,0) -> 0 | S648: =IF($O648=S$13,1,0) -> 0 | T648: =IF($O648=T$13,1,0) -> 0 | U648: =IF($O648=U$13,1,0) -> 0 | V648: =IF($O648=V$13,1,0) -> 0 | W648: =IF($O648=W$13,1,0) -> 0 | ... AA648: =IF($O648=AA$13,1,0) -> 0 | AB648: =IF($B648=AB$13,1,0) -> 1 | AC648: =IF($B648=AC$13,1,0) -> 0 | AD648: =IF($B648=AD$13,1,0) -> 0 | AE648: =IF($B648=AE$13,1,0) -> 0 | AF648: =IF($B648=AF$13,1,0) -> 0 | AG648: 708.0172 | AH648: 146.36271 | AI648: 76.173861 | AJ648: 50 | AK648: =LN(H648) -> 11.129772 | AL648: =LN(D648+'Models training data'!$Y$4) -> 6.9069789 | AM648: =LN(E648+'Models training data'!$Y$5) -> 5.3536328 | AN648: =LN(F648+'Models training data'!$Y$6) -> 4.800345 | AO648: =LN(G648+'Models training data'!$Y$7) -> 4.6011966 | AP648: =V648+W648+X648+Y648+Z648 -> 0 | AQ648: =AA648+AC648+AD648+AE648+AF648 -> 0 | AR648: =$C$1+SUMPRODUCT($K$1:$AQ$1,K648:AQ648) -> 85220.436 | AS648: =$C$2+SUMPRODUCT($K$2:$AQ$2,K648:AQ648) -> 67322.765 | AT648: =$C$3+SUMPRODUCT($K$3:$AQ$3,K648:AQ648) -> 11.128758 | AU648: =$C$4+SUMPRODUCT($K$4:$AQ$4,K648:AQ648) -> 68195.145 | AV648: =$C$5+SUMPRODUCT($K$5:$AQ$5,K648:AQ648) -> 11.141423 | AW648: =$C$6+SUMPRODUCT($K$6:$AQ$6,K648:AQ648) -> 68651.528 | AX648: =$C$7+SUMPRODUCT($K$7:$AQ$7,K648:AQ648) -> 11.145112 | AY648: =$C$8+SUMPRODUCT($K$8:$AQ$8,K648:AQ648) -> 11.295525 | AZ648: =$C$9+SUMPRODUCT($K$9:$AQ$9,K648:AQ648) -> 11.152737
B649: =B648 -> DL | C649: 44604 | D649: 739.84447 | E649: 153.58709 | F649: 79.982551 | G649: 50 | H649: 68819.14 | I649: =SUM(D649:G649) -> 1023.4141 | J649: =YEAR(C649) -> 2022 | K649: =IF(B649=B648,K648+1,1) -> 7 | L649: =K649^2 -> 49 | M649: =LN(L649) -> 3.8918203 | N649: =IF(K649<127,1,0) -> 1 | O649: =MONTH(C649) -> 2 | P649: =IF($O649=P$13,1,0) -> 0 | Q649: =IF($O649=Q$13,1,0) -> 1 | R649: =IF($O649=R$13,1,0) -> 0 | S649: =IF($O649=S$13,1,0) -> 0 | T649: =IF($O649=T$13,1,0) -> 0 | U649: =IF($O649=U$13,1,0) -> 0 | V649: =IF($O649=V$13,1,0) -> 0 | W649: =IF($O649=W$13,1,0) -> 0 | ... AA649: =IF($O649=AA$13,1,0) -> 0 | AB649: =IF($B649=AB$13,1,0) -> 1 | AC649: =IF($B649=AC$13,1,0) -> 0 | AD649: =IF($B649=AD$13,1,0) -> 0 | AE649: =IF($B649=AE$13,1,0) -> 0 | AF649: =IF($B649=AF$13,1,0) -> 0 | AG649: 739.84447 | AH649: 153.58709 | AI649: 79.982551 | AJ649: 50 | AK649: =LN(H649) -> 11.139237 | AL649: =LN(D649+'Models training data'!$Y$4) -> 6.9383341 | AM649: =LN(E649+'Models training data'!$Y$5) -> 5.3872398 | AN649: =LN(F649+'Models training data'!$Y$6) -> 4.8311979 | AO649: =LN(G649+'Models training data'!$Y$7) -> 4.6011966 | AP649: =V649+W649+X649+Y649+Z649 -> 0 | AQ649: =AA649+AC649+AD649+AE649+AF649 -> 0 | AR649: =$C$1+SUMPRODUCT($K$1:$AQ$1,K649:AQ649) -> 85196.046 | AS649: =$C$2+SUMPRODUCT($K$2:$AQ$2,K649:AQ649) -> 67298.667 | AT649: =$C$3+SUMPRODUCT($K$3:$AQ$3,K649:AQ649) -> 11.128501 | AU649: =$C$4+SUMPRODUCT($K$4:$AQ$4,K649:AQ649) -> 68103.929 | AV649: =$C$5+SUMPRODUCT($K$5:$AQ$5,K649:AQ649) -> 11.140198 | AW649: =$C$6+SUMPRODUCT($K$6:$AQ$6,K649:AQ649) -> 68428.487 | AX649: =$C$7+SUMPRODUCT($K$7:$AQ$7,K649:AQ649) -> 11.142545 | AY649: =$C$8+SUMPRODUCT($K$8:$AQ$8,K649:AQ649) -> 11.297322 | AZ649: =$C$9+SUMPRODUCT($K$9:$AQ$9,K649:AQ649) -> 11.157369
B650: =B649 -> DL | C650: 44611 | D650: 774.33518 | E650: 161.21957 | F650: 83.981678 | G650: 50 | H650: 69472.37 | I650: =SUM(D650:G650) -> 1069.5364 | J650: =YEAR(C650) -> 2022 | K650: =IF(B650=B649,K649+1,1) -> 8 | L650: =K650^2 -> 64 | M650: =LN(L650) -> 4.1588831 | N650: =IF(K650<127,1,0) -> 1 | O650: =MONTH(C650) -> 2 | P650: =IF($O650=P$13,1,0) -> 0 | Q650: =IF($O650=Q$13,1,0) -> 1 | R650: =IF($O650=R$13,1,0) -> 0 | S650: =IF($O650=S$13,1,0) -> 0 | T650: =IF($O650=T$13,1,0) -> 0 | U650: =IF($O650=U$13,1,0) -> 0 | V650: =IF($O650=V$13,1,0) -> 0 | W650: =IF($O650=W$13,1,0) -> 0 | ... AA650: =IF($O650=AA$13,1,0) -> 0 | AB650: =IF($B650=AB$13,1,0) -> 1 | AC650: =IF($B650=AC$13,1,0) -> 0 | AD650: =IF($B650=AD$13,1,0) -> 0 | AE650: =IF($B650=AE$13,1,0) -> 0 | AF650: =IF($B650=AF$13,1,0) -> 0 | AG650: 774.33518 | AH650: 161.21957 | AI650: 83.981678 | AJ650: 50 | AK650: =LN(H650) -> 11.148684 | AL650: =LN(D650+'Models training data'!$Y$4) -> 6.9712388 | AM650: =LN(E650+'Models training data'!$Y$5) -> 5.4215595 | AN650: =LN(F650+'Models training data'!$Y$6) -> 4.8626005 | AO650: =LN(G650+'Models training data'!$Y$7) -> 4.6011966 | AP650: =V650+W650+X650+Y650+Z650 -> 0 | AQ650: =AA650+AC650+AD650+AE650+AF650 -> 0 | AR650: =$C$1+SUMPRODUCT($K$1:$AQ$1,K650:AQ650) -> 85171.656 | AS650: =$C$2+SUMPRODUCT($K$2:$AQ$2,K650:AQ650) -> 67274.57 | AT650: =$C$3+SUMPRODUCT($K$3:$AQ$3,K650:AQ650) -> 11.128243 | AU650: =$C$4+SUMPRODUCT($K$4:$AQ$4,K650:AQ650) -> 68013.891 | AV650: =$C$5+SUMPRODUCT($K$5:$AQ$5,K650:AQ650) -> 11.13899 | AW650: =$C$6+SUMPRODUCT($K$6:$AQ$6,K650:AQ650) -> 68235.279 | AX650: =$C$7+SUMPRODUCT($K$7:$AQ$7,K650:AQ650) -> 11.140321 | AY650: =$C$8+SUMPRODUCT($K$8:$AQ$8,K650:AQ650) -> 11.299241 | AZ650: =$C$9+SUMPRODUCT($K$9:$AQ$9,K650:AQ650) -> 11.162095
B651: =B650 -> DL | C651: 44618 | D651: 811.30088 | E651: 169.25711 | F651: 88.180762 | G651: 50 | H651: 70128.652 | I651: =SUM(D651:G651) -> 1118.7388 | J651: =YEAR(C651) -> 2022 | K651: =IF(B651=B650,K650+1,1) -> 9 | L651: =K651^2 -> 81 | M651: =LN(L651) -> 4.3944492 | N651: =IF(K651<127,1,0) -> 1 | O651: =MONTH(C651) -> 2 | P651: =IF($O651=P$13,1,0) -> 0 | Q651: =IF($O651=Q$13,1,0) -> 1 | R651: =IF($O651=R$13,1,0) -> 0 | S651: =IF($O651=S$13,1,0) -> 0 | T651: =IF($O651=T$13,1,0) -> 0 | U651: =IF($O651=U$13,1,0) -> 0 | V651: =IF($O651=V$13,1,0) -> 0 | W651: =IF($O651=W$13,1,0) -> 0 | ... AA651: =IF($O651=AA$13,1,0) -> 0 | AB651: =IF($B651=AB$13,1,0) -> 1 | AC651: =IF($B651=AC$13,1,0) -> 0 | AD651: =IF($B651=AD$13,1,0) -> 0 | AE651: =IF($B651=AE$13,1,0) -> 0 | AF651: =IF($B651=AF$13,1,0) -> 0 | AG651: 811.30088 | AH651: 169.25711 | AI651: 88.180762 | AJ651: 50 | AK651: =LN(H651) -> 11.158087 | AL651: =LN(D651+'Models training data'!$Y$4) -> 7.0053425 | AM651: =LN(E651+'Models training data'!$Y$5) -> 5.4564709 | AN651: =LN(F651+'Models training data'!$Y$6) -> 4.8945452 | AO651: =LN(G651+'Models training data'!$Y$7) -> 4.6011966 | AP651: =V651+W651+X651+Y651+Z651 -> 0 | AQ651: =AA651+AC651+AD651+AE651+AF651 -> 0 | AR651: =$C$1+SUMPRODUCT($K$1:$AQ$1,K651:AQ651) -> 85147.265 | AS651: =$C$2+SUMPRODUCT($K$2:$AQ$2,K651:AQ651) -> 67250.473 | AT651: =$C$3+SUMPRODUCT($K$3:$AQ$3,K651:AQ651) -> 11.127986 | AU651: =$C$4+SUMPRODUCT($K$4:$AQ$4,K651:AQ651) -> 67925.032 | AV651: =$C$5+SUMPRODUCT($K$5:$AQ$5,K651:AQ651) -> 11.137799 | AW651: =$C$6+SUMPRODUCT($K$6:$AQ$6,K651:AQ651) -> 68064.858 | AX651: =$C$7+SUMPRODUCT($K$7:$AQ$7,K651:AQ651) -> 11.138359 | AY651: =$C$8+SUMPRODUCT($K$8:$AQ$8,K651:AQ651) -> 11.30128 | AZ651: =$C$9+SUMPRODUCT($K$9:$AQ$9,K651:AQ651) -> 11.166907
B652: =B651 -> DL | C652: 44625 | D652: 850.64018 | E652: 177.70825 | F652: 92.5898 | G652: 60.036705 | H652: 71831.675 | I652: =SUM(D652:G652) -> 1180.9749 | J652: =YEAR(C652) -> 2022 | K652: =IF(B652=B651,K651+1,1) -> 10 | L652: =K652^2 -> 100 | M652: =LN(L652) -> 4.6051702 | N652: =IF(K652<127,1,0) -> 1 | O652: =MONTH(C652) -> 3 | P652: =IF($O652=P$13,1,0) -> 0 | Q652: =IF($O652=Q$13,1,0) -> 0 | R652: =IF($O652=R$13,1,0) -> 1 | S652: =IF($O652=S$13,1,0) -> 0 | T652: =IF($O652=T$13,1,0) -> 0 | U652: =IF($O652=U$13,1,0) -> 0 | V652: =IF($O652=V$13,1,0) -> 0 | W652: =IF($O652=W$13,1,0) -> 0 | ... AA652: =IF($O652=AA$13,1,0) -> 0 | AB652: =IF($B652=AB$13,1,0) -> 1 | AC652: =IF($B652=AC$13,1,0) -> 0 | AD652: =IF($B652=AD$13,1,0) -> 0 | AE652: =IF($B652=AE$13,1,0) -> 0 | AF652: =IF($B652=AF$13,1,0) -> 0 | AG652: 850.64018 | AH652: 177.70825 | AI652: 92.5898 | AJ652: 60.036705 | AK652: =LN(H652) -> 11.182081 | AL652: =LN(D652+'Models training data'!$Y$4) -> 7.0404023 | AM652: =LN(E652+'Models training data'!$Y$5) -> 5.4919099 | AN652: =LN(F652+'Models training data'!$Y$6) -> 4.9270238 | AO652: =LN(G652+'Models training data'!$Y$7) -> 4.6972035 | AP652: =V652+W652+X652+Y652+Z652 -> 0 | AQ652: =AA652+AC652+AD652+AE652+AF652 -> 0 | AR652: =$C$1+SUMPRODUCT($K$1:$AQ$1,K652:AQ652) -> 84207.664 | AS652: =$C$2+SUMPRODUCT($K$2:$AQ$2,K652:AQ652) -> 66308.765 | AT652: =$C$3+SUMPRODUCT($K$3:$AQ$3,K652:AQ652) -> 11.116921 | AU652: =$C$4+SUMPRODUCT($K$4:$AQ$4,K652:AQ652) -> 66875.746 | AV652: =$C$5+SUMPRODUCT($K$5:$AQ$5,K652:AQ652) -> 11.125204 | AW652: =$C$6+SUMPRODUCT($K$6:$AQ$6,K652:AQ652) -> 67165.448 | AX652: =$C$7+SUMPRODUCT($K$7:$AQ$7,K652:AQ652) -> 11.127923 | AY652: =$C$8+SUMPRODUCT($K$8:$AQ$8,K652:AQ652) -> 11.305038 | AZ652: =$C$9+SUMPRODUCT($K$9:$AQ$9,K652:AQ652) -> 11.183733
B653: =B652 -> DL | C653: 44632 | D653: 892.31417 | E653: 186.5878 | F653: 97.21929 | G653: 51.003671 | H653: 71559.813 | I653: =SUM(D653:G653) -> 1227.1249 | J653: =YEAR(C653) -> 2022 | K653: =IF(B653=B652,K652+1,1) -> 11 | L653: =K653^2 -> 121 | M653: =LN(L653) -> 4.7957905 | N653: =IF(K653<127,1,0) -> 1 | O653: =MONTH(C653) -> 3 | P653: =IF($O653=P$13,1,0) -> 0 | Q653: =IF($O653=Q$13,1,0) -> 0 | R653: =IF($O653=R$13,1,0) -> 1 | S653: =IF($O653=S$13,1,0) -> 0 | T653: =IF($O653=T$13,1,0) -> 0 | U653: =IF($O653=U$13,1,0) -> 0 | V653: =IF($O653=V$13,1,0) -> 0 | W653: =IF($O653=W$13,1,0) -> 0 | ... AA653: =IF($O653=AA$13,1,0) -> 0 | AB653: =IF($B653=AB$13,1,0) -> 1 | AC653: =IF($B653=AC$13,1,0) -> 0 | AD653: =IF($B653=AD$13,1,0) -> 0 | AE653: =IF($B653=AE$13,1,0) -> 0 | AF653: =IF($B653=AF$13,1,0) -> 0 | AG653: 892.31417 | AH653: 186.5878 | AI653: 97.21929 | AJ653: 51.003671 | AK653: =LN(H653) -> 11.178289 | AL653: =LN(D653+'Models training data'!$Y$4) -> 7.0762491 | AM653: =LN(E653+'Models training data'!$Y$5) -> 5.5278401 | AN653: =LN(F653+'Models training data'!$Y$6) -> 4.9600279 | AO653: =LN(G653+'Models training data'!$Y$7) -> 4.6112229 | AP653: =V653+W653+X653+Y653+Z653 -> 0 | AQ653: =AA653+AC653+AD653+AE653+AF653 -> 0 | AR653: =$C$1+SUMPRODUCT($K$1:$AQ$1,K653:AQ653) -> 84183.274 | AS653: =$C$2+SUMPRODUCT($K$2:$AQ$2,K653:AQ653) -> 66284.667 | AT653: =$C$3+SUMPRODUCT($K$3:$AQ$3,K653:AQ653) -> 11.116663 | AU653: =$C$4+SUMPRODUCT($K$4:$AQ$4,K653:AQ653) -> 66789.245 | AV653: =$C$5+SUMPRODUCT($K$5:$AQ$5,K653:AQ653) -> 11.124047 | AW653: =$C$6+SUMPRODUCT($K$6:$AQ$6,K653:AQ653) -> 67027.543 | AX653: =$C$7+SUMPRODUCT($K$7:$AQ$7,K653:AQ653) -> 11.126336 | AY653: =$C$8+SUMPRODUCT($K$8:$AQ$8,K653:AQ653) -> 11.305876 | AZ653: =$C$9+SUMPRODUCT($K$9:$AQ$9,K653:AQ653) -> 11.178011
B654: =B653 -> DL | C654: 44639 | D654: 936.32927 | E654: 195.91426 | F654: 102.08025 | G654: 50.100367 | H654: 72117.989 | I654: =SUM(D654:G654) -> 1284.4242 | J654: =YEAR(C654) -> 2022 | K654: =IF(B654=B653,K653+1,1) -> 12 | L654: =K654^2 -> 144 | M654: =LN(L654) -> 4.9698133 | N654: =IF(K654<127,1,0) -> 1 | O654: =MONTH(C654) -> 3 | P654: =IF($O654=P$13,1,0) -> 0 | Q654: =IF($O654=Q$13,1,0) -> 0 | R654: =IF($O654=R$13,1,0) -> 1 | S654: =IF($O654=S$13,1,0) -> 0 | T654: =IF($O654=T$13,1,0) -> 0 | U654: =IF($O654=U$13,1,0) -> 0 | V654: =IF($O654=V$13,1,0) -> 0 | W654: =IF($O654=W$13,1,0) -> 0 | ... AA654: =IF($O654=AA$13,1,0) -> 0 | AB654: =IF($B654=AB$13,1,0) -> 1 | AC654: =IF($B654=AC$13,1,0) -> 0 | AD654: =IF($B654=AD$13,1,0) -> 0 | AE654: =IF($B654=AE$13,1,0) -> 0 | AF654: =IF($B654=AF$13,1,0) -> 0 | AG654: 936.32927 | AH654: 195.91426 | AI654: 102.08025 | AJ654: 50.100367 | AK654: =LN(H654) -> 11.186059 | AL654: =LN(D654+'Models training data'!$Y$4) -> 7.1127642 | AM654: =LN(E654+'Models training data'!$Y$5) -> 5.5642382 | AN654: =LN(F654+'Models training data'!$Y$6) -> 4.9935484 | AO654: =LN(G654+'Models training data'!$Y$7) -> 4.6022038 | AP654: =V654+W654+X654+Y654+Z654 -> 0 | AQ654: =AA654+AC654+AD654+AE654+AF654 -> 0 | AR654: =$C$1+SUMPRODUCT($K$1:$AQ$1,K654:AQ654) -> 84158.884 | AS654: =$C$2+SUMPRODUCT($K$2:$AQ$2,K654:AQ654) -> 66260.57 | AT654: =$C$3+SUMPRODUCT($K$3:$AQ$3,K654:AQ654) -> 11.116405 | AU654: =$C$4+SUMPRODUCT($K$4:$AQ$4,K654:AQ654) -> 66703.923 | AV654: =$C$5+SUMPRODUCT($K$5:$AQ$5,K654:AQ654) -> 11.122907 | AW654: =$C$6+SUMPRODUCT($K$6:$AQ$6,K654:AQ654) -> 66901.646 | AX654: =$C$7+SUMPRODUCT($K$7:$AQ$7,K654:AQ654) -> 11.124886 | AY654: =$C$8+SUMPRODUCT($K$8:$AQ$8,K654:AQ654) -> 11.308135 | AZ654: =$C$9+SUMPRODUCT($K$9:$AQ$9,K654:AQ654) -> 11.181928
B655: =B654 -> DL | C655: 44646 | D655: 982.7253 | E655: 205.70851 | F655: 107.18427 | G655: 75.214236 | H655: 75099.379 | I655: =SUM(D655:G655) -> 1370.8323 | J655: =YEAR(C655) -> 2022 | K655: =IF(B655=B654,K654+1,1) -> 13 | L655: =K655^2 -> 169 | M655: =LN(L655) -> 5.1298987 | N655: =IF(K655<127,1,0) -> 1 | O655: =MONTH(C655) -> 3 | P655: =IF($O655=P$13,1,0) -> 0 | Q655: =IF($O655=Q$13,1,0) -> 0 | R655: =IF($O655=R$13,1,0) -> 1 | S655: =IF($O655=S$13,1,0) -> 0 | T655: =IF($O655=T$13,1,0) -> 0 | U655: =IF($O655=U$13,1,0) -> 0 | V655: =IF($O655=V$13,1,0) -> 0 | W655: =IF($O655=W$13,1,0) -> 0 | ... AA655: =IF($O655=AA$13,1,0) -> 0 | AB655: =IF($B655=AB$13,1,0) -> 1 | AC655: =IF($B655=AC$13,1,0) -> 0 | AD655: =IF($B655=AD$13,1,0) -> 0 | AE655: =IF($B655=AE$13,1,0) -> 0 | AF655: =IF($B655=AF$13,1,0) -> 0 | AG655: 982.7253 | AH655: 205.70851 | AI655: 107.18427 | AJ655: 75.214236 | AK655: =LN(H655) -> 11.226568 | AL655: =LN(D655+'Models training data'!$Y$4) -> 7.1498635 | AM655: =LN(E655+'Models training data'!$Y$5) -> 5.6010873 | AN655: =LN(F655+'Models training data'!$Y$6) -> 5.027576 | AO655: =LN(G655+'Models training data'!$Y$7) -> 4.826854 | AP655: =V655+W655+X655+Y655+Z655 -> 0 | AQ655: =AA655+AC655+AD655+AE655+AF655 -> 0 | AR655: =$C$1+SUMPRODUCT($K$1:$AQ$1,K655:AQ655) -> 84134.493 | AS655: =$C$2+SUMPRODUCT($K$2:$AQ$2,K655:AQ655) -> 66236.472 | AT655: =$C$3+SUMPRODUCT($K$3:$AQ$3,K655:AQ655) -> 11.116148 | AU655: =$C$4+SUMPRODUCT($K$4:$AQ$4,K655:AQ655) -> 66619.779 | AV655: =$C$5+SUMPRODUCT($K$5:$AQ$5,K655:AQ655) -> 11.121784 | AW655: =$C$6+SUMPRODUCT($K$6:$AQ$6,K655:AQ655) -> 66785.831 | AX655: =$C$7+SUMPRODUCT($K$7:$AQ$7,K655:AQ655) -> 11.123553 | AY655: =$C$8+SUMPRODUCT($K$8:$AQ$8,K655:AQ655) -> 11.314673 | AZ655: =$C$9+SUMPRODUCT($K$9:$AQ$9,K655:AQ655) -> 11.214964
... B799: =B798 -> DL | C799: 45654 | D799: 380.16106 | E799: 100 | F799: 50 | G799: 50 | H799: 65472.965 | I799: =SUM(D799:G799) -> 580.16106 | J799: =YEAR(C799) -> 2024 | K799: =IF(B799=B798,K798+1,1) -> 157 | L799: =K799^2 -> 24649 | M799: =LN(L799) -> 10.112492 | N799: =IF(K799<127,1,0) -> 0 | O799: =MONTH(C799) -> 12 | P799: =IF($O799=P$13,1,0) -> 0 | Q799: =IF($O799=Q$13,1,0) -> 0 | R799: =IF($O799=R$13,1,0) -> 0 | S799: =IF($O799=S$13,1,0) -> 0 | T799: =IF($O799=T$13,1,0) -> 0 | U799: =IF($O799=U$13,1,0) -> 0 | V799: =IF($O799=V$13,1,0) -> 0 | W799: =IF($O799=W$13,1,0) -> 0 | ... AA799: =IF($O799=AA$13,1,0) -> 1 | AB799: =IF($B799=AB$13,1,0) -> 1 | AC799: =IF($B799=AC$13,1,0) -> 0 | AD799: =IF($B799=AD$13,1,0) -> 0 | AE799: =IF($B799=AE$13,1,0) -> 0 | AF799: =IF($B799=AF$13,1,0) -> 0 | AG799: 380.16106 | AH799: 100 | AI799: 50 | AJ799: 50 | AK799: =LN(H799) -> 11.089393 | AL799: =LN(D799+'Models training data'!$Y$4) -> 6.5093171 | AM799: =LN(E799+'Models training data'!$Y$5) -> 5.1060187 | AN799: =LN(F799+'Models training data'!$Y$6) -> 4.557853 | AO799: =LN(G799+'Models training data'!$Y$7) -> 4.6011966 | AP799: =V799+W799+X799+Y799+Z799 -> 0 | AQ799: =AA799+AC799+AD799+AE799+AF799 -> 1 | AR799: =$C$1+SUMPRODUCT($K$1:$AQ$1,K799:AQ799) -> 81456.478 | AS799: =$C$2+SUMPRODUCT($K$2:$AQ$2,K799:AQ799) -> 63597.911 | AT799: =$C$3+SUMPRODUCT($K$3:$AQ$3,K799:AQ799) -> 11.087477 | AU799: =$C$4+SUMPRODUCT($K$4:$AQ$4,K799:AQ799) -> 68248.531 | AV799: =$C$5+SUMPRODUCT($K$5:$AQ$5,K799:AQ799) -> 11.154151 | AW799: =$C$6+SUMPRODUCT($K$6:$AQ$6,K799:AQ799) -> 64406.943 | AX799: =$C$7+SUMPRODUCT($K$7:$AQ$7,K799:AQ799) -> 11.095208 | AY799: =$C$8+SUMPRODUCT($K$8:$AQ$8,K799:AQ799) -> 11.181909 | AZ799: =$C$9+SUMPRODUCT($K$9:$AQ$9,K799:AQ799) -> 11.123331
B800: MD | C800: 44562 | D800: 810 | E800: 160 | F800: 80 | G800: 50 | H800: 68221.843 | I800: =SUM(D800:G800) -> 1100 | J800: =YEAR(C800) -> 2022 | K800: =IF(B800=B799,K799+1,1) -> 1 | L800: =K800^2 -> 1 | M800: =LN(L800) -> 0 | N800: =IF(K800<127,1,0) -> 1 | O800: =MONTH(C800) -> 1 | P800: =IF($O800=P$13,1,0) -> 1 | Q800: =IF($O800=Q$13,1,0) -> 0 | R800: =IF($O800=R$13,1,0) -> 0 | S800: =IF($O800=S$13,1,0) -> 0 | T800: =IF($O800=T$13,1,0) -> 0 | U800: =IF($O800=U$13,1,0) -> 0 | V800: =IF($O800=V$13,1,0) -> 0 | W800: =IF($O800=W$13,1,0) -> 0 | ... AA800: =IF($O800=AA$13,1,0) -> 0 | AB800: =IF($B800=AB$13,1,0) -> 0 | AC800: =IF($B800=AC$13,1,0) -> 1 | AD800: =IF($B800=AD$13,1,0) -> 0 | AE800: =IF($B800=AE$13,1,0) -> 0 | AF800: =IF($B800=AF$13,1,0) -> 0 | AG800: 810 | AH800: 160 | AI800: 80 | AJ800: 50 | AK800: =LN(H800) -> 11.13052 | AL800: =LN(D800+'Models training data'!$Y$4) -> 7.0041619 | AM800: =LN(E800+'Models training data'!$Y$5) -> 5.4161541 | AN800: =LN(F800+'Models training data'!$Y$6) -> 4.831337 | AO800: =LN(G800+'Models training data'!$Y$7) -> 4.6011966 | AP800: =V800+W800+X800+Y800+Z800 -> 0 | AQ800: =AA800+AC800+AD800+AE800+AF800 -> 1 | AR800: =$C$1+SUMPRODUCT($K$1:$AQ$1,K800:AQ800) -> 86392.099 | AS800: =$C$2+SUMPRODUCT($K$2:$AQ$2,K800:AQ800) -> 70018.158 | AT800: =$C$3+SUMPRODUCT($K$3:$AQ$3,K800:AQ800) -> 11.161263 | AU800: =$C$4+SUMPRODUCT($K$4:$AQ$4,K800:AQ800) -> 71123.666 | AV800: =$C$5+SUMPRODUCT($K$5:$AQ$5,K800:AQ800) -> 11.177272 | AW800: =$C$6+SUMPRODUCT($K$6:$AQ$6,K800:AQ800) -> 73209.139 | AX800: =$C$7+SUMPRODUCT($K$7:$AQ$7,K800:AQ800) -> 11.19899 | AY800: =$C$8+SUMPRODUCT($K$8:$AQ$8,K800:AQ800) -> 11.224446 | AZ800: =$C$9+SUMPRODUCT($K$9:$AQ$9,K800:AQ800) -> 11.154192
B801: =B800 -> MD | C801: 44569 | D801: 822.15 | E801: 164 | F801: 83.6 | G801: 50 | H801: 68677.095 | I801: =SUM(D801:G801) -> 1119.75 | J801: =YEAR(C801) -> 2022 | K801: =IF(B801=B800,K800+1,1) -> 2 | L801: =K801^2 -> 4 | M801: =LN(L801) -> 1.3862944 | N801: =IF(K801<127,1,0) -> 1 | O801: =MONTH(C801) -> 1 | P801: =IF($O801=P$13,1,0) -> 1 | Q801: =IF($O801=Q$13,1,0) -> 0 | R801: =IF($O801=R$13,1,0) -> 0 | S801: =IF($O801=S$13,1,0) -> 0 | T801: =IF($O801=T$13,1,0) -> 0 | U801: =IF($O801=U$13,1,0) -> 0 | V801: =IF($O801=V$13,1,0) -> 0 | W801: =IF($O801=W$13,1,0) -> 0 | ... AA801: =IF($O801=AA$13,1,0) -> 0 | AB801: =IF($B801=AB$13,1,0) -> 0 | AC801: =IF($B801=AC$13,1,0) -> 1 | AD801: =IF($B801=AD$13,1,0) -> 0 | AE801: =IF($B801=AE$13,1,0) -> 0 | AF801: =IF($B801=AF$13,1,0) -> 0 | AG801: 822.15 | AH801: 164 | AI801: 83.6 | AJ801: 50 | AK801: =LN(H801) -> 11.137171 | AL801: =LN(D801+'Models training data'!$Y$4) -> 7.0151348 | AM801: =LN(E801+'Models training data'!$Y$5) -> 5.4337748 | AN801: =LN(F801+'Models training data'!$Y$6) -> 4.8596456 | AO801: =LN(G801+'Models training data'!$Y$7) -> 4.6011966 | AP801: =V801+W801+X801+Y801+Z801 -> 0 | AQ801: =AA801+AC801+AD801+AE801+AF801 -> 1 | AR801: =$C$1+SUMPRODUCT($K$1:$AQ$1,K801:AQ801) -> 86367.709 | AS801: =$C$2+SUMPRODUCT($K$2:$AQ$2,K801:AQ801) -> 69994.061 | AT801: =$C$3+SUMPRODUCT($K$3:$AQ$3,K801:AQ801) -> 11.161005 | AU801: =$C$4+SUMPRODUCT($K$4:$AQ$4,K801:AQ801) -> 71026.556 | AV801: =$C$5+SUMPRODUCT($K$5:$AQ$5,K801:AQ801) -> 11.175962 | AW801: =$C$6+SUMPRODUCT($K$6:$AQ$6,K801:AQ801) -> 72206.22 | AX801: =$C$7+SUMPRODUCT($K$7:$AQ$7,K801:AQ801) -> 11.187445 | AY801: =$C$8+SUMPRODUCT($K$8:$AQ$8,K801:AQ801) -> 11.225415 | AZ801: =$C$9+SUMPRODUCT($K$9:$AQ$9,K801:AQ801) -> 11.157688
B802: =B801 -> MD | C802: 44576 | D802: 843.4125 | E802: 170.2 | F802: 87.74 | G802: 50 | H802: 69235.894 | I802: =SUM(D802:G802) -> 1151.3525 | J802: =YEAR(C802) -> 2022 | K802: =IF(B802=B801,K801+1,1) -> 3 | L802: =K802^2 -> 9 | M802: =LN(L802) -> 2.1972246 | N802: =IF(K802<127,1,0) -> 1 | O802: =MONTH(C802) -> 1 | P802: =IF($O802=P$13,1,0) -> 1 | Q802: =IF($O802=Q$13,1,0) -> 0 | R802: =IF($O802=R$13,1,0) -> 0 | S802: =IF($O802=S$13,1,0) -> 0 | T802: =IF($O802=T$13,1,0) -> 0 | U802: =IF($O802=U$13,1,0) -> 0 | V802: =IF($O802=V$13,1,0) -> 0 | W802: =IF($O802=W$13,1,0) -> 0 | ... AA802: =IF($O802=AA$13,1,0) -> 0 | AB802: =IF($B802=AB$13,1,0) -> 0 | AC802: =IF($B802=AC$13,1,0) -> 1 | AD802: =IF($B802=AD$13,1,0) -> 0 | AE802: =IF($B802=AE$13,1,0) -> 0 | AF802: =IF($B802=AF$13,1,0) -> 0 | AG802: 843.4125 | AH802: 170.2 | AI802: 87.74 | AJ802: 50 | AK802: =LN(H802) -> 11.145275 | AL802: =LN(D802+'Models training data'!$Y$4) -> 7.0340524 | AM802: =LN(E802+'Models training data'!$Y$5) -> 5.4604876 | AN802: =LN(F802+'Models training data'!$Y$6) -> 4.8912396 | AO802: =LN(G802+'Models training data'!$Y$7) -> 4.6011966 | AP802: =V802+W802+X802+Y802+Z802 -> 0 | AQ802: =AA802+AC802+AD802+AE802+AF802 -> 1 | AR802: =$C$1+SUMPRODUCT($K$1:$AQ$1,K802:AQ802) -> 86343.318 | AS802: =$C$2+SUMPRODUCT($K$2:$AQ$2,K802:AQ802) -> 69969.963 | AT802: =$C$3+SUMPRODUCT($K$3:$AQ$3,K802:AQ802) -> 11.160748 | AU802: =$C$4+SUMPRODUCT($K$4:$AQ$4,K802:AQ802) -> 70930.625 | AV802: =$C$5+SUMPRODUCT($K$5:$AQ$5,K802:AQ802) -> 11.17467 | AW802: =$C$6+SUMPRODUCT($K$6:$AQ$6,K802:AQ802) -> 71619.55 | AX802: =$C$7+SUMPRODUCT($K$7:$AQ$7,K802:AQ802) -> 11.180692 | AY802: =$C$8+SUMPRODUCT($K$8:$AQ$8,K802:AQ802) -> 11.226893 | AZ802: =$C$9+SUMPRODUCT($K$9:$AQ$9,K802:AQ802) -> 11.161952
B803: =B802 -> MD | C803: 44583 | D803: 871.69162 | E803: 177.71 | F803: 92.123 | G803: 66.781509 | H803: 71491.716 | I803: =SUM(D803:G803) -> 1208.3061 | J803: =YEAR(C803) -> 2022 | K803: =IF(B803=B802,K802+1,1) -> 4 | L803: =K803^2 -> 16 | M803: =LN(L803) -> 2.7725887 | N803: =IF(K803<127,1,0) -> 1 | O803: =MONTH(C803) -> 1 | P803: =IF($O803=P$13,1,0) -> 1 | Q803: =IF($O803=Q$13,1,0) -> 0 | R803: =IF($O803=R$13,1,0) -> 0 | S803: =IF($O803=S$13,1,0) -> 0 | T803: =IF($O803=T$13,1,0) -> 0 | U803: =IF($O803=U$13,1,0) -> 0 | V803: =IF($O803=V$13,1,0) -> 0 | W803: =IF($O803=W$13,1,0) -> 0 | ... AA803: =IF($O803=AA$13,1,0) -> 0 | AB803: =IF($B803=AB$13,1,0) -> 0 | AC803: =IF($B803=AC$13,1,0) -> 1 | AD803: =IF($B803=AD$13,1,0) -> 0 | AE803: =IF($B803=AE$13,1,0) -> 0 | AF803: =IF($B803=AF$13,1,0) -> 0 | AG803: 871.69162 | AH803: 177.71 | AI803: 92.123 | AJ803: 66.781509 | AK803: =LN(H803) -> 11.177337 | AL803: =LN(D803+'Models training data'!$Y$4) -> 7.0586708 | AM803: =LN(E803+'Models training data'!$Y$5) -> 5.4919171 | AN803: =LN(F803+'Models training data'!$Y$6) -> 4.9236347 | AO803: =LN(G803+'Models training data'!$Y$7) -> 4.7569032 | AP803: =V803+W803+X803+Y803+Z803 -> 0 | AQ803: =AA803+AC803+AD803+AE803+AF803 -> 1 | AR803: =$C$1+SUMPRODUCT($K$1:$AQ$1,K803:AQ803) -> 86318.928 | AS803: =$C$2+SUMPRODUCT($K$2:$AQ$2,K803:AQ803) -> 69945.866 | AT803: =$C$3+SUMPRODUCT($K$3:$AQ$3,K803:AQ803) -> 11.16049 | AU803: =$C$4+SUMPRODUCT($K$4:$AQ$4,K803:AQ803) -> 70835.873 | AV803: =$C$5+SUMPRODUCT($K$5:$AQ$5,K803:AQ803) -> 11.173394 | AW803: =$C$6+SUMPRODUCT($K$6:$AQ$6,K803:AQ803) -> 71203.301 | AX803: =$C$7+SUMPRODUCT($K$7:$AQ$7,K803:AQ803) -> 11.1759 | AY803: =$C$8+SUMPRODUCT($K$8:$AQ$8,K803:AQ803) -> 11.231377 | AZ803: =$C$9+SUMPRODUCT($K$9:$AQ$9,K803:AQ803) -> 11.185909
B804: =B803 -> MD | C804: 44590 | D804: 905.55216 | E804: 186.0955 | F804: 96.72875 | G804: 51.678151 | H804: 70653.953 | I804: =SUM(D804:G804) -> 1240.0546 | J804: =YEAR(C804) -> 2022 | K804: =IF(B804=B803,K803+1,1) -> 5 | L804: =K804^2 -> 25 | M804: =LN(L804) -> 3.2188758 | N804: =IF(K804<127,1,0) -> 1 | O804: =MONTH(C804) -> 1 | P804: =IF($O804=P$13,1,0) -> 1 | Q804: =IF($O804=Q$13,1,0) -> 0 | R804: =IF($O804=R$13,1,0) -> 0 | S804: =IF($O804=S$13,1,0) -> 0 | T804: =IF($O804=T$13,1,0) -> 0 | U804: =IF($O804=U$13,1,0) -> 0 | V804: =IF($O804=V$13,1,0) -> 0 | W804: =IF($O804=W$13,1,0) -> 0 | ... AA804: =IF($O804=AA$13,1,0) -> 0 | AB804: =IF($B804=AB$13,1,0) -> 0 | AC804: =IF($B804=AC$13,1,0) -> 1 | AD804: =IF($B804=AD$13,1,0) -> 0 | AE804: =IF($B804=AE$13,1,0) -> 0 | AF804: =IF($B804=AF$13,1,0) -> 0 | AG804: 905.55216 | AH804: 186.0955 | AI804: 96.72875 | AJ804: 51.678151 | AK804: =LN(H804) -> 11.165549 | AL804: =LN(D804+'Models training data'!$Y$4) -> 7.0873723 | AM804: =LN(E804+'Models training data'!$Y$5) -> 5.5258815 | AN804: =LN(F804+'Models training data'!$Y$6) -> 4.9565819 | AO804: =LN(G804+'Models training data'!$Y$7) -> 4.6179046 | AP804: =V804+W804+X804+Y804+Z804 -> 0 | AQ804: =AA804+AC804+AD804+AE804+AF804 -> 1 | AR804: =$C$1+SUMPRODUCT($K$1:$AQ$1,K804:AQ804) -> 86294.538 | AS804: =$C$2+SUMPRODUCT($K$2:$AQ$2,K804:AQ804) -> 69921.769 | AT804: =$C$3+SUMPRODUCT($K$3:$AQ$3,K804:AQ804) -> 11.160232 | AU804: =$C$4+SUMPRODUCT($K$4:$AQ$4,K804:AQ804) -> 70742.3 | AV804: =$C$5+SUMPRODUCT($K$5:$AQ$5,K804:AQ804) -> 11.172135 | AW804: =$C$6+SUMPRODUCT($K$6:$AQ$6,K804:AQ804) -> 70880.433 | AX804: =$C$7+SUMPRODUCT($K$7:$AQ$7,K804:AQ804) -> 11.172184 | AY804: =$C$8+SUMPRODUCT($K$8:$AQ$8,K804:AQ804) -> 11.23102 | AZ804: =$C$9+SUMPRODUCT($K$9:$AQ$9,K804:AQ804) -> 11.17343
B805: =B804 -> MD | C805: 44597 | D805: 944.02293 | E805: 195.15028 | F805: 101.56515 | G805: 50.167815 | H805: 70771.539 | I805: =SUM(D805:G805) -> 1290.9062 | J805: =YEAR(C805) -> 2022 | K805: =IF(B805=B804,K804+1,1) -> 6 | L805: =K805^2 -> 36 | M805: =LN(L805) -> 3.5835189 | N805: =IF(K805<127,1,0) -> 1 | O805: =MONTH(C805) -> 2 | P805: =IF($O805=P$13,1,0) -> 0 | Q805: =IF($O805=Q$13,1,0) -> 1 | R805: =IF($O805=R$13,1,0) -> 0 | S805: =IF($O805=S$13,1,0) -> 0 | T805: =IF($O805=T$13,1,0) -> 0 | U805: =IF($O805=U$13,1,0) -> 0 | V805: =IF($O805=V$13,1,0) -> 0 | W805: =IF($O805=W$13,1,0) -> 0 | ... AA805: =IF($O805=AA$13,1,0) -> 0 | AB805: =IF($B805=AB$13,1,0) -> 0 | AC805: =IF($B805=AC$13,1,0) -> 1 | AD805: =IF($B805=AD$13,1,0) -> 0 | AE805: =IF($B805=AE$13,1,0) -> 0 | AF805: =IF($B805=AF$13,1,0) -> 0 | AG805: 944.02293 | AH805: 195.15028 | AI805: 101.56515 | AJ805: 50.167815 | AK805: =LN(H805) -> 11.167212 | AL805: =LN(D805+'Models training data'!$Y$4) -> 7.1190122 | AM805: =LN(E805+'Models training data'!$Y$5) -> 5.5613059 | AN805: =LN(F805+'Models training data'!$Y$6) -> 4.9900491 | AO805: =LN(G805+'Models training data'!$Y$7) -> 4.6028801 | AP805: =V805+W805+X805+Y805+Z805 -> 0 | AQ805: =AA805+AC805+AD805+AE805+AF805 -> 1 | AR805: =$C$1+SUMPRODUCT($K$1:$AQ$1,K805:AQ805) -> 85220.436 | AS805: =$C$2+SUMPRODUCT($K$2:$AQ$2,K805:AQ805) -> 68845.56 | AT805: =$C$3+SUMPRODUCT($K$3:$AQ$3,K805:AQ805) -> 11.148281 | AU805: =$C$4+SUMPRODUCT($K$4:$AQ$4,K805:AQ805) -> 69717.94 | AV805: =$C$5+SUMPRODUCT($K$5:$AQ$5,K805:AQ805) -> 11.160945 | AW805: =$C$6+SUMPRODUCT($K$6:$AQ$6,K805:AQ805) -> 70174.324 | AX805: =$C$7+SUMPRODUCT($K$7:$AQ$7,K805:AQ805) -> 11.164634 | AY805: =$C$8+SUMPRODUCT($K$8:$AQ$8,K805:AQ805) -> 11.23303 | AZ805: =$C$9+SUMPRODUCT($K$9:$AQ$9,K805:AQ805) -> 11.176503
B806: =B805 -> MD | C806: 44604 | D806: 986.45929 | E806: 204.78279 | F806: 106.6434 | G806: 58.940035 | H806: 72340.235 | I806: =SUM(D806:G806) -> 1356.8255 | J806: =YEAR(C806) -> 2022 | K806: =IF(B806=B805,K805+1,1) -> 7 | L806: =K806^2 -> 49 | M806: =LN(L806) -> 3.8918203 | N806: =IF(K806<127,1,0) -> 1 | O806: =MONTH(C806) -> 2 | P806: =IF($O806=P$13,1,0) -> 0 | Q806: =IF($O806=Q$13,1,0) -> 1 | R806: =IF($O806=R$13,1,0) -> 0 | S806: =IF($O806=S$13,1,0) -> 0 | T806: =IF($O806=T$13,1,0) -> 0 | U806: =IF($O806=U$13,1,0) -> 0 | V806: =IF($O806=V$13,1,0) -> 0 | W806: =IF($O806=W$13,1,0) -> 0 | ... AA806: =IF($O806=AA$13,1,0) -> 0 | AB806: =IF($B806=AB$13,1,0) -> 0 | AC806: =IF($B806=AC$13,1,0) -> 1 | AD806: =IF($B806=AD$13,1,0) -> 0 | AE806: =IF($B806=AE$13,1,0) -> 0 | AF806: =IF($B806=AF$13,1,0) -> 0 | AG806: 986.45929 | AH806: 204.78279 | AI806: 106.6434 | AJ806: 58.940035 | AK806: =LN(H806) -> 11.189136 | AL806: =LN(D806+'Models training data'!$Y$4) -> 7.1527903 | AM806: =LN(E806+'Models training data'!$Y$5) -> 5.5976619 | AN806: =LN(F806+'Models training data'!$Y$6) -> 5.0240245 | AO806: =LN(G806+'Models training data'!$Y$7) -> 4.6871507 | AP806: =V806+W806+X806+Y806+Z806 -> 0 | AQ806: =AA806+AC806+AD806+AE806+AF806 -> 1 | AR806: =$C$1+SUMPRODUCT($K$1:$AQ$1,K806:AQ806) -> 85196.046 | AS806: =$C$2+SUMPRODUCT($K$2:$AQ$2,K806:AQ806) -> 68821.463 | AT806: =$C$3+SUMPRODUCT($K$3:$AQ$3,K806:AQ806) -> 11.148023 | AU806: =$C$4+SUMPRODUCT($K$4:$AQ$4,K806:AQ806) -> 69626.724 | AV806: =$C$5+SUMPRODUCT($K$5:$AQ$5,K806:AQ806) -> 11.15972 | AW806: =$C$6+SUMPRODUCT($K$6:$AQ$6,K806:AQ806) -> 69951.282 | AX806: =$C$7+SUMPRODUCT($K$7:$AQ$7,K806:AQ806) -> 11.162067 | AY806: =$C$8+SUMPRODUCT($K$8:$AQ$8,K806:AQ806) -> 11.236855 | AZ806: =$C$9+SUMPRODUCT($K$9:$AQ$9,K806:AQ806) -> 11.192027
B807: =B806 -> MD | C807: 44611 | D807: 1032.4469 | E807: 214.95943 | F807: 111.97557 | G807: 50.894003 | H807: 72155.164 | I807: =SUM(D807:G807) -> 1410.2759 | J807: =YEAR(C807) -> 2022 | K807: =IF(B807=B806,K806+1,1) -> 8 | L807: =K807^2 -> 64 | M807: =LN(L807) -> 4.1588831 | N807: =IF(K807<127,1,0) -> 1 | O807: =MONTH(C807) -> 2 | P807: =IF($O807=P$13,1,0) -> 0 | Q807: =IF($O807=Q$13,1,0) -> 1 | R807: =IF($O807=R$13,1,0) -> 0 | S807: =IF($O807=S$13,1,0) -> 0 | T807: =IF($O807=T$13,1,0) -> 0 | U807: =IF($O807=U$13,1,0) -> 0 | V807: =IF($O807=V$13,1,0) -> 0 | W807: =IF($O807=W$13,1,0) -> 0 | ... AA807: =IF($O807=AA$13,1,0) -> 0 | AB807: =IF($B807=AB$13,1,0) -> 0 | AC807: =IF($B807=AC$13,1,0) -> 1 | AD807: =IF($B807=AD$13,1,0) -> 0 | AE807: =IF($B807=AE$13,1,0) -> 0 | AF807: =IF($B807=AF$13,1,0) -> 0 | AG807: 1032.4469 | AH807: 214.95943 | AI807: 111.97557 | AJ807: 50.894003 | AK807: =LN(H807) -> 11.186574 | AL807: =LN(D807+'Models training data'!$Y$4) -> 7.1881511 | AM807: =LN(E807+'Models training data'!$Y$5) -> 5.6346879 | AN807: =LN(F807+'Models training data'!$Y$6) -> 5.0584984 | AO807: =LN(G807+'Models training data'!$Y$7) -> 4.6101322 | AP807: =V807+W807+X807+Y807+Z807 -> 0 | AQ807: =AA807+AC807+AD807+AE807+AF807 -> 1 | AR807: =$C$1+SUMPRODUCT($K$1:$AQ$1,K807:AQ807) -> 85171.656 | AS807: =$C$2+SUMPRODUCT($K$2:$AQ$2,K807:AQ807) -> 68797.366 | AT807: =$C$3+SUMPRODUCT($K$3:$AQ$3,K807:AQ807) -> 11.147765 | AU807: =$C$4+SUMPRODUCT($K$4:$AQ$4,K807:AQ807) -> 69536.687 | AV807: =$C$5+SUMPRODUCT($K$5:$AQ$5,K807:AQ807) -> 11.158513 | AW807: =$C$6+SUMPRODUCT($K$6:$AQ$6,K807:AQ807) -> 69758.075 | AX807: =$C$7+SUMPRODUCT($K$7:$AQ$7,K807:AQ807) -> 11.159843 | AY807: =$C$8+SUMPRODUCT($K$8:$AQ$8,K807:AQ807) -> 11.238162 | AZ807: =$C$9+SUMPRODUCT($K$9:$AQ$9,K807:AQ807) -> 11.187589
B808: =B807 -> MD | C808: 44618 | D808: 1081.7345 | E808: 225.67615 | F808: 117.57435 | G808: 50.0894 | H808: 72720.43 | I808: =SUM(D808:G808) -> 1475.0744 | J808: =YEAR(C808) -> 2022 | K808: =IF(B808=B807,K807+1,1) -> 9 | L808: =K808^2 -> 81 | M808: =LN(L808) -> 4.3944492 | N808: =IF(K808<127,1,0) -> 1 | O808: =MONTH(C808) -> 2 | P808: =IF($O808=P$13,1,0) -> 0 | Q808: =IF($O808=Q$13,1,0) -> 1 | R808: =IF($O808=R$13,1,0) -> 0 | S808: =IF($O808=S$13,1,0) -> 0 | T808: =IF($O808=T$13,1,0) -> 0 | U808: =IF($O808=U$13,1,0) -> 0 | V808: =IF($O808=V$13,1,0) -> 0 | W808: =IF($O808=W$13,1,0) -> 0 | ... AA808: =IF($O808=AA$13,1,0) -> 0 | AB808: =IF($B808=AB$13,1,0) -> 0 | AC808: =IF($B808=AC$13,1,0) -> 1 | AD808: =IF($B808=AD$13,1,0) -> 0 | AE808: =IF($B808=AE$13,1,0) -> 0 | AF808: =IF($B808=AF$13,1,0) -> 0 | AG808: 1081.7345 | AH808: 225.67615 | AI808: 117.57435 | AJ808: 50.0894 | AK808: =LN(H808) -> 11.194378 | AL808: =LN(D808+'Models training data'!$Y$4) -> 7.2247106 | AM808: =LN(E808+'Models training data'!$Y$5) -> 5.6722513 | AN808: =LN(F808+'Models training data'!$Y$6) -> 5.0934608 | AO808: =LN(G808+'Models training data'!$Y$7) -> 4.6020938 | AP808: =V808+W808+X808+Y808+Z808 -> 0 | AQ808: =AA808+AC808+AD808+AE808+AF808 -> 1 | AR808: =$C$1+SUMPRODUCT($K$1:$AQ$1,K808:AQ808) -> 85147.265 | AS808: =$C$2+SUMPRODUCT($K$2:$AQ$2,K808:AQ808) -> 68773.268 | AT808: =$C$3+SUMPRODUCT($K$3:$AQ$3,K808:AQ808) -> 11.147508 | AU808: =$C$4+SUMPRODUCT($K$4:$AQ$4,K808:AQ808) -> 69447.828 | AV808: =$C$5+SUMPRODUCT($K$5:$AQ$5,K808:AQ808) -> 11.157322 | AW808: =$C$6+SUMPRODUCT($K$6:$AQ$6,K808:AQ808) -> 69587.654 | AX808: =$C$7+SUMPRODUCT($K$7:$AQ$7,K808:AQ808) -> 11.157881 | AY808: =$C$8+SUMPRODUCT($K$8:$AQ$8,K808:AQ808) -> 11.240783 | AZ808: =$C$9+SUMPRODUCT($K$9:$AQ$9,K808:AQ808) -> 11.191805
B809: =B808 -> MD | C809: 44625 | D809: 1134.1869 | E809: 236.94433 | F809: 123.45307 | G809: 85.155365 | H809: 76409.525 | I809: =SUM(D809:G809) -> 1579.7397 | J809: =YEAR(C809) -> 2022 | K809: =IF(B809=B808,K808+1,1) -> 10 | L809: =K809^2 -> 100 | M809: =LN(L809) -> 4.6051702 | N809: =IF(K809<127,1,0) -> 1 | O809: =MONTH(C809) -> 3 | P809: =IF($O809=P$13,1,0) -> 0 | Q809: =IF($O809=Q$13,1,0) -> 0 | R809: =IF($O809=R$13,1,0) -> 1 | S809: =IF($O809=S$13,1,0) -> 0 | T809: =IF($O809=T$13,1,0) -> 0 | U809: =IF($O809=U$13,1,0) -> 0 | V809: =IF($O809=V$13,1,0) -> 0 | W809: =IF($O809=W$13,1,0) -> 0 | ... AA809: =IF($O809=AA$13,1,0) -> 0 | AB809: =IF($B809=AB$13,1,0) -> 0 | AC809: =IF($B809=AC$13,1,0) -> 1 | AD809: =IF($B809=AD$13,1,0) -> 0 | AE809: =IF($B809=AE$13,1,0) -> 0 | AF809: =IF($B809=AF$13,1,0) -> 0 | AG809: 1134.1869 | AH809: 236.94433 | AI809: 123.45307 | AJ809: 85.155365 | AK809: =LN(H809) -> 11.243863 | AL809: =LN(D809+'Models training data'!$Y$4) -> 7.2622033 | AM809: =LN(E809+'Models training data'!$Y$5) -> 5.7102827 | AN809: =LN(F809+'Models training data'!$Y$6) -> 5.1289015 | AO809: =LN(G809+'Models training data'!$Y$7) -> 4.9034865 | AP809: =V809+W809+X809+Y809+Z809 -> 0 | AQ809: =AA809+AC809+AD809+AE809+AF809 -> 1 | AR809: =$C$1+SUMPRODUCT($K$1:$AQ$1,K809:AQ809) -> 84207.664 | AS809: =$C$2+SUMPRODUCT($K$2:$AQ$2,K809:AQ809) -> 67831.56 | AT809: =$C$3+SUMPRODUCT($K$3:$AQ$3,K809:AQ809) -> 11.136443 | AU809: =$C$4+SUMPRODUCT($K$4:$AQ$4,K809:AQ809) -> 68398.542 | AV809: =$C$5+SUMPRODUCT($K$5:$AQ$5,K809:AQ809) -> 11.144727 | AW809: =$C$6+SUMPRODUCT($K$6:$AQ$6,K809:AQ809) -> 68688.243 | AX809: =$C$7+SUMPRODUCT($K$7:$AQ$7,K809:AQ809) -> 11.147445 | AY809: =$C$8+SUMPRODUCT($K$8:$AQ$8,K809:AQ809) -> 11.249284 | AZ809: =$C$9+SUMPRODUCT($K$9:$AQ$9,K809:AQ809) -> 11.23456
B810: =B809 -> MD | C810: 44632 | D810: 1189.7522 | E810: 248.78374 | F810: 129.62572 | G810: 79.395398 | H810: 76668.951 | I810: =SUM(D810:G810) -> 1647.5571 | J810: =YEAR(C810) -> 2022 | K810: =IF(B810=B809,K809+1,1) -> 11 | L810: =K810^2 -> 121 | M810: =LN(L810) -> 4.7957905 | N810: =IF(K810<127,1,0) -> 1 | O810: =MONTH(C810) -> 3 | P810: =IF($O810=P$13,1,0) -> 0 | Q810: =IF($O810=Q$13,1,0) -> 0 | R810: =IF($O810=R$13,1,0) -> 1 | S810: =IF($O810=S$13,1,0) -> 0 | T810: =IF($O810=T$13,1,0) -> 0 | U810: =IF($O810=U$13,1,0) -> 0 | V810: =IF($O810=V$13,1,0) -> 0 | W810: =IF($O810=W$13,1,0) -> 0 | ... AA810: =IF($O810=AA$13,1,0) -> 0 | AB810: =IF($B810=AB$13,1,0) -> 0 | AC810: =IF($B810=AC$13,1,0) -> 1 | AD810: =IF($B810=AD$13,1,0) -> 0 | AE810: =IF($B810=AE$13,1,0) -> 0 | AF810: =IF($B810=AF$13,1,0) -> 0 | AG810: 1189.7522 | AH810: 248.78374 | AI810: 129.62572 | AJ810: 79.395398 | AK810: =LN(H810) -> 11.247252 | AL810: =LN(D810+'Models training data'!$Y$4) -> 7.3004451 | AM810: =LN(E810+'Models training data'!$Y$5) -> 5.7487425 | AN810: =LN(F810+'Models training data'!$Y$6) -> 5.16481 | AO810: =LN(G810+'Models training data'!$Y$7) -> 4.8598033 | AP810: =V810+W810+X810+Y810+Z810 -> 0 | AQ810: =AA810+AC810+AD810+AE810+AF810 -> 1 | AR810: =$C$1+SUMPRODUCT($K$1:$AQ$1,K810:AQ810) -> 84183.274 | AS810: =$C$2+SUMPRODUCT($K$2:$AQ$2,K810:AQ810) -> 67807.463 | AT810: =$C$3+SUMPRODUCT($K$3:$AQ$3,K810:AQ810) -> 11.136185 | AU810: =$C$4+SUMPRODUCT($K$4:$AQ$4,K810:AQ810) -> 68312.041 | AV810: =$C$5+SUMPRODUCT($K$5:$AQ$5,K810:AQ810) -> 11.14357 | AW810: =$C$6+SUMPRODUCT($K$6:$AQ$6,K810:AQ810) -> 68550.339 | AX810: =$C$7+SUMPRODUCT($K$7:$AQ$7,K810:AQ810) -> 11.145858 | AY810: =$C$8+SUMPRODUCT($K$8:$AQ$8,K810:AQ810) -> 11.251435 | AZ810: =$C$9+SUMPRODUCT($K$9:$AQ$9,K810:AQ810) -> 11.234484
B811: =B810 -> MD | C811: 44639 | D811: 1248.439 | E811: 261.21902 | F811: 136.10701 | G811: 83.659894 | H811: 77628.007 | I811: =SUM(D811:G811) -> 1729.4249 | J811: =YEAR(C811) -> 2022 | K811: =IF(B811=B810,K810+1,1) -> 12 | L811: =K811^2 -> 144 | M811: =LN(L811) -> 4.9698133 | N811: =IF(K811<127,1,0) -> 1 | O811: =MONTH(C811) -> 3 | P811: =IF($O811=P$13,1,0) -> 0 | Q811: =IF($O811=Q$13,1,0) -> 0 | R811: =IF($O811=R$13,1,0) -> 1 | S811: =IF($O811=S$13,1,0) -> 0 | T811: =IF($O811=T$13,1,0) -> 0 | U811: =IF($O811=U$13,1,0) -> 0 | V811: =IF($O811=V$13,1,0) -> 0 | W811: =IF($O811=W$13,1,0) -> 0 | ... AA811: =IF($O811=AA$13,1,0) -> 0 | AB811: =IF($B811=AB$13,1,0) -> 0 | AC811: =IF($B811=AC$13,1,0) -> 1 | AD811: =IF($B811=AD$13,1,0) -> 0 | AE811: =IF($B811=AE$13,1,0) -> 0 | AF811: =IF($B811=AF$13,1,0) -> 0 | AG811: 1248.439 | AH811: 261.21902 | AI811: 136.10701 | AJ811: 83.659894 | AK811: =LN(H811) -> 11.259684 | AL811: =LN(D811+'Models training data'!$Y$4) -> 7.3393076 | AM811: =LN(E811+'Models training data'!$Y$5) -> 5.787606 | AN811: =LN(F811+'Models training data'!$Y$6) -> 5.2011757 | AO811: =LN(G811+'Models training data'!$Y$7) -> 4.8923271 | AP811: =V811+W811+X811+Y811+Z811 -> 0 | AQ811: =AA811+AC811+AD811+AE811+AF811 -> 1 | AR811: =$C$1+SUMPRODUCT($K$1:$AQ$1,K811:AQ811) -> 84158.884 | AS811: =$C$2+SUMPRODUCT($K$2:$AQ$2,K811:AQ811) -> 67783.366 | AT811: =$C$3+SUMPRODUCT($K$3:$AQ$3,K811:AQ811) -> 11.135928 | AU811: =$C$4+SUMPRODUCT($K$4:$AQ$4,K811:AQ811) -> 68226.718 | AV811: =$C$5+SUMPRODUCT($K$5:$AQ$5,K811:AQ811) -> 11.14243 | AW811: =$C$6+SUMPRODUCT($K$6:$AQ$6,K811:AQ811) -> 68424.441 | AX811: =$C$7+SUMPRODUCT($K$7:$AQ$7,K811:AQ811) -> 11.144409 | AY811: =$C$8+SUMPRODUCT($K$8:$AQ$8,K811:AQ811) -> 11.25535 | AZ811: =$C$9+SUMPRODUCT($K$9:$AQ$9,K811:AQ811) -> 11.243945
B812: =B811 -> MD | C812: 44646 | D812: 1310.3004 | E812: 274.27801 | F812: 142.91236 | G812: 78.926468 | H812: 77956.109 | I812: =SUM(D812:G812) -> 1806.4172 | J812: =YEAR(C812) -> 2022 | K812: =IF(B812=B811,K811+1,1) -> 13 | L812: =K812^2 -> 169 | M812: =LN(L812) -> 5.1298987 | N812: =IF(K812<127,1,0) -> 1 | O812: =MONTH(C812) -> 3 | P812: =IF($O812=P$13,1,0) -> 0 | Q812: =IF($O812=Q$13,1,0) -> 0 | R812: =IF($O812=R$13,1,0) -> 1 | S812: =IF($O812=S$13,1,0) -> 0 | T812: =IF($O812=T$13,1,0) -> 0 | U812: =IF($O812=U$13,1,0) -> 0 | V812: =IF($O812=V$13,1,0) -> 0 | W812: =IF($O812=W$13,1,0) -> 0 | ... AA812: =IF($O812=AA$13,1,0) -> 0 | AB812: =IF($B812=AB$13,1,0) -> 0 | AC812: =IF($B812=AC$13,1,0) -> 1 | AD812: =IF($B812=AD$13,1,0) -> 0 | AE812: =IF($B812=AE$13,1,0) -> 0 | AF812: =IF($B812=AF$13,1,0) -> 0 | AG812: 1310.3004 | AH812: 274.27801 | AI812: 142.91236 | AJ812: 78.926468 | AK812: =LN(H812) -> 11.263901 | AL812: =LN(D812+'Models training data'!$Y$4) -> 7.3787004 | AM812: =LN(E812+'Models training data'!$Y$5) -> 5.8268555 | AN812: =LN(F812+'Models training data'!$Y$6) -> 5.2379878 | AO812: =LN(G812+'Models training data'!$Y$7) -> 4.8561616 | AP812: =V812+W812+X812+Y812+Z812 -> 0 | AQ812: =AA812+AC812+AD812+AE812+AF812 -> 1 | AR812: =$C$1+SUMPRODUCT($K$1:$AQ$1,K812:AQ812) -> 84134.493 | AS812: =$C$2+SUMPRODUCT($K$2:$AQ$2,K812:AQ812) -> 67759.268 | AT812: =$C$3+SUMPRODUCT($K$3:$AQ$3,K812:AQ812) -> 11.13567 | AU812: =$C$4+SUMPRODUCT($K$4:$AQ$4,K812:AQ812) -> 68142.574 | AV812: =$C$5+SUMPRODUCT($K$5:$AQ$5,K812:AQ812) -> 11.141306 | AW812: =$C$6+SUMPRODUCT($K$6:$AQ$6,K812:AQ812) -> 68308.627 | AX812: =$C$7+SUMPRODUCT($K$7:$AQ$7,K812:AQ812) -> 11.143075 | AY812: =$C$8+SUMPRODUCT($K$8:$AQ$8,K812:AQ812) -> 11.258002 | AZ812: =$C$9+SUMPRODUCT($K$9:$AQ$9,K812:AQ812) -> 11.244927
... B956: =B955 -> MD | C956: 45654 | D956: 502.75199 | E956: 100.95139 | F956: 50.748633 | G956: 50 | H956: 65053.707 | I956: =SUM(D956:G956) -> 704.45201 | J956: =YEAR(C956) -> 2024 | K956: =IF(B956=B955,K955+1,1) -> 157 | L956: =K956^2 -> 24649 | M956: =LN(L956) -> 10.112492 | N956: =IF(K956<127,1,0) -> 0 | O956: =MONTH(C956) -> 12 | P956: =IF($O956=P$13,1,0) -> 0 | Q956: =IF($O956=Q$13,1,0) -> 0 | R956: =IF($O956=R$13,1,0) -> 0 | S956: =IF($O956=S$13,1,0) -> 0 | T956: =IF($O956=T$13,1,0) -> 0 | U956: =IF($O956=U$13,1,0) -> 0 | V956: =IF($O956=V$13,1,0) -> 0 | W956: =IF($O956=W$13,1,0) -> 0 | ... AA956: =IF($O956=AA$13,1,0) -> 1 | AB956: =IF($B956=AB$13,1,0) -> 0 | AC956: =IF($B956=AC$13,1,0) -> 1 | AD956: =IF($B956=AD$13,1,0) -> 0 | AE956: =IF($B956=AE$13,1,0) -> 0 | AF956: =IF($B956=AF$13,1,0) -> 0 | AG956: 502.75199 | AH956: 100.95139 | AI956: 50.748633 | AJ956: 50 | AK956: =LN(H956) -> 11.082968 | AL956: =LN(D956+'Models training data'!$Y$4) -> 6.6770315 | AM956: =LN(E956+'Models training data'!$Y$5) -> 5.1117677 | AN956: =LN(F956+'Models training data'!$Y$6) -> 4.5656715 | AO956: =LN(G956+'Models training data'!$Y$7) -> 4.6011966 | AP956: =V956+W956+X956+Y956+Z956 -> 0 | AQ956: =AA956+AC956+AD956+AE956+AF956 -> 2 | AR956: =$C$1+SUMPRODUCT($K$1:$AQ$1,K956:AQ956) -> 81456.478 | AS956: =$C$2+SUMPRODUCT($K$2:$AQ$2,K956:AQ956) -> 65120.707 | AT956: =$C$3+SUMPRODUCT($K$3:$AQ$3,K956:AQ956) -> 11.106999 | AU956: =$C$4+SUMPRODUCT($K$4:$AQ$4,K956:AQ956) -> 69771.326 | AV956: =$C$5+SUMPRODUCT($K$5:$AQ$5,K956:AQ956) -> 11.173674 | AW956: =$C$6+SUMPRODUCT($K$6:$AQ$6,K956:AQ956) -> 65929.739 | AX956: =$C$7+SUMPRODUCT($K$7:$AQ$7,K956:AQ956) -> 11.11473 | AY956: =$C$8+SUMPRODUCT($K$8:$AQ$8,K956:AQ956) -> 11.108976 | AZ956: =$C$9+SUMPRODUCT($K$9:$AQ$9,K956:AQ956) -> 11.121773

Sheet EDA
A1: SPEND | AJ1: 2024 SPEND | AR1: SALES
AL26: 2024 Spend
AL27: Facebook_spend | AM27: =GETPIVOTDATA("Sum of Facebook_spend_",$AL$59) -> 40517.032
AL28: CT | AM28: 4802.1835
AL29: DL | AM29: 3979.9587
AL30: MD | AM30: 3998.8607
K31: WEEKLY AND MONTHLY SPENDING BY STATE | T31: SPEND TREND | W31: TRENDS | AL31: NJ | AM31: 5662.4037
K32: Year | L32: Months (Date) | M32: Date | N32: Sum of Facebook_spend_ | O32: Sum of YouTube_spend | P32: Sum of Radio_Spend | Q32: Sum of TV_Spend | R32: Sum of Total Spend | T32: Row Labels | U32: Sum of Total Spend | W32: Row Labels | X32: Sum of Facebook_spend_ | Y32: Sum of YouTube_spend | Z32: Sum of Radio_Spend | AA32: Sum of TV_Spend | AL32: NY | AM32: 11979.424
A33: SPEND BY STATE | D33: SALE BY STATE | G33: SPEND BY TACTIC | K33: 2022 | L33: Jan | M33: 44562 | N33: 691.11267 | O33: 1040 | P33: 2080 | Q33: 10530 | R33: 14341.113 | T33: 44562 | U33: 14341.113 | W33: 2022 | X33: 87576.028 | Y33: 61941.871 | Z33: 123026.79 | AA33: 463736.31 | AL33: PA | AM33: 10094.201
A34: CT | B34: =GETPIVOTDATA("Sum of Total Spend",$A$57,"State","CT") -> 220183.98 | D34: CT | E34: =GETPIVOTDATA("sales",$H$57,"State","CT") -> 12670347 | G34: Facebook Spend | H34: =GETPIVOTDATA("Sum of Facebook_spend_",$A$67) -> 217712.03 | M34: 44569 | N34: 740.30074 | O34: 1086.8 | P34: 2132 | Q34: 10687.95 | R34: 14647.051 | T34: 44569 | U34: 14647.051 | W34: Qtr1 | X34: 10494.321 | Y34: 15932.856 | Z34: 31166.327 | AA34: 154001.44 | AL34: Youtube_spend | AM34: =GETPIVOTDATA("Sum of YouTube_spend",$AL$59) -> 51779.111
A35: DL | B35: =GETPIVOTDATA("Sum of Total Spend",$A$57,"State","DL") -> 122619.37 | D35: DL | E35: =GETPIVOTDATA("sales",$H$57,"State","DL") -> 11459150 | G35: Youtube Spend | H35: =GETPIVOTDATA("Sum of YouTube_spend",$A$67) -> 209563.46 | M35: 44576 | N35: 785.35746 | O35: 1140.62 | P35: 2212.6 | Q35: 10964.363 | R35: 15102.94 | T35: 44576 | U35: 15102.94 | W35: Qtr2 | X35: 24064.879 | Y35: 14800.093 | Z35: 35842.681 | AA35: 116251.16 | AL35: CT | AM35: 3985.4996
A36: MD | B36: =GETPIVOTDATA("Sum of Total Spend",$A$57,"State","MD") -> 150296.68 | D36: MD | E36: =GETPIVOTDATA("sales",$H$57,"State","MD") -> 11624136 | G36: Radio Spend | H36: =GETPIVOTDATA("Sum of Radio_Spend",$A$67) -> 301546.63 | M36: 44583 | N36: 792.62122 | O36: 1197.599 | P36: 2310.23 | Q36: 11331.991 | R36: 15632.441 | T36: 44583 | U36: 15632.441 | W36: Qtr3 | X36: 43285.412 | Y36: 18454.162 | Z36: 33051.466 | AA36: 88508.652 | AL36: DL | AM36: 2698.5746
A37: NJ | B37: =GETPIVOTDATA("Sum of Total Spend",$A$57,"State","NJ") -> 405770.08 | D37: NJ | E37: =GETPIVOTDATA("sales",$H$57,"State","NJ") -> 15572136 | G37: TV Spend | H37: =GETPIVOTDATA("Sum of TV_Spend",$A$67) -> 1305423.2 | M37: 44590 | N37: 812.9557 | O37: 1257.4738 | P37: 2419.2415 | Q37: 11772.178 | R37: 16261.849 | T37: 44590 | U37: 16261.849 | W37: Qtr4 | X37: 9731.4165 | Y37: 12754.759 | Z37: 22966.316 | AA37: 104975.05 | AL37: MD | AM37: 2817.6357
A38: NY | B38: =GETPIVOTDATA("Sum of Total Spend",$A$57,"State","NY") -> 785244.34 | D38: NY | E38: =GETPIVOTDATA("sales",$H$57,"State","NY") -> 18071603 | L38: Feb | M38: 44597 | N38: 703.60893 | O38: 1090.6162 | P38: 2281.6973 | Q38: 11496.957 | R38: 15572.879 | T38: 44597 | U38: 15572.879 | W38: 2023 | X38: 89618.967 | Y38: 95842.476 | Z38: 86572.82 | AA38: 517819.77 | AL38: NJ | AM38: 7071.8417
A39: PA | B39: =GETPIVOTDATA("Sum of Total Spend",$A$57,"State","PA") -> 350130.92 | D39: PA | E39: =GETPIVOTDATA("sales",$H$57,"State","PA") -> 16224597 | M39: 44604 | N39: 714.52554 | O39: 1122.1739 | P39: 2266.529 | Q39: 11467.124 | R39: 15570.352 | T39: 44604 | U39: 15570.352 | W39: Qtr1 | X39: 7270.3597 | Y39: 10383.417 | Z39: 20913.636 | AA39: 102654.6 | AL39: NY | AM39: 15215.952
M40: 44611 | N40: 767.84991 | O40: 1175.9853 | P40: 2315.2288 | Q40: 11617.203 | R40: 15876.268 | T40: 44611 | U40: 15876.268 | W40: Qtr2 | X40: 12034.818 | Y40: 8237.1868 | Z40: 19213.956 | AA40: 127677.24 | AL40: PA | AM40: 19989.607
M41: 44618 | N41: 813.24902 | O41: 1234.5548 | P41: 2398.677 | Q41: 11901.77 | R41: 16348.251 | T41: 44618 | U41: 16348.251 | W41: Qtr3 | X41: 51727.882 | Y41: 64886.87 | Z41: 20405.77 | AA41: 156391.72 | AL41: Radio_Spend | AM41: 91947.022
C42: SPEND BY YEAR | L42: Mar | M42: 44625 | N42: 855.50455 | O42: 1296.2596 | P42: 2502.4542 | Q42: 12289.453 | R42: 16943.671 | T42: 44625 | U42: 16943.671 | W42: Qtr4 | X42: 18585.908 | Y42: 12335.002 | Z42: 26039.459 | AA42: 131096.2 | AL42: CT | AM42: 7584.0068
C43: 2022 | D43: 736281 | E43: 2023 | F43: 789854.03 | G43: 2024 | H43: 508110.34 | M43: 44632 | N43: 867.81811 | O43: 1361.0703 | P43: 2619.4986 | Q43: 12758.742 | R43: 17607.129 | T43: 44632 | U43: 17607.129 | W43: 2024 | X43: 40517.032 | Y43: 51779.111 | Z43: 91947.022 | AA43: 323867.17 | AL43: DL | AM43: 5426.5782
C44: CT | D44: 77533.752 | E44: CT | F44: 90732.232 | G44: CT | H44: 51917.999 | M44: 44639 | N44: 937.59238 | O44: 1429.1236 | P44: 2746.4344 | Q44: 13295.05 | R44: 18408.2 | T44: 44639 | U44: 18408.2 | W44: Qtr1 | X44: 6301.3488 | Y44: 8705.6583 | Z44: 22397.345 | AA44: 91964.764 | AL44: MD | AM44: 5703.3547
C45: DL | D45: 41734.982 | E45: DL | F45: 46956.698 | G45: DL | H45: 33927.686 | M45: 44646 | N45: 1011.8249 | O45: 1500.5797 | P45: 2881.7365 | Q45: 13888.662 | R45: 19282.804 | T45: 44646 | U45: 19282.804 | W45: Qtr2 | X45: 8581.9767 | Y45: 15321.625 | Z45: 29227.157 | AA45: 55679.958 | AL45: NJ | AM45: 34517.117
C46: MD | D46: 52045.182 | E46: MD | F46: 60395.366 | G46: MD | H46: 37856.131 | L46: Apr | M46: 44653 | N46: 1016.9771 | O46: 1521.302 | P46: 2964.4728 | Q46: 14350.012 | R46: 19852.764 | T46: 44653 | U46: 19852.764 | W46: Qtr3 | X46: 17006.896 | Y46: 17899.075 | Z46: 20767.951 | AA46: 80540.002 | AL46: NY | AM46: 27694.463
C47: NJ | D47: 174514.27 | E47: NJ | F47: 127938.03 | G47: NJ | H47: 103317.78 | M47: 44660 | N47: 1081.3361 | O47: 1517.4975 | P47: 2999.3111 | Q47: 14719.237 | R47: 20317.382 | T47: 44660 | U47: 20317.382 | W47: Qtr4 | X47: 8626.8103 | Y47: 9852.7523 | Z47: 19554.569 | AA47: 95682.448 | AL47: PA | AM47: 11021.502 | AT47: Sales by Month | AW47: Total Sales Trend
C48: NY | D48: 264244.98 | E48: NY | F48: 331923.7 | G48: NY | H48: 189075.66 | M48: 44667 | N48: 1185.7359 | O48: 911.08417 | P48: 2343.3605 | Q48: 12074.022 | R48: 16514.202 | T48: 44667 | U48: 16514.202 | W48: Grand Total | X48: 217712.03 | Y48: 209563.46 | Z48: 301546.63 | AA48: 1305423.2 | AL48: TV_Spend | AM48: 323867.17 | AT48: Jan | AU48: 6642876.1 | AW48: 2022 | AX48: Quarter 1 | AY48: 6939377.9
C49: PA | D49: 126207.84 | E49: PA | F49: 131908 | G49: PA | H49: 92015.077 | M49: 44674 | N49: 1303.9361 | O49: 857.13619 | P49: 2003.1786 | Q49: 10238.855 | R49: 14403.105 | T49: 44674 | U49: 14403.105 | AL49: CT | AM49: 35546.309 | AT49: Feb | AU49: 6041919.9 | AX49: Quarter 2 | AY49: 7426306.4
M50: 44681 | N50: 1434.2924 | O50: 858.50166 | P50: 1821.7412 | Q50: 8970.9831 | R50: 13085.518 | T50: 44681 | U50: 13085.518 | AL50: DL | AM50: 21822.575 | AT50: Mar | AU50: 6458441.4 | AX50: Quarter 3 | AY50: 7890941.7
L51: May | M51: 44688 | N51: 1577.7179 | O51: 865.46609 | P51: 2015.9684 | Q51: 8100.3859 | R51: 12559.538 | T51: 44688 | U51: 12559.538 | AL51: MD | AM51: 25336.28 | AT51: Apr | AU51: 6930992.7 | AX51: Quarter 4 | AY51: 6851919.6
M52: 44695 | N52: 1735.4893 | O52: 1190.9013 | P52: 2664.7344 | Q52: 7508.0498 | R52: 13099.175 | T52: 44695 | U52: 13099.175 | AL52: NJ | AM52: 56066.417 | AT52: May | AU52: 6563504.7 | AW52: 2023 | AX52: Quarter 1 | AY52: 5896539.7
M53: 44702 | N53: 1909.0382 | O53: 1249.4213 | P53: 2965.3612 | Q53: 7110.6673 | R53: 13234.488 | T53: 44702 | U53: 13234.488 | AL53: NY | AM53: 134185.82 | AT53: Jun | AU53: 7724624.6 | AX53: Quarter 2 | AY53: 6901525.6
M54: 44709 | N54: 2099.942 | O54: 1282.3011 | P54: 3092.6639 | Q54: 6849.9249 | R54: 13324.832 | T54: 44709 | U54: 13324.832 | AL54: PA | AM54: 50909.768 | AT54: Jul | AU54: 8964088.1 | AX54: Quarter 3 | AY54: 9457770.3
L55: Jun | M55: 44716 | N55: 2309.9362 | O55: 1296.2626 | P55: 3171.4151 | Q55: 6685.0048 | R55: 13462.619 | T55: 44716 | U55: 13462.619 | AT55: Aug | AU55: 8296491.6 | AX55: Quarter 4 | AY55: 6995243.1
A56: Spend by State | H56: Sale by State | M56: 44723 | N56: 2540.9298 | O56: 1308.4391 | P56: 3226.0415 | Q56: 6587.3363 | R56: 13662.747 | T56: 44723 | U56: 13662.747 | AT56: Sep | AU56: 7718502.4 | AW56: 2024 | AX56: Quarter 1 | AY56: 6307319.8
A57: Row Labels | B57: Sum of Total Spend | C57: Sum of Facebook_spend_ | D57: Sum of YouTube_spend | E57: Sum of Radio_Spend | F57: Sum of TV_Spend | H57: Row Labels | I57: Sum of sales | M57: 44730 | N57: 2795.0228 | O57: 983.33273 | P57: 3268.7581 | Q57: 6536.9217 | R57: 13584.035 | T57: 44730 | U57: 13584.035 | AL57: Year | AM57: 2024 | AT57: Oct | AU57: 6751586.9 | AX57: Quarter 2 | AY57: 6891290
A58: CT | B58: 220183.98 | C58: 26672.641 | D58: 22104.77 | E58: 28765.791 | F58: 142640.78 | H58: CT | I58: 12670347 | M58: 44737 | N58: 3074.5251 | O58: 958.44698 | P58: 3305.6737 | Q58: 6519.7644 | R58: 13858.41 | T58: 44737 | U58: 13858.41 | AT58: Nov | AU58: 6550558.9 | AX58: Quarter 3 | AY58: 7630370.2
A59: DL | B59: 122619.37 | C59: 15798.776 | D59: 12491.542 | E59: 17484.136 | F59: 76844.912 | H59: DL | I59: 11459150 | L59: Jul | M59: 44744 | N59: 3381.9776 | O59: 963.65954 | P59: 3339.8445 | Q59: 6526.0684 | R59: 14211.55 | T59: 44744 | U59: 14211.55 | AL59: Sum of Facebook_spend_ | AM59: Sum of YouTube_spend | AN59: Sum of Radio_Spend | AO59: Sum of TV_Spend | AT59: Dec | AU59: 6978381.3 | AX59: Quarter 4 | AY59: 6433364.3
A60: MD | B60: 150296.68 | C60: 18203.396 | D60: 15110.041 | E60: 20250.327 | F60: 96732.915 | H60: MD | I60: 11624136 | M60: 44751 | N60: 3720.1753 | O60: 971.95895 | P60: 3372.8 | Q60: 6548.9785 | R60: 14613.913 | T60: 44751 | U60: 14613.913 | AL60: 40517.032 | AM60: 51779.111 | AN60: 91947.022 | AO60: 323867.17
A61: NJ | B61: 405770.08 | C61: 40667.245 | D61: 29992.741 | E61: 100552.89 | F61: 234557.2 | H61: NJ | I61: 15572136 | M61: 44758 | N61: 4092.1929 | O61: 1457.4088 | P61: 3223.9036 | Q61: 6583.698 | R61: 15357.203 | T61: 44758 | U61: 15357.203
A62: NY | B62: 785244.34 | C62: 75831.973 | D62: 74617.091 | E62: 91699.312 | F62: 543095.96 | H62: NY | I62: 18071603 | M62: 44765 | N62: 4501.4121 | O62: 1542.4052 | P62: 3009.6381 | Q62: 6626.8707 | R62: 15680.326 | T62: 44765 | U62: 15680.326
A63: PA | B63: 350130.92 | C63: 40537.997 | D63: 55247.273 | E63: 42794.178 | F63: 211551.48 | H63: PA | I63: 16224597 | M63: 44772 | N63: 4951.5534 | O63: 1588.9082 | P63: 2784.4187 | Q63: 6676.1494 | R63: 16001.03 | T63: 44772 | U63: 16001.03
A64: Grand Total | B64: 2034245.4 | C64: 217712.03 | D64: 209563.46 | E64: 301546.63 | F64: 1305423.2 | H64: Grand Total | I64: 85621969 | L64: Aug | M64: 44779 | N64: 3462.8248 | O64: 1607.0052 | P64: 2572.2009 | Q64: 6729.8929 | R64: 14371.924 | T64: 44779 | U64: 14371.924
M65: 44786 | N65: 3321.3791 | O65: 1622.396 | P65: 2382.1986 | Q65: 6786.9543 | R65: 14112.928 | T65: 44786 | U65: 14112.928
A66: Spend By Tactic | M66: 44793 | N66: 3548.6314 | O66: 1131.8338 | P66: 2216.669 | Q66: 6846.5325 | R66: 13743.667 | T66: 44793 | U66: 13743.667
A67: Sum of Total Spend | B67: Sum of Facebook_spend_ | C67: Sum of YouTube_spend | D67: Sum of Radio_Spend | E67: Sum of TV_Spend | M67: 44800 | N67: 3895.1161 | O67: 1179.6976 | P67: 2172.6595 | Q67: 6908.0689 | R67: 14155.542 | T67: 44800 | U67: 14155.542
A68: 2034245.4 | B68: 217712.03 | C68: 209563.46 | D68: 301546.63 | E68: 1305423.2 | L68: Sep | M68: 44807 | N68: 4226.3894 | O68: 1194.2491 | P68: 2102.1444 | Q68: 6971.1743 | R68: 14493.957 | T68: 44807 | U68: 14493.957 | AR68: WEEKLY TREND | AU68: SALES BY MONTH | AX68: TOTAL SALES TREND
M69: 44814 | N69: 1219.7721 | O69: 1205.5671 | P69: 2026.6144 | Q69: 7035.5784 | R69: 11487.532 | T69: 44814 | U69: 11487.532 | AR69: Row Labels | AS69: Sum of sales | AU69: Row Labels | AV69: Sum of sales | AX69: Row Labels | AY69: Sum of sales
M70: 44821 | N70: 1454.0724 | O70: 1931.8062 | P70: 1955.5889 | Q70: 7101.0938 | R70: 12442.561 | T70: 44821 | U70: 12442.561 | AR70: 2022 | AU70: Jan | AV70: 6642876.1 | AX70: 2022 | AY70: 29108546
A71: Spend By Year | M71: 44828 | N71: 1509.9154 | O71: 2057.2666 | P71: 1892.7854 | Q71: 7167.5915 | R71: 12627.559 | T71: 44828 | U71: 12627.559 | AR71: Jan | AU71: Feb | AV71: 6041919.9 | AX71: Qtr1 | AY71: 6939377.9
A72: Row Labels | B72: Sum of Facebook_spend_ | C72: Sum of YouTube_spend | D72: Sum of Radio_Spend | E72: Sum of TV_Spend | L72: Oct | M72: 44835 | N72: 1543.9902 | O72: 2124.9586 | P72: 1839.177 | Q72: 6363.2757 | R72: 11871.401 | T72: 44835 | U72: 11871.401 | AR72: 44562 | AS72: 512388.91 | AU72: Mar | AV72: 6458441.4 | AX72: Qtr2 | AY72: 7426306.4
A73: 2024 | B73: 40517.032 | C73: 51779.111 | D73: 91947.022 | E73: 323867.17 | M73: 44842 | N73: 814.5263 | O73: 900.45374 | P73: 1683.9862 | Q73: 6693.0138 | R73: 10091.98 | T73: 44842 | U73: 10091.98 | AR73: 44569 | AS73: 516931.53 | AU73: Apr | AV73: 6930992.7 | AX73: Qtr3 | AY73: 7890941.7
A74: Grand Total | B74: 40517.032 | C74: 51779.111 | D74: 91947.022 | E74: 323867.17 | M74: 44849 | N74: 690.23996 | O74: 783.98284 | P74: 1613.0347 | Q74: 6945.0926 | R74: 10032.35 | T74: 44849 | U74: 10032.35 | AR74: 44576 | AS74: 521864.7 | AU74: May | AV74: 6563504.7 | AX74: Qtr4 | AY74: 6851919.6
A75: Row Labels | B75: Sum of Total Spend | C75: Sum of TV_Spend | D75: Sum of Radio_Spend | E75: Sum of YouTube_spend | F75: Sum of Facebook_spend_ | M75: 44856 | N75: 665.27151 | O75: 778.37512 | P75: 1584.2694 | Q75: 7143.0226 | R75: 10170.939 | T75: 44856 | U75: 10170.939 | AR75: 44583 | AS75: 526819.11 | AU75: Jun | AV75: 7724624.6 | AX75: 2023 | AY75: 29251079
A76: 2022 | B76: 736281 | C76: 463736.31 | D76: 123026.79 | E76: 61941.871 | F76: 87576.028 | M76: 44863 | N76: 653.02491 | O76: 783.91412 | P76: 1576.6643 | Q76: 7303.2632 | R76: 10316.867 | T76: 44863 | U76: 10316.867 | AR76: 44590 | AS76: 530025.29 | AU76: Jul | AV76: 8964088.1 | AX76: Qtr1 | AY76: 5896539.7
A77: CT | B77: 77533.752 | C77: 52759.987 | D77: 10308.75 | E77: 5118.2325 | F77: 9346.7826 | L77: Nov | M77: 44870 | N77: 650.07157 | O77: 790.62878 | P77: 1579.707 | Q77: 7437.3409 | R77: 10457.748 | T77: 44870 | U77: 10457.748 | AR77: Feb | AU77: Aug | AV77: 8296491.6 | AX77: Qtr2 | AY77: 6901525.6
A78: DL | B78: 41734.982 | C78: 27853.957 | D78: 6383.0501 | E78: 3182.6362 | F78: 4315.3384 | M78: 44877 | N78: 644.7818 | O78: 797.52262 | P78: 1588.1421 | Q78: 7554.4458 | R78: 10584.892 | T78: 44877 | U78: 10584.892 | AR78: 44597 | AS78: 524581.86 | AU78: Sep | AV78: 7718502.4 | AX78: Qtr3 | AY78: 9457770.3
A79: MD | B79: 52045.182 | C79: 35173.644 | D79: 7298.2735 | E79: 3625.0466 | F79: 5948.2173 | M79: 44884 | N79: 588.21374 | O79: 804.83549 | P79: 1599.7191 | Q79: 7659.9023 | R79: 10652.671 | T79: 44884 | U79: 10652.671 | AR79: 44604 | AS79: 528055.07 | AU79: Oct | AV79: 6751586.9 | AX79: Qtr4 | AY79: 6995243.1
A80: NJ | B80: 174514.27 | C80: 87933.311 | D80: 46101.86 | E80: 15304.737 | F80: 25174.358 | M80: 44891 | N80: 619.23396 | O80: 812.3676 | P80: 1613.064 | Q80: 7757.4397 | R80: 10802.105 | T80: 44891 | U80: 10802.105 | AR80: 44611 | AS80: 531836.31 | AU80: Nov | AV80: 6550558.9 | AX80: 2024 | AY80: 27262344
A81: NY | B81: 264244.98 | C81: 180875.43 | D81: 37471.733 | E81: 18732.945 | F81: 27164.868 | L81: Dec | M81: 44898 | N81: 602.62241 | O81: 819.98966 | P81: 1627.3686 | Q81: 7849.671 | R81: 10899.652 | T81: 44898 | U81: 10899.652 | AR81: 44618 | AS81: 537411.27 | AU81: Dec | AV81: 6978381.3 | AX81: Qtr1 | AY81: 6307319.8
A82: PA | B82: 126207.84 | C82: 79139.98 | D82: 15463.125 | E82: 15978.274 | F82: 15626.464 | M82: 44905 | N82: 578.13841 | O82: 827.68939 | P82: 1642.2292 | Q82: 7938.4276 | R82: 10986.485 | T82: 44905 | U82: 10986.485 | AR82: Mar | AU82: Grand Total | AV82: 85621969 | AX82: Qtr2 | AY82: 6891290
A83: 2023 | B83: 789854.03 | C83: 517819.77 | D83: 86572.82 | E83: 95842.476 | F83: 89618.967 | M83: 44912 | N83: 567.27178 | O83: 835.46627 | P83: 1657.445 | Q83: 8024.9937 | R83: 11085.177 | T83: 44912 | U83: 11085.177 | AR83: 44625 | AS83: 544881.73 | AX83: Qtr3 | AY83: 7630370.2
A84: CT | B84: 90732.232 | C84: 54334.485 | D84: 10873.034 | E84: 13001.037 | F84: 12523.674 | M84: 44919 | N84: 567.34559 | O84: 843.32093 | P84: 1672.9162 | Q84: 8110.271 | R84: 11193.854 | T84: 44919 | U84: 11193.854 | AR84: 44632 | AS84: 548316.8 | AX84: Qtr4 | AY84: 6433364.3
A85: DL | B85: 46956.698 | C85: 27168.381 | D85: 5674.5073 | E85: 6610.3316 | F85: 7503.4788 | M85: 44926 | N85: 546.68442 | O85: 851.25414 | P85: 1688.5937 | Q85: 8194.8928 | R85: 11281.425 | T85: 44926 | U85: 11281.425 | AR85: 44639 | AS85: 554439.01 | AX85: Grand Total | AY85: 85621969
A86: MD | B86: 60395.366 | C86: 36222.99 | D86: 7248.699 | E86: 8667.3583 | F86: 8256.3182 | K86: 2023 | L86: Jan | M86: 44933 | N86: 583.14967 | O86: 859.26668 | P86: 1704.4538 | Q86: 8279.3052 | R86: 11426.175 | T86: 44933 | U86: 11426.175 | AR86: 44646 | AS86: 561826.31
A87: NJ | B87: 127938.03 | C87: 90557.476 | D87: 19933.913 | E87: 7616.1622 | F87: 9830.4831 | M87: 44940 | N87: 565.99608 | O87: 867.35935 | P87: 1720.4854 | Q87: 8363.8226 | R87: 11517.663 | T87: 44940 | U87: 11517.663 | AR87: Apr
A88: NY | B88: 331923.7 | C88: 228034.71 | D88: 26533.116 | E88: 40668.194 | F88: 36687.681 | M88: 44947 | N88: 597.27975 | O88: 875.53294 | P88: 1736.6838 | Q88: 8448.6679 | R88: 11658.164 | T88: 44947 | U88: 11658.164 | AR88: 44653 | AS88: 564305.89
A89: PA | B89: 131908 | C89: 81501.728 | D89: 16309.551 | E89: 19279.392 | F89: 14817.332 | M89: 44954 | N89: 625.3262 | O89: 883.78827 | P89: 1753.0474 | Q89: 8533.9995 | R89: 11796.161 | T89: 44954 | U89: 11796.161 | AR89: 44660 | AS89: 565917.99
A90: 2024 | B90: 508110.34 | C90: 323867.17 | D90: 91947.022 | E90: 51779.111 | F90: 40517.032 | L90: Feb | M90: 44961 | N90: 603.18976 | O90: 892.12615 | P90: 1769.5763 | Q90: 8619.9309 | R90: 11884.823 | T90: 44961 | U90: 11884.823 | AR90: 44667 | AS90: 530877.45
A91: CT | B91: 51917.999 | C91: 35546.309 | D91: 7584.0068 | E91: 3985.4996 | F91: 4802.1835 | M91: 44968 | N91: 605.78662 | O91: 900.54741 | P91: 1786.2713 | Q91: 8706.5443 | R91: 11999.15 | T91: 44968 | U91: 11999.15 | AR91: 44674 | AS91: 521717.8
A92: DL | B92: 33927.686 | C92: 21822.575 | D92: 5426.5782 | E92: 2698.5746 | F92: 3979.9587 | M92: 44975 | N92: 627.02671 | O92: 909.05289 | P92: 1803.1336 | Q92: 8793.8995 | R92: 12133.113 | T92: 44975 | U92: 12133.113 | AR92: 44681 | AS92: 519403.17
A93: MD | B93: 37856.131 | C93: 25336.28 | D93: 5703.3547 | E93: 2817.6357 | F93: 3998.8607 | M93: 44982 | N93: 627.12999 | O93: 917.64342 | P93: 1820.1647 | Q93: 8882.0414 | R93: 12246.98 | T93: 44982 | U93: 12246.98 | AR93: May
A94: NJ | B94: 103317.78 | C94: 56066.417 | D94: 34517.117 | E94: 7071.8417 | F94: 5662.4037 | L94: Mar | M94: 44989 | N94: 651.93906 | O94: 926.31985 | P94: 1837.3663 | Q94: 8971.0038 | R94: 12386.629 | T94: 44989 | U94: 12386.629 | AR94: 44688 | AS94: 559376.65
A95: NY | B95: 189075.66 | C95: 134185.82 | D95: 27694.463 | E95: 15215.952 | F95: 11979.424 | M95: 44996 | N95: 604.40837 | O95: 935.08305 | P95: 1854.7399 | Q95: 7964.9349 | R95: 11359.166 | T95: 44996 | U95: 11359.166 | AR95: 44695 | AS95: 573636.61
A96: PA | B96: 92015.077 | C96: 50909.768 | D96: 11021.502 | E96: 19989.607 | F96: 10094.201 | M96: 45003 | N96: 606.84213 | O96: 716.3937 | P96: 1619.4648 | Q96: 8384.3761 | R96: 11327.077 | T96: 45003 | U96: 11327.077 | AR96: 44702 | AS96: 577358.97
A97: Grand Total | B97: 2034245.4 | C97: 1305423.2 | D97: 301546.63 | E97: 209563.46 | F97: 217712.03 | M97: 45010 | N97: 572.28533 | O97: 700.30362 | P97: 1508.2482 | Q97: 8706.0742 | R97: 11486.911 | T97: 45010 | U97: 11486.911 | AR97: 44709 | AS97: 580713.64
L98: Apr | M98: 45017 | N98: 506.77589 | O98: 704.53125 | P98: 1459.1251 | Q98: 8959.633 | R98: 11630.065 | T98: 45017 | U98: 11630.065 | AR98: Jun
M99: 45024 | N99: 540.67968 | O99: 603.71338 | P99: 1441.1136 | Q99: 9165.7779 | R99: 11751.285 | T99: 45024 | U99: 11751.285 | AR99: 44716 | AS99: 607176.22
M100: 45031 | N100: 593.07027 | O100: 598.0642 | P100: 1438.7233 | Q100: 9339.0197 | R100: 11968.877 | T100: 45031 | U100: 11968.877 | AR100: 44723 | AS100: 610645.58
M101: 45038 | N101: 652.20956 | O101: 601.97621 | P101: 1444.2098 | Q101: 9489.5187 | R101: 12187.914 | T101: 45038 | U101: 12187.914 | AR101: 44730 | AS101: 606529.57
M102: 45045 | N102: 717.41374 | O102: 606.88911 | P102: 1453.7016 | Q102: 9624.3901 | R102: 12402.394 | T102: 45045 | U102: 12402.394 | AR102: 44737 | AS102: 608646.82
L103: May | M103: 45052 | N103: 789.15344 | O103: 611.94731 | P103: 1465.2634 | Q103: 9748.6173 | R103: 12614.981 | T103: 45052 | U103: 12614.981 | AR103: Jul
M104: 45059 | N104: 868.06861 | O104: 617.06572 | P104: 1477.9285 | Q104: 9865.6918 | R104: 12828.755 | T104: 45059 | U104: 12828.755 | AR104: 44744 | AS104: 620246.05
M105: 45066 | N105: 954.87546 | O105: 622.23627 | P105: 1491.2139 | Q105: 9978.0606 | R105: 13046.386 | T105: 45066 | U105: 13046.386 | AR105: 44751 | AS105: 624049.07
M106: 45073 | N106: 1050.363 | O106: 627.45862 | P106: 1504.8792 | Q106: 10087.439 | R106: 13270.14 | T106: 45073 | U106: 13270.14 | AR106: 44758 | AS106: 638135.95
L107: Jun | M107: 45080 | N107: 1155.3993 | O107: 632.7332 | P107: 1518.8045 | Q107: 10195.033 | R107: 13501.97 | T107: 45080 | U107: 13501.97 | AR107: 44765 | AS107: 642278.2
M108: 45087 | N108: 1270.9392 | O108: 638.43922 | P108: 1533.3516 | Q108: 10301.686 | R108: 13744.416 | T108: 45087 | U108: 13744.416 | AR108: 44772 | AS108: 645908.05
M109: 45094 | N109: 1398.0332 | O109: 644.31148 | P109: 1548.3646 | Q109: 10407.995 | R109: 13998.704 | T109: 45094 | U109: 13998.704 | AR109: Aug
M110: 45101 | N110: 1537.8365 | O110: 727.82087 | P110: 1437.2768 | Q110: 10514.38 | R110: 14217.314 | T110: 45101 | U110: 14217.314 | AR110: 44779 | AS110: 622466.52
L111: Jul | M111: 45108 | N111: 1691.6201 | O111: 4498.3441 | P111: 1388.3639 | Q111: 10621.137 | R111: 18199.465 | T111: 45108 | U111: 18199.465 | AR111: 44786 | AS111: 606167.34
M112: 45115 | N112: 1860.7821 | O112: 4877.4225 | P112: 1370.6047 | Q112: 10728.477 | R112: 18837.287 | T112: 45115 | U112: 18837.287 | AR112: 44793 | AS112: 594160.38
M113: 45122 | N113: 2046.8603 | O113: 7149.1487 | P113: 1368.4893 | Q113: 10836.552 | R113: 21401.051 | T113: 45122 | U113: 21401.051 | AR113: 44800 | AS113: 597797.34
M114: 45129 | N114: 2251.5464 | O114: 7376.3213 | P114: 1374.2634 | Q114: 10945.471 | R114: 21947.602 | T114: 45129 | U114: 21947.602 | AR114: Sep
M115: 45136 | N115: 2476.701 | O115: 7399.0386 | P115: 1384.0507 | Q115: 11055.313 | R115: 22315.104 | T115: 45136 | U115: 22315.104 | AR115: 44807 | AS115: 578633.56
L116: Aug | M116: 45143 | N116: 4946.1525 | O116: 7401.3103 | P116: 1395.9136 | Q116: 11166.138 | R116: 24909.514 | T116: 45143 | U116: 24909.514 | AR116: 44814 | AS116: 561286.46
M117: 45150 | N117: 5514.8124 | O117: 7401.5375 | P117: 1408.8838 | Q117: 11277.989 | R117: 25603.223 | T117: 45150 | U117: 25603.223 | AR117: 44821 | AS117: 579972.48
M118: 45157 | N118: 5614.1492 | O118: 7401.5602 | P118: 1422.4783 | Q118: 11390.902 | R118: 25829.089 | T118: 45157 | U118: 25829.089 | AR118: 44828 | AS118: 579840.29
M119: 45164 | N119: 5348.9747 | O119: 3798.0522 | P119: 1436.4558 | Q119: 11504.904 | R119: 22088.386 | T119: 45164 | U119: 22088.386 | AR119: Oct
L120: Sep | M120: 45171 | N120: 5079.5575 | O120: 3443.4459 | P120: 1450.6968 | Q120: 11620.018 | R120: 21593.718 | T120: 45171 | U120: 21593.718 | AR120: 44835 | AS120: 532332.69
M121: 45178 | N121: 4350.4186 | O121: 1201.4806 | P121: 1465.142 | Q121: 11736.263 | R121: 18753.305 | T121: 45178 | U121: 18753.305 | AR121: 44842 | AS121: 500032.13
M122: 45185 | N122: 3893.2584 | O122: 985.85545 | P122: 1479.7625 | Q122: 11853.658 | R122: 18212.534 | T122: 45185 | U122: 18212.534 | AR122: 44849 | AS122: 489406.72
M123: 45192 | N123: 3501.7208 | O123: 972.95001 | P123: 1676.4723 | Q123: 11083.187 | R123: 17234.33 | T123: 45192 | U123: 17234.33 | AR123: 44856 | AS123: 488719.35
M124: 45199 | N124: 3151.3275 | O124: 980.40311 | P124: 1784.193 | Q124: 10571.714 | R124: 16487.637 | T124: 45199 | U124: 16487.637 | AR124: 44863 | AS124: 489294.28
...

Sheet Models training data
A1: train | B1: 1
W2: LN_Spend+20% Average
A3: State | B3: Date | C3: Sum of ln_facebook_spend+20%avg | D3: Sum of ln_youtube_spend+20%avg | E3: Sum of ln_radio_spend+20%avg | F3: Sum of ln_tv_spend+20%avg | G3: Sum of dum_pa | H3: Sum of dum_ny | I3: Sum of dum_nj | J3: Sum of dum_md | K3: Sum of dum_dl | L3: Sum of month_6_9_10_11_12 | M3: Sum of momth_1_2_3_4_5 | N3: Sum of count | O3: Sum of ln_sales | P3: Sum of sales | X3: avg spend | Y3: 20% spend
A4: CT | B4: 44562 | C4: 4.9097428 | D4: 5.1082367 | E4: 5.7203514 | F4: 7.3173497 | G4: 0 | H4: 0 | I4: 0 | J4: 0 | K4: 0 | L4: 0 | M4: 0 | N4: 1 | O4: 11.252593 | P4: 77079.506 | R4: NOTES: | W4: tv_spend | X4: =AVERAGE(Z13:Z768) -> 1456.0337 | Y4: =X4*0.2 -> 291.20673
B5: 44569 | C5: 4.8264038 | D5: 5.1403673 | E5: 5.7398318 | F5: 7.329377 | G5: 0 | H5: 0 | I5: 0 | J5: 0 | K5: 0 | L5: 0 | M5: 0 | N5: 2 | O5: 11.248505 | P5: 76765.045 | W5: radio_spend | X5: =AVERAGE(Y13:Y768) -> 325.06043 | Y5: =X5*0.2 -> 65.012086 | BO5: BEST MODEL (has the highest Adjusted R^2
B6: 44576 | C6: 4.90642 | D6: 5.1760847 | E6: 5.7692958 | F6: 7.3500829 | G6: 0 | H6: 0 | I6: 0 | J6: 0 | K6: 0 | L6: 0 | M6: 0 | N6: 3 | O6: 11.265279 | P6: 78063.605 | R6: Why do we include dummy variables? | W6: youtube_spend | X6: =AVERAGE(X13:X768) -> 226.89242 | Y6: =X6*0.2 -> 45.378484
B7: 44583 | C7: 4.8639956 | D7: 5.2125578 | E7: 5.8038603 | F7: 7.3769737 | G7: 0 | H7: 0 | I7: 0 | J7: 0 | K7: 0 | L7: 0 | M7: 0 | N7: 4 | O7: 11.268033 | P7: 78278.861 | R7: **we include dummy variable when we need a numerical | W7: facebook_spend | X7: =AVERAGE(W13:W768) -> 248.01717 | Y7: =X7*0.2 -> 49.603434 | AG7: MODEL 1: LINEAR TREND, WITH SEASONALITY, 11 DUMMIES | AW7: MODEL 2: LINEAR TREND, SEASONALITY, STATE DUMMIES | BN7: MODEL 3: LINEAR TREND, SEASONALITY, 5 STATE DUMMIES, Y=LN_SALES | CD7: MODEL 4: QUADRATIC TREND, SEASONALITY, 5 STATE DUMMIES, Y=SALES | CT7: MODEL 5: QUADRATIC TREND, SEASONALITY, 5 STATE DUMMIES, Y=LN_SALES | DJ7: MODEL 6: LN_COUNT, SEASONALITY, Y=SALES | DZ7: MODEL 7: LN_COUNT, SEASONALITY, Y=LN_SALES | EP7: MODEL 8: BEST PREVIOUS MODEL + SPENDS | FF7: MODEL 9: BEST PREVIOUS MODELS + LN_SPENDS+20% AVG
B8: 44590 | C8: 4.8541942 | D8: 5.2495031 | E8: 5.8410931 | F8: 7.4082487 | G8: 0 | H8: 0 | I8: 0 | J8: 0 | K8: 0 | L8: 0 | M8: 0 | N8: 5 | O8: 11.274852 | P8: 78814.469 | R8: value to represent categorical data within a statisitcal | AG8: SUMMARY OUTPUT | AW8: SUMMARY OUTPUT | BN8: SUMMARY OUTPUT | CD8: SUMMARY OUTPUT | CT8: SUMMARY OUTPUT | DJ8: SUMMARY OUTPUT | DZ8: SUMMARY OUTPUT | EP8: SUMMARY OUTPUT | FF8: SUMMARY OUTPUT
B9: 44597 | C9: 5.0372731 | D9: 5.2868833 | E9: 5.8797995 | F9: 7.442634 | G9: 0 | H9: 0 | I9: 0 | J9: 0 | K9: 0 | L9: 0 | M9: 0 | N9: 6 | O9: 11.29874 | P9: 80719.856 | R9: model. They are usually binary and take on a value of 1 or 0 | AK9: **note: | BB9: **note: | BS9: **note | CJ9: **note | CY9: **note | ET9: **note | FI9: **note
B10: 44604 | C10: 5.1023222 | D10: 5.3246846 | E10: 5.9193945 | F10: 7.4792407 | G10: 0 | H10: 0 | I10: 0 | J10: 0 | K10: 0 | L10: 0 | M10: 0 | N10: 7 | O10: 11.313352 | P10: 81908.017 | R10: dummies help to heighten accuracy and helps the computer | U10: train | V10: 1 | AG10: Regression Statistics | AK10: dropped month 7 to avoid perfect collinearity | AW10: Regression Statistics | BB10: dropped months 7 & 8 | BN10: Regression Statistics | BS10: Y=Ln_sales | CD10: Regression Statistics | CJ10: dropped months 6,7,8,9 | CT10: Regression Statistics | CY10: months 6,7,8,9 still dropped | DJ10: Regression Statistics | DZ10: Regression Statistics | EP10: Regression Statistics | ET10: our best previous model was 3 (lowest adj. R^2 | FF10: Regression Statistics | FI10: our best previous model was 3 (lowest adj. R^2
B11: 44611 | C11: 4.9623807 | D11: 5.3628958 | E11: 5.95959 | F11: 7.517454 | G11: 0 | H11: 0 | I11: 0 | J11: 0 | K11: 0 | L11: 0 | M11: 0 | N11: 8 | O11: 11.306869 | P11: 81378.715 | R11: read the data in an easier fashion. | AG11: Multiple R | AH11: 0.49073958 | AK11: month 8 has a high p-value of 49% | AW11: Multiple R | AX11: 0.92546095 | BB11: dropped CT state to avoid perfect collinearity | BN11: Multiple R | BO11: 0.92691021 | BS11: Months 7&8 are still dropped | CD11: Multiple R | CE11: 0.91687958 | CJ11: included count^2 | CT11: Multiple R | CU11: 0.92108119 | CY11: same as model 4, using LN_SALES | DJ11: Multiple R | DK11: 0.91758421 | DZ11: Multiple R | EA11: 0.92168229 | EP11: Multiple R | EQ11: 0.93135761 | ET11: to create this model, Y=LN_sales | FF11: Multiple R | FG11: 0.97774493 | FI11: to create this model, Y=LN_sales
B12: 44618 | C12: 5.1650989 | D12: 5.4015056 | E12: 6.0002417 | F12: 7.5568505 | G12: 0 | H12: 0 | I12: 0 | J12: 0 | K12: 0 | L12: 0 | M12: 0 | N12: 9 | O12: 11.335284 | P12: 83724.296 | U12: State | V12: Date | W12: Sum of Facebook_spend_ | X12: Sum of YouTube_spend | Y12: Sum of Radio_Spend | Z12: Sum of TV_Spend | AG12: R Square | AH12: 0.24082533 | AW12: R Square | AX12: 0.85647797 | BN12: R Square | BO12: 0.85916254 | CD12: R Square | CE12: 0.84066817 | CJ12: 5 state dummies | CT12: R Square | CU12: 0.84839056 | CY12: as Y instead for quadratic trend | DJ12: R Square | DK12: 0.84196078 | DZ12: R Square | EA12: 0.84949825 | EP12: R Square | EQ12: 0.867427 | ET12: included our spends | FF12: R Square | FG12: 0.95598516 | FI12: included our spends but with a 20%+avg
B13: 44625 | C13: 5.0885347 | D13: 5.4405028 | E13: 6.0412746 | F13: 7.5971389 | G13: 0 | H13: 0 | I13: 0 | J13: 0 | K13: 0 | L13: 0 | M13: 0 | N13: 10 | O13: 11.335742 | P13: 83762.625 | U13: CT | V13: 44562 | W13: 86.001096 | X13: 120 | Y13: 240 | Z13: 1215 | AG13: Adjusted R Square | AH13: 0.2285641 | AW13: Adjusted R Square | AX13: 0.85337059 | BN13: Adjusted R Square | BO13: 0.85611329 | CD13: Adjusted R Square | CE13: 0.83743847 | CT13: Adjusted R Square | CU13: 0.8453174 | DJ13: Adjusted R Square | DK13: 0.83897489 | DZ13: Adjusted R Square | EA13: 0.84665476 | EM13: R^2 went up from Model | EO13: <-------------- | EP13: Adjusted R Square | EQ13: 0.86528584 | ET13: combined included months into new columns | FF13: Adjusted R Square | FG13: 0.95527428 | FI13: combined included months into new columns
B14: 44632 | C14: 5.1405758 | D14: 5.4798764 | E14: 6.0826473 | F14: 7.6381188 | G14: 0 | H14: 0 | I14: 0 | J14: 0 | K14: 0 | L14: 0 | M14: 0 | N14: 11 | O14: 11.348588 | P14: 84845.538 | R14: Why do we include our variables in an LN version? | V14: 44569 | W14: 75.158057 | X14: 125.4 | Y14: 246 | Z14: 1233.225 | AG14: Standard Error | AH14: 17386.422 | AW14: Standard Error | AX14: 7580.0285 | BN14: Standard Error | BO14: 0.08171165 | CD14: Standard Error | CE14: 7981.2181 | CT14: Standard Error | CU14: 0.084721644 | DJ14: Standard Error | DK14: 7943.4122 | DZ14: Standard Error | EA14: 0.084354602 | EM14: 3 when including spends | EP14: Standard Error | EQ14: 0.079064268 | ET14: in order to fit into regression | FF14: Standard Error | FG14: 0.045556704 | FI14: in order to fit into regression
B15: 44639 | C15: 5.2291112 | D15: 5.5196152 | E15: 6.1243346 | F15: 7.6796514 | G15: 0 | H15: 0 | I15: 0 | J15: 0 | K15: 0 | L15: 0 | M15: 0 | N15: 12 | O15: 11.364496 | P15: 86206.124 | R15: The natural log helps make our data normally distributed, stabilizing | V15: 44576 | W15: 85.551266 | X15: 131.61 | Y15: 255.3 | Z15: 1265.1187 | AG15: Observations | AH15: 756 | AW15: Observations | AX15: 756 | BN15: Observations | BO15: 756 | CD15: Observations | CE15: 756 | CT15: Observations | CU15: 756 | DJ15: Observations | DK15: 756 | DZ15: Observations | EA15: 756 | EP15: Observations | EQ15: 756 | FF15: Observations | FG15: 756
B16: 44646 | C16: 5.2628489 | D16: 5.5597081 | E16: 6.1663189 | F16: 7.7216399 | G16: 0 | H16: 0 | I16: 0 | J16: 0 | K16: 0 | L16: 0 | M16: 0 | N16: 13 | O16: 11.375131 | P16: 87127.754 | R16: variance, and transforming non-linear relationships into linear ones. | V16: 44583 | W16: 79.937326 | X16: 138.1845 | Y16: 266.565 | Z16: 1307.5374
B17: 44653 | C17: 5.2783042 | D17: 5.5710407 | E17: 6.1910905 | F17: 7.7528325 | G17: 0 | H17: 0 | I17: 0 | J17: 0 | K17: 0 | L17: 0 | M17: 0 | N17: 14 | O17: 11.380047 | P17: 87557.174 | R17: It also heps provide more accurate MAPEs compared to other models. | V17: 44590 | W17: 78.673846 | X17: 145.09313 | Y17: 279.14325 | Z17: 1358.3282 | AG17: ANOVA | AW17: ANOVA | BN17: ANOVA | CD17: ANOVA | CT17: ANOVA | DJ17: ANOVA | DZ17: ANOVA | EP17: ANOVA | FF17: ANOVA
B18: 44660 | C18: 5.3449476 | D18: 5.5795875 | E18: 6.2076431 | F18: 7.7768786 | G18: 0 | H18: 0 | I18: 0 | J18: 0 | K18: 0 | L18: 0 | M18: 0 | N18: 15 | O18: 11.388401 | P18: 88291.705 | R18: ** you can see in the following models, when we use "SALES" as our | V18: 44597 | W18: 104.44593 | X18: 152.34772 | Y18: 292.72541 | Z18: 1416.0344 | AH18: df | AI18: SS | AJ18: MS | AK18: F | AL18: Significance F | AX18: df | AY18: SS | AZ18: MS | BA18: F | BB18: Significance F | BO18: df | BP18: SS | BQ18: MS | BR18: F | BS18: Significance F | CE18: df | CF18: SS | CG18: MS | CH18: F | CI18: Significance F | CU18: df | CV18: SS | CW18: MS | CX18: F | CY18: Significance F | DK18: df | DL18: SS | DM18: MS | DN18: F | DO18: Significance F | EA18: df | EB18: SS | EC18: MS | ED18: F | EE18: Significance F | EQ18: df | ER18: SS | ES18: MS | ET18: F | EU18: Significance F | FG18: df | FH18: SS | FI18: MS | FJ18: F | FK18: Significance F
B19: 44667 | C19: 5.4180003 | D19: 4.7646855 | E19: 5.8179412 | F19: 7.5628587 | G19: 0 | H19: 0 | I19: 0 | J19: 0 | K19: 0 | L19: 0 | M19: 0 | N19: 16 | O19: 11.274425 | P19: 78780.832 | R19: Y compared to "LN_SALES", our mapes are higher, meaning they are not | V19: 44604 | W19: 114.79982 | X19: 159.9651 | Y19: 307.17418 | Z19: 1479.6889 | AG19: Regression | AH19: 12 | AI19: 7.1247514e+10 | AJ19: 5.9372928e+09 | AK19: 19.641201 | AL19: 1.82863e-37 | AW19: Regression | AX19: 16 | AY19: 2.5338665e+11 | AZ19: 1.5836666e+10 | BA19: 275.6272 | BB19: 0 | BN19: Regression | BO19: 16 | BP19: 30.100212 | BQ19: 1.8812633 | BR19: 281.76148 | BS19: 0 | CD19: Regression | CE19: 15 | CF19: 2.4870937e+11 | CG19: 1.6580625e+10 | CH19: 260.29302 | CI19: 6.5020797e-283 | CT19: Regression | CU19: 15 | CV19: 29.722823 | CW19: 1.9815215 | CX19: 276.06417 | CY19: 7.1705832e-291 | DJ19: Regression | DK19: 14 | DL19: 2.4909178e+11 | DM19: 1.779227e+10 | DN19: 281.97926 | DO19: 1.8850437e-285 | DZ19: Regression | EA19: 14 | EB19: 29.76163 | EC19: 2.1258307 | ED19: 298.7522 | EE19: 2.7241555e-293 | EP19: Regression | EQ19: 12 | ER19: 30.389752 | ES19: 2.5324794 | ET19: 405.1216 | EU19: 0 | FF19: Regression | FG19: 12 | FH19: 33.492331 | FI19: 2.7910276 | FJ19: 1344.8057 | FK19: 0
B20: 44674 | C20: 5.4930573 | D20: 4.634991 | E20: 5.5479424 | F20: 7.381124 | G20: 0 | H20: 0 | I20: 0 | J20: 0 | K20: 0 | L20: 0 | M20: 0 | N20: 17 | O20: 11.237755 | P20: 75944.251 | R20: as accurate. | V20: 44611 | W20: 93.330244 | X20: 167.96336 | Y20: 322.43914 | Z20: 1548.6704 | AG20: Residual | AH20: 743 | AI20: 2.2459974e+11 | AJ20: 3.0228767e+08 | AW20: Residual | AX20: 739 | AY20: 4.2460599e+10 | AZ20: 57456832 | BN20: Residual | BO20: 739 | BP20: 4.9341506 | BQ20: 0.0066767938 | CD20: Residual | CE20: 740 | CF20: 4.7137883e+10 | CG20: 63699842 | CT20: Residual | CU20: 740 | CV20: 5.3115402 | CW20: 0.007177757 | DJ20: Residual | DK20: 741 | DL20: 4.6755468e+10 | DM20: 63097797 | DZ20: Residual | EA20: 741 | EB20: 5.2727329 | EC20: 0.0071156989 | EP20: Residual | EQ20: 743 | ER20: 4.6446108 | ES20: 0.0062511585 | FF20: Residual | FG20: 743 | FH20: 1.5420321 | FI20: 0.0020754133
B21: 44681 | C21: 5.5696315 | D21: 4.6260001 | E21: 5.3821268 | F21: 7.2321061 | G21: 0 | H21: 0 | I21: 0 | J21: 0 | K21: 0 | L21: 0 | M21: 0 | N21: 18 | O21: 11.226048 | P21: 75060.346 | V21: 44618 | W21: 125.45134 | X21: 176.36152 | Y21: 338.51422 | Z21: 1622.6018 | AG21: Total | AH21: 755 | AI21: 2.9584725e+11 | AW21: Total | AX21: 755 | AY21: 2.9584725e+11 | BN21: Total | BO21: 755 | BP21: 35.034363 | CD21: Total | CE21: 755 | CF21: 2.9584725e+11 | CT21: Total | CU21: 755 | CV21: 35.034363 | DJ21: Total | DK21: 755 | DL21: 2.9584725e+11 | DZ21: Total | EA21: 755 | EB21: 35.034363 | EP21: Total | EQ21: 755 | ER21: 35.034363 | FF21: Total | FG21: 755 | FH21: 35.034363
B22: 44688 | C22: 5.6476025 | D22: 4.6300797 | E22: 5.2904784 | F22: 7.1141755 | G22: 0 | H22: 0 | I22: 0 | J22: 0 | K22: 0 | L22: 0 | M22: 0 | N22: 19 | O22: 11.304637 | P22: 81197.238 | V22: 44625 | W22: 112.54865 | X22: 185.1796 | Y22: 355.4165 | Z22: 1701.2804
B23: 44695 | C23: 5.7268849 | D23: 4.6354927 | E23: 5.2443217 | F23: 7.0240287 | G23: 0 | H23: 0 | I23: 0 | J23: 0 | K23: 0 | L23: 0 | M23: 0 | N23: 20 | O23: 11.305623 | P23: 81277.367 | R23: How do our variables have an effect on sales? | V23: 44632 | W23: 121.21065 | X23: 194.43858 | Y23: 373.1756 | Z23: 1784.6283 | AH23: Coefficients | AI23: Standard Error | AJ23: t Stat | AK23: P-value | AL23: Lower 95% | AM23: Upper 95% | AN23: Lower 95.0% | AO23: Upper 95.0% | AX23: Coefficients | AY23: Standard Error | AZ23: t Stat | BA23: P-value | BB23: Lower 95% | BC23: Upper 95% | BD23: Lower 95.0% | BE23: Upper 95.0% | BO23: Coefficients | BP23: Standard Error | BQ23: t Stat | BR23: P-value | BS23: Lower 95% | BT23: Upper 95% | BU23: Lower 95.0% | BV23: Upper 95.0% | CE23: Coefficients | CF23: Standard Error | CG23: t Stat | CH23: P-value | CI23: Lower 95% | CJ23: Upper 95% | CK23: Lower 95.0% | CL23: Upper 95.0% | CU23: Coefficients | CV23: Standard Error | CW23: t Stat | CX23: P-value | CY23: Lower 95% | CZ23: Upper 95% | DA23: Lower 95.0% | DB23: Upper 95.0% | DK23: Coefficients | DL23: Standard Error | DM23: t Stat | DN23: P-value | DO23: Lower 95% | DP23: Upper 95% | DQ23: Lower 95.0% | DR23: Upper 95.0% | EA23: Coefficients | EB23: Standard Error | EC23: t Stat | ED23: P-value | EE23: Lower 95% | EF23: Upper 95% | EG23: Lower 95.0% | EH23: Upper 95.0% | EQ23: Coefficients | ER23: Standard Error | ES23: t Stat | ET23: P-value | EU23: Lower 95% | EV23: Upper 95% | EW23: Lower 95.0% | EX23: Upper 95.0% | FG23: Coefficients | FH23: Standard Error | FI23: t Stat | FJ23: P-value | FK23: Lower 95% | FL23: Upper 95% | FM23: Lower 95.0% | FN23: Upper 95.0%
B24: 44702 | C24: 5.8073981 | D24: 4.6410603 | E24: 5.2235363 | F24: 6.957384 | G24: 0 | H24: 0 | I24: 0 | J24: 0 | K24: 0 | L24: 0 | M24: 0 | N24: 21 | O24: 11.309282 | P24: 81575.353 | R24: We include our spends as a way to further help our accuracy in forecasting | V24: 44639 | W24: 137.02343 | X24: 204.16051 | Y24: 391.82853 | Z24: 1872.6585 | AG24: Intercept | AH24: 110221.95 | AI24: 2449.3505 | AJ24: 45.000481 | AK24: 2.1831117e-214 | AL24: 105413.48 | AM24: 115030.42 | AN24: 105413.48 | AO24: 115030.42 | AW24: Intercept | AX24: 101870.91 | AY24: 1052.6762 | AZ24: 96.773267 | BA24: 0 | BB24: 99804.319 | BC24: 103937.5 | BD24: 99804.319 | BE24: 103937.5 | BN24: Intercept | BO24: 11.507982 | BP24: 0.011347702 | BQ24: 1014.1244 | BR24: 0 | BS24: 11.485704 | BT24: 11.53026 | BU24: 11.485704 | BV24: 11.53026 | CD24: Intercept | CE24: 99191.043 | CF24: 1340.4582 | CG24: 73.997866 | CH24: 0 | CI24: 96559.489 | CJ24: 101822.6 | CK24: 96559.489 | CL24: 101822.6 | CT24: Intercept | CU24: 11.492466 | CV24: 0.014229134 | CW24: 807.6715 | CX24: 0 | CY24: 11.464531 | CZ24: 11.5204 | DA24: 11.464531 | DB24: 11.5204 | DJ24: Intercept | DK24: 101555.06 | DL24: 1550.6073 | DM24: 65.493736 | DN24: 0 | DO24: 98510.957 | DP24: 104599.17 | DQ24: 98510.957 | DR24: 104599.17 | DZ24: Intercept | EA24: 11.515151 | EB24: 0.016466584 | EC24: 699.30422 | ED24: 0 | EE24: 11.482825 | EF24: 11.547478 | EG24: 11.482825 | EH24: 11.547478 | EP24: Intercept | EQ24: 11.319305 | ER24: 0.015143158 | ES24: 747.48646 | ET24: 0 | EU24: 11.289577 | EV24: 11.349034 | EW24: 11.289577 | EX24: 11.349034 | FF24: Intercept | FG24: 9.8805996 | FH24: 0.044014716 | FI24: 224.484 | FJ24: 0 | FK24: 9.7941916 | FL24: 9.9670076 | FM24: 9.7941916 | FN24: 9.9670076
